Workbook

Sheet Sample
A1: Line in Master | B1: Company Name | C1: Year | D1: Reporting Period | E1: Reporting Year
A2: 10 | B2: AdvanSix Inc | C2: 2021 | D2: 2020 calendar year | E2: 2020
A3: 11 | B3: Aflac Inc | C3: 2020 | D3: 2018 | E3: 2018
A4: 12 | B4: Agilent Technologies Inc | C4: 2021 | D4: 11/1/2019 - 10/31/2020 | E4: 2020
A5: 14 | B5: AGNC Investment Corp | C5: 2021 | D5: 2020 calendar year | E5: 2020
A6: 15 | B6: AIG - American International Group Inc | C6: 2021 | D6: 2020 calendar year | E6: 2020
A7: 17 | B7: Akamai Technologies Inc | C7: 2021 | D7: 2020 calendar year | E7: 2020
A8: 21 | B8: Albemarle Corp | C8: 2020 | D8: 2019 calendar year | E8: 2019
A9: 27 | B9: Alliance Data Systems Corp | C9: 2020 | D9: 2020 calendar year | E9: 2020
A10: 28 | B10: Alliance Data Systems Corp | C10: 2019 | D10: 2019 calendar year | E10: 2019
A11: 29 | B11: Alliant Energy Corp | C11: 2020 | D11: 2020 | E11: 2020
A12: 30 | B12: Allison Transmission Holdings Inc | C12: 2021 | D12: 2020 | E12: 2020
A13: 35 | B13: Ameren Corp | C13: 2021 | D13: 2020 calendar year | E13: 2020
A14: 36 | B14: American Airlines Group Inc | C14: 2020 | D14: 2019 calendar year | E14: 2019
A15: 39 | B15: American Express Co | C15: 2020 | D15: 2019 calendar year | E15: 2019
A16: 40 | B16: American Homes 4 Rent | C16: 2021 | D16: 2020 calendar year | E16: 2020
A17: 42 | B17: American Tower Corp | C17: 2020 | D17: 2019 calendar year | E17: 2019
A18: 48 | B18: Amphenol Corp | C18: 2021 | D18: 2020 calendar year | E18: 2020
A19: 49 | B19: Amphenol Corp | C19: 2020 | D19: 2019 calendar year | E19: 2019
A20: 50 | B20: Amphenol Corp | C20: 2019 | D20: 2018 calendar year | E20: 2018
A21: 51 | B21: Amyris Inc | C21: 2021 | D21: 2020 calendar year | E21: 2020
A22: 52 | B22: Annaly Capital Management Inc | C22: 2021 | D22: 2020 calendar year | E22: 2020
A23: 53 | B23: Annaly Capital Management Inc | C23: 2020 | D23: 2019 calendar year | E23: 2019
A24: 55 | B24: Antero Midstream | C24: 2020 | D24: 2019 | E24: 2019
A25: 56 | B25: Antero Resources Corp | C25: 2020 | D25: 2019 | E25: 2019
A26: 58 | B26: Apache Corp | C26: 2020 | D26: 2019 calendar year | E26: 2019
A27: 69 | B27: Arconic Corp | C27: 2020 | D27: 2019 | E27: 2019
A28: 70 | B28: Arcosa, Inc | C28: 2021 | D28: 2020 | E28: 2020
A29: 71 | B29: Arena Pharmaceuticals Inc | C29: 2021 | D29: 2020 | E29: 2020
A30: 75 | B30: Ashland LLC | C30: 2021 | D30: 2019 | E30: 2019
A31: 78 | B31: Atkore International | C31: 2021 | D31: 10/1/2018-9/1/2020 | E31: 2020
A32: 82 | B32: AvalonBay Communities Inc | C32: 2021 | D32: 2020 calendar year | E32: 2020
A33: 89 | B33: Barnes Group Inc | C33: 2021 | D33: 2020 calendar year | E33: 2020
A34: 90 | B34: Baxter International Inc | C34: 2020 | D34: 2019 calendar year | E34: 2019
A35: 91 | B35: Becton Dickinson and Co | C35: 2021 | D35: 10/1/2019-9/30/2020 | E35: 2020
A36: 94 | B36: Berry Plastics Group Inc | C36: 2021 | D36: 2020 | E36: 2020
A37: 98 | B37: Blackbaud, Inc. | C37: 2021 | D37: 2020 calendar year | E37: 2020
A38: 102 | B38: Bloom Energy Corp | C38: 2021 | D38: 2020 | E38: 2020
A39: 119 | B39: Bunge Ltd | C39: 2021 | D39: 2020 calendar year | E39: 2020
A40: 120 | B40: Burlington Stores Inc | C40: 2020 | D40: 2020 fiscal year (1/30/202020-1/30/2021) | E40: 2021
A41: 121 | B41: Cabot Corp | C41: 2021 | D41: 2020 calendar year | E41: 2020
A42: 123 | B42: Cabot Oil & Gas Corp | C42: 2020 | D42: 2019 calendar year | E42: 2019
A43: 124 | B43: Calavo Growers Inc | C43: 2021 | D43: 2020 calendar year | E43: 2020
A44: 126 | B44: California Water Service Group | C44: 2021 | D44: 2020 calendar year | E44: 2020
A45: 127 | B45: Callon Petroleum Co | C45: 2021 | D45: 2020 calendar year | E45: 2020
A46: 128 | B46: Callon Petroleum Co | C46: 2020 | D46: 2019 calendar year | E46: 2019
A47: 130 | B47: Cardinal Health Inc | C47: 2021 | D47: 7/1/2019-6/30/2020 | E47: 2020
A48: 131 | B48: Carrier Global Corp | C48: 2020 | D48: 2019 calendar year | E48: 2019
A49: 132 | B49: Catalent Inc | C49: 2021 | D49: 7/1/2020-6/30/2021 | E49: 2021
A50: 133 | B50: Catalent Inc | C50: 2020 | D50: 7/1/2018-6/30/2019 | E50: 2019
... A53: 146 | B53: CH Robinson Worldwide Inc | C53: 2021 | D53: 2020 calendar year | E53: 2020
A54: 147 | B54: Charah Solutions Inc | C54: 2021 | D54: 2020 | E54: 2020
A55: 149 | B55: Chart Industries Inc | C55: 2021 | D55: 2020 | E55: 2020
A56: 152 | B56: Chemours Co/The | C56: 2020 | D56: 2019 calendar year | E56: 2019
A57: 154 | B57: Cheniere Energy Partners LP | C57: 2021 | D57: 2020 calendar year | E57: 2020
A58: 157 | B58: Chipotle Mexican Grill Inc | C58: 2021 | D58: 2020 calendar year | E58: 2020
A59: 164 | B59: Citigroup Inc (Citi) | C59: 2021 | D59: 2020 calendar year | E59: 2020
A60: 165 | B60: Citizens Financial Group Inc | C60: 2021 | D60: 2020 calendar year | E60: 2020
A61: 173 | B61: CNX Resources Corp | C61: 2021 | D61: 2020 calendar year | E61: 2020
A62: 176 | B62: Coeur Mining Inc | C62: 2020 | D62: 2019 | E62: 2019
A63: 178 | B63: Columbia Sportswear Co | C63: 2021 | D63: 2020 calendar year | E63: 2020
A64: 184 | B64: CommScope Holding Co Inc | C64: 2021 | D64: 2020 calendar year | E64: 2020
A65: 188 | B65: ConAgra Foods Inc | C65: 2020 | D65: 2020 Fiscal year (5/25/2019 - 5/25/2020) | E65: 2020
A66: 190 | B66: Conduent Inc. | C66: 2021 | D66: 2020 calendar year | E66: 2020
A67: 194 | B67: Cooper Cos Inc/The | C67: 2021 | D67: 10/1/2019-5/1/2020 | E67: 2020
A68: 195 | B68: Cooper-Standard Holdings Inc | C68: 2021 | D68: 2020 calendar year | E68: 2020
A69: 200 | B69: Crestwood Equity Partners LP | C69: 2021 | D69: 2020 calendar year | E69: 2020
A70: 201 | B70: Crestwood Equity Partners LP | C70: 2020 | D70: 2019 calendar year | E70: 2019
A71: 202 | B71: Crown Castle International Corp | C71: 2020 | D71: 2019 calendar year | E71: 2019
A72: 205 | B72: CSX Corp | C72: 2020 | D72: 2019 calendar year | E72: 2019
A73: 206 | B73: Cummins Inc. | C73: 2020 | D73: 2019 calendar year | E73: 2019
A74: 207 | B74: Cushman & Wakefield PLC | C74: 2021 | D74: 2020 calendar year | E74: 2020
... A102: 304 | B102: Flex Ltd | C102: 2020 | D102: 2019 calendar year | E102: 2019
A103: 306 | B103: Flowserve Corp | C103: 2020 | D103: 2019 | E103: 2019
A104: 310 | B104: Foot Locker Inc | C104: 2021 | D104: 2/3/2019-1/30/2021 | E104: 2021
A105: 325 | B105: General Mills Inc | C105: 2021 | D105: 5/30/2020-5/30/2021 | E105: 2021
A106: 326 | B106: General Mills Inc | C106: 2020 | D106: 5/21/2018-5/21/2019 | E106: 2019
A107: 328 | B107: General Motors Co (GM) | C107: 2021 | D107: 2020 | E107: 2020
A108: 329 | B108: General Motors Co (GM) | C108: 2020 | D108: 2019 | E108: 2019
A109: 330 | B109: General Motors Co (GM) | C109: 2019 | D109: 2018 | E109: 2018
A110: 333 | B110: Gentherm Inc | C110: 2021 | D110: 2020 calendar year | E110: 2020
A111: 341 | B111: Graphic Packaging Holding Co | C111: 2021 | D111: 2020 calendar year | E111: 2020
A112: 342 | B112: Graphic Packaging Holding Co | C112: 2020 | D112: 2019 calendar year | E112: 2019
A113: 343 | B113: Greenbrier Cos Inc/The | C113: 2020 | D113: 9/1/2018– 8/1/ 2020 | E113: 2020
A114: 344 | B114: Greif Inc. | C114: 2021 | D114: 11/1/2019 - 10/31/2020 | E114: 2020
A115: 346 | B115: Guess?, Inc. | C115: 2021 | D115: 2021 | E115: 2021
A116: 353 | B116: Harsco Corp | C116: 2021 | D116: 2020 calendar year | E116: 2020
A117: 354 | B117: Harsco Corp | C117: 2020 | D117: 2019 calendar year | E117: 2019
A118: 356 | B118: Hawaiian Electric Industries Inc | C118: 2021 | D118: 2020 | E118: 2020
A119: 358 | B119: Hawaiian Holdings Inc | C119: 2020 | D119: 2019 | E119: 2019
A120: 359 | B120: Healthpeak Properties Inc | C120: 2021 | D120: 2020 calendar year | E120: 2020
A121: 360 | B121: Healthpeak Properties Inc | C121: 2020 | D121: 2019 calendar year | E121: 2019
A122: 366 | B122: Hershey Co/The | C122: 2021 | D122: 2020 | E122: 2020
A123: 367 | B123: Hershey Co/The | C123: 2020 | D123: 2019 | E123: 2019
A124: 368 | B124: Hess Corp | C124: 2021 | D124: 2020 calendar year | E124: 2020
A125: 370 | B125: Hess Corp | C125: 2019 | D125: 2018 calendar year | E125: 2018
A126: 372 | B126: Hewlett Packard Enterprise Co | C126: 2020 | D126: 10/1/2018-10/31/2019 | E126: 2019
A127: 379 | B127: Hologic Inc | C127: 2021 | D127: 2020 | E127: 2020
A128: 381 | B128: Home Depot Inc/The | C128: 2020 | D128: 2/4/2019-2/2/2020 | E128: 2020
A129: 389 | B129: Howmet Aerospace Inc | C129: 2021 | D129: 2020 calendar year | E129: 2020
...

Sheet Compustat Links
A1: SASB Sample Name | B1: cusip | C1: Latest Annual datadate | D1: gvkey | E1: conm | F1: tic | G1: cik | H1: Name Match | I1: Checked? (1 if the SASB name does match with Compustat name)
A2: AdvanSix Inc | B2: 00773T101 | C2: 46022 | D2: 028070 | E2: ADVANSIX INC | F2: ASIX | G2: 1673985 | H2: =IF(E2=A2,1,"Check") -> 1 | I2: 1
A3: Aflac Inc | B3: 1055102 | C3: 46022 | D3: 001449 | E3: AFLAC INC | F3: AFL | G3: 4977 | H3: =IF(E3=A3,1,"Check") -> 1 | I3: 1
A4: Agilent Technologies Inc | B4: 00846U101 | C4: 45961 | D4: 126554 | E4: AGILENT TECHNOLOGIES INC | F4: A | G4: 1090872 | H4: =IF(E4=A4,1,"Check") -> 1 | I4: 1
A5: AGNC Investment Corp | B5: 00123Q104 | C5: 46022 | D5: 179889 | E5: AGNC INVESTMENT CORP | F5: AGNC | G5: 1423689 | H5: =IF(E5=A5,1,"Check") -> 1 | I5: 1
A6: AIG - American International Group Inc | B6: 26874784 | C6: 46022 | D6: 001487 | E6: AMERICAN INTERNATIONAL GROUP | F6: AIG | G6: 5272 | H6: =IF(E6=A6,1,"Check") -> Check | I6: 1
A7: Akamai Technologies Inc | B7: 00971T101 | C7: 46022 | D7: 125595 | E7: AKAMAI TECHNOLOGIES INC | F7: AKAM | G7: 1086222 | H7: =IF(E7=A7,1,"Check") -> 1 | I7: 1
A8: Albemarle Corp | B8: 12653101 | C8: 46022 | D8: 029751 | E8: ALBEMARLE CORP | F8: ALB | G8: 915913 | H8: =IF(E8=A8,1,"Check") -> 1 | I8: 1
A9: Alliance Data Systems Corp | B9: 18581108 | C9: 46022 | D9: 143974 | E9: BREAD FINANCIAL HOLDINGS INC | F9: BFH | G9: 1101215 | H9: =IF(E9=A9,1,"Check") -> Check | I9: Name change Alliance Data Systems Corporation -> Bread Financial in 2022
A10: Alliant Energy Corp | B10: 18802108 | C10: 46022 | D10: 011554 | E10: ALLIANT ENERGY CORP | F10: LNT | G10: 352541 | H10: =IF(E10=A10,1,"Check") -> 1 | I10: 1
A11: Allison Transmission Holdings Inc | B11: 01973R101 | C11: 46022 | D11: 177966 | E11: ALLISON TRANSMISSION HLDGS | F11: ALSN | G11: 1411207 | H11: =IF(E11=A11,1,"Check") -> Check | I11: 1
A12: Ameren Corp | B12: 23608102 | C12: 46022 | D12: 010860 | E12: AMEREN CORP | F12: AEE | G12: 1002910 | H12: =IF(E12=A12,1,"Check") -> 1 | I12: 1
A13: American Airlines Group Inc | B13: 02376R102 | C13: 46022 | D13: 001045 | E13: AMERICAN AIRLINES GROUP INC | F13: AAL | G13: 6201 | H13: =IF(E13=A13,1,"Check") -> 1 | I13: 1
A14: American Express Co | B14: 25816109 | C14: 46022 | D14: 001447 | E14: AMERICAN EXPRESS CO | F14: AXP | G14: 4962 | H14: =IF(E14=A14,1,"Check") -> 1 | I14: 1
A15: American Homes 4 Rent | B15: 02665T306 | C15: 46022 | D15: 017639 | E15: AMERICAN HOMES 4 RENT | F15: AMH | G15: 1562401 | H15: =IF(E15=A15,1,"Check") -> 1 | I15: 1
A16: American Tower Corp | B16: 03027X100 | C16: 46022 | D16: 105365 | E16: AMERICAN TOWER CORP | F16: AMT | G16: 1053507 | H16: =IF(E16=A16,1,"Check") -> 1 | I16: 1
A17: Amphenol Corp | B17: 32095101 | C17: 46022 | D17: 014282 | E17: AMPHENOL CORP | F17: APH | G17: 820313 | H17: =IF(E17=A17,1,"Check") -> 1 | I17: 1
A18: Amyris Inc | B18: 03236M200 | C18: 44926 | D18: 184717 | E18: AMYRIS INC | F18: AMRSQ | G18: 1365916 | H18: =IF(E18=A18,1,"Check") -> 1 | I18: 1
A19: Annaly Capital Management Inc | B19: 35710839 | C19: 46022 | D19: 065556 | E19: ANNALY CAPITAL MANAGEMENT | F19: NLY | G19: 1043219 | H19: =IF(E19=A19,1,"Check") -> Check | I19: 1
A20: Antero Midstream | B20: 03676B102 | C20: 46022 | D20: 031109 | E20: ANTERO MIDSTREAM CORP | F20: AM | G20: 1623925 | H20: =IF(E20=A20,1,"Check") -> Check | I20: name change - Antero Midstream became Antero Midstream Partners LP in 2014 after IPO
A21: Antero Resources Corp | B21: 03674X106 | C21: 46022 | D21: 018465 | E21: ANTERO RESOURCES CORP | F21: AR | G21: 1433270 | H21: =IF(E21=A21,1,"Check") -> 1 | I21: 1
A22: Apache Corp | B22: 03743Q108 | C22: 46022 | D22: 001678 | E22: APA CORP | F22: APA | G22: 1841666 | H22: =IF(E22=A22,1,"Check") -> Check | I22: Apache Corporation is a direct, wholly-owned subsidiary of APA
A23: Arconic Corp | B23: 03966V107 | C23: 44926 | D23: 035978 | E23: ARCONIC CORP | F23: ARNC | G23: 1790982 | H23: =IF(E23=A23,1,"Check") -> 1 | I23: 1
A24: Arcosa, Inc | B24: 39653100 | C24: 46022 | D24: 328795 | E24: ARCOSA INC | F24: ACA | G24: 1739445 | H24: =IF(E24=A24,1,"Check") -> Check | I24: 1
A25: Arena Pharmaceuticals Inc | B25: 40047607 | C25: 44561 | D25: 138122 | E25: ARENA PHARMACEUTICALS INC | F25: ARNA | G25: 1080709 | H25: =IF(E25=A25,1,"Check") -> 1 | I25: 1
A26: Ashland LLC | B26: 44186104 | C26: 45930 | D26: 001794 | E26: ASHLAND INC | F26: ASH | G26: 1674862 | H26: =IF(E26=A26,1,"Check") -> Check | I26: 1
A27: Atkore International | B27: 47649108 | C27: 45930 | D27: 027014 | E27: ATKORE INTERNATIONAL GROUP INC | F27: ATKR | G27: 1666138 | H27: Check | I27: 1
A28: AvalonBay Communities Inc | B28: 53484101 | C28: 46022 | D28: 029875 | E28: AVALONBAY COMMUNITIES INC | F28: AVB | G28: 915912 | H28: =IF(E28=A28,1,"Check") -> 1 | I28: 1
A29: Barnes Group Inc | B29: 67806109 | C29: 45291 | D29: 002049 | E29: BARNES GROUP INC | F29: B.2 | G29: 9984 | H29: =IF(E29=A29,1,"Check") -> 1 | I29: 1
A30: Baxter International Inc | B30: 71813109 | C30: 46022 | D30: 002086 | E30: BAXTER INTERNATIONAL INC | F30: BAX | G30: 10456 | H30: =IF(E30=A30,1,"Check") -> 1 | I30: 1
A31: Becton Dickinson and Co | B31: 75887109 | C31: 45930 | D31: 002111 | E31: BECTON DICKINSON & CO | F31: BDX | G31: 10795 | H31: =IF(E31=A31,1,"Check") -> Check | I31: 1
A32: Berry Plastics Group Inc | B32: 08579X101 | C32: 45657 | D32: 013431 | E32: BERRY CORP | F32: BRY | G32: 1705873 | H32: =IF(E32=A32,1,"Check") -> Check | I32: Name change - Berry Plastics Group, Inc. changed its name to Berry Global Group, Inc. in 2017
A33: Blackbaud, Inc. | B33: 09227Q100 | C33: 46022 | D33: 260893 | E33: BLACKBAUD INC | F33: BLKB | G33: 1280058 | H33: =IF(E33=A33,1,"Check") -> Check | I33: 1
A34: Bloom Energy Corp | B34: 93712107 | C34: 46022 | D34: 033668 | E34: BLOOM ENERGY CORP | F34: BE | G34: 1664703 | H34: =IF(E34=A34,1,"Check") -> 1 | I34: 1
A35: Bunge Ltd | B35: H11356104 | C35: 46022 | D35: 144435 | E35: BUNGE GLOBAL SA | F35: BG | G35: 1996862 | H35: =IF(E35=A35,1,"Check") -> Check | I35: Name change - Bunge Ltd changed to Bunge Global SA
A36: Burlington Stores Inc | B36: 122017106 | C36: 46053 | D36: 018675 | E36: BURLINGTON STORES INC | F36: BURL | G36: 1579298 | H36: =IF(E36=A36,1,"Check") -> 1 | I36: 1
A37: Cabot Corp | B37: 127055101 | C37: 45930 | D37: 002593 | E37: CABOT CORP | F37: CBT | G37: 16040 | H37: =IF(E37=A37,1,"Check") -> 1 | I37: 1
A38: Cabot Oil & Gas Corp | B38: 127097103 | C38: 46022 | D38: 020548 | E38: COTERRA ENERGY INC | F38: CTRA | G38: 858470 | H38: =IF(E38=A38,1,"Check") -> Check | I38: Name change - Cabot Oil & Gas changed to Coterra Energy
A39: Calavo Growers Inc | B39: 128246105 | C39: 45961 | D39: 147708 | E39: CALAVO GROWERS INC | F39: CVGW | G39: 1133470 | H39: =IF(E39=A39,1,"Check") -> 1 | I39: 1
A40: California Water Service Group | B40: 130788102 | C40: 46022 | D40: 002628 | E40: CALIFORNIA WATER SERVICE GP | F40: CWT | G40: 1035201 | H40: =IF(E40=A40,1,"Check") -> Check | I40: 1
A41: Callon Petroleum Co | B41: 13123X508 | C41: 45291 | D41: 015060 | E41: CALLON PETROLEUM CO/DE | F41: CPE | G41: 928022 | H41: =IF(E41=A41,1,"Check") -> Check | I41: 1
A42: Cardinal Health Inc | B42: 14149Y108 | C42: 45838 | D42: 002751 | E42: CARDINAL HEALTH INC | F42: CAH | G42: 721371 | H42: =IF(E42=A42,1,"Check") -> 1 | I42: 1
A43: Carrier Global Corp | B43: 14448C104 | C43: 46022 | D43: 036191 | E43: CARRIER GLOBAL CORP | F43: CARR | G43: 1783180 | H43: =IF(E43=A43,1,"Check") -> 1 | I43: 1
A44: Catalent Inc | B44: 148806102 | C44: 45473 | D44: 020228 | E44: CATALENT INC | F44: CTLT | G44: 1596783 | H44: =IF(E44=A44,1,"Check") -> 1 | I44: 1
A45: Caterpillar Inc | B45: 149123101 | C45: 46022 | D45: 002817 | E45: CATERPILLAR INC | F45: CAT | G45: 18230 | H45: =IF(E45=A45,1,"Check") -> 1 | I45: 1
A46: Century Communities Inc | B46: 156504300 | C46: 46022 | D46: 018004 | E46: CENTURY COMMUNITIES INC | F46: CCS | G46: 1576940 | H46: =IF(E46=A46,1,"Check") -> 1 | I46: 1
A47: CH Robinson Worldwide Inc | B47: 12541W209 | C47: 45657 | D47: 065609 | E47: C H ROBINSON WORLDWIDE INC | F47: CHRW | G47: 1043277 | H47: =IF(E47=A47,1,"Check") -> Check | I47: 1
A48: Charah Solutions Inc | B48: 15957P303 | C48: 44926 | D48: 033596 | E48: CHARAH SOLUTIONS | F48: CHRA | G48: 1730346 | H48: =IF(E48=A48,1,"Check") -> Check | I48: 1
A49: Chart Industries Inc | B49: 16115Q308 | C49: 45657 | D49: 025964 | E49: CHART INDUSTRIES INC | F49: GTLS | G49: 892553 | H49: =IF(E49=A49,1,"Check") -> 1 | I49: 1
A50: Chemours Co/The | B50: 163851108 | C50: 46022 | D50: 022741 | E50: CHEMOURS CO | F50: CC | G50: 1627223 | H50: =IF(E50=A50,1,"Check") -> Check | I50: 1
A51: Cheniere Energy Partners LP | B51: 16411Q101 | C51: 43830 | D51: 176914 | E51: CHENIERE ENERGY PARTNERS LP | F51: CQP | G51: 1383650 | H51: =IF(E51=A51,1,"Check") -> 1 | I51: 1
A52: Chipotle Mexican Grill Inc | B52: 169656105 | C52: 46022 | D52: 165914 | E52: CHIPOTLE MEXICAN GRILL INC | F52: CMG | G52: 1058090 | H52: =IF(E52=A52,1,"Check") -> 1 | I52: 1
A53: Citigroup Inc (Citi) | B53: 172967424 | C53: 46022 | D53: 003243 | E53: CITIGROUP INC | F53: C | G53: 831001 | H53: =IF(E53=A53,1,"Check") -> Check | I53: 1
A54: Citizens Financial Group Inc | B54: 174610105 | C54: 46022 | D54: 021825 | E54: CITIZENS FINANCIAL GROUP INC | F54: CFG | G54: 759944 | H54: =IF(E54=A54,1,"Check") -> 1 | I54: 1
A55: CNX Resources Corp | B55: 12653C108 | C55: 46022 | D55: 120093 | E55: CNX RESOURCES CORP | F55: CNX | G55: 1070412 | H55: =IF(E55=A55,1,"Check") -> 1 | I55: 1
A56: Coeur Mining Inc | B56: 192108504 | C56: 46022 | D56: 003153 | E56: COEUR MINING INC | F56: CDE | G56: 215466 | H56: =IF(E56=A56,1,"Check") -> 1 | I56: 1
A57: Columbia Sportswear Co | B57: 198516106 | C57: 46022 | D57: 105936 | E57: COLUMBIA SPORTSWEAR CO | F57: COLM | G57: 1050797 | H57: =IF(E57=A57,1,"Check") -> 1 | I57: 1
A58: CommScope Holding Co Inc | B58: 20337X109 | C58: 45657 | D58: 018036 | E58: VISTANCE NETWORKS INC | F58: VISN | G58: 1517228 | H58: =IF(E58=A58,1,"Check") -> Check | I58: Restructure - CommScope Holding Company, Inc. has restructured and became VISTANCE NETWORKS INC in 2026
A59: ConAgra Foods Inc | B59: 205887102 | C59: 45808 | D59: 003362 | E59: CONAGRA BRANDS INC | F59: CAG | G59: 23217 | H59: =IF(E59=A59,1,"Check") -> Check | I59: name change - In 2016, ConAgra changed its name to "Conagra Brands"
A60: Conduent Inc. | B60: 206787103 | C60: 46022 | D60: 028719 | E60: CONDUENT INC | F60: CNDT | G60: 1677703 | H60: =IF(E60=A60,1,"Check") -> Check | I60: 1
A61: Cooper Cos Inc/The | B61: 216648501 | C61: 45961 | D61: 003504 | E61: COOPER COS INC (THE) | F61: COO | G61: 711404 | H61: =IF(E61=A61,1,"Check") -> Check | I61: 1
A62: Cooper-Standard Holdings Inc | B62: 21676P103 | C62: 46022 | D62: 163765 | E62: COOPER-STANDARD HOLDINGS INC | F62: CPS | G62: 1320461 | H62: =IF(E62=A62,1,"Check") -> 1 | I62: 1
A63: Crestwood Equity Partners LP | B63: 226344208 | C63: 44926 | D63: 162894 | E63: CRESTWOOD EQUITY PARTNERS LP | F63: CEQP | G63: 1136352 | H63: =IF(E63=A63,1,"Check") -> 1 | I63: 1
A64: Crown Castle International Corp | B64: 22822V101 | C64: 46022 | D64: 113490 | E64: CROWN CASTLE INC | F64: CCI | G64: 1051470 | H64: =IF(E64=A64,1,"Check") -> Check | I64: name change - Crown Castle International Corp changed its name to Crown Castle Inc on August 1, 2022
A65: CSX Corp | B65: 126408103 | C65: 46022 | D65: 002574 | E65: CSX CORP | F65: CSX | G65: 277948 | H65: =IF(E65=A65,1,"Check") -> 1 | I65: 1
A66: Cummins Inc. | B66: 231021106 | C66: 46022 | D66: 003650 | E66: CUMMINS INC | F66: CMI | G66: 26172 | H66: =IF(E66=A66,1,"Check") -> Check | I66: 1
A67: Cushman & Wakefield PLC | B67: G2717C106 | C67: 46022 | D67: 033809 | E67: CUSHMAN & WAKEFIELD | F67: CWK | G67: 1628369 | H67: =IF(E67=A67,1,"Check") -> Check | I67: 1
A68: CVS Health Corp | B68: 126650100 | C68: 46022 | D68: 007241 | E68: CVS HEALTH CORP | F68: CVS | G68: 64803 | H68: =IF(E68=A68,1,"Check") -> 1 | I68: 1
A69: CyrusOne Inc | B69: 23283R100 | C69: 44561 | D69: 016116 | E69: CYRUSONE INC | F69: CONE | G69: 1553023 | H69: =IF(E69=A69,1,"Check") -> 1 | I69: 1
A70: Danaher Corp | B70: 235851102 | C70: 46022 | D70: 003735 | E70: DANAHER CORP | F70: DHR | G70: 313616 | H70: =IF(E70=A70,1,"Check") -> 1 | I70: 1
A71: Darling Ingredients Inc. | B71: 237266101 | C71: 45657 | D71: 030651 | E71: DARLING INGREDIENTS INC | F71: DAR | G71: 916540 | H71: =IF(E71=A71,1,"Check") -> Check | I71: 1
A72: Deere & Co. | B72: 244199105 | C72: 45961 | D72: 003835 | E72: DEERE & CO | F72: DE | G72: 315189 | H72: =IF(E72=A72,1,"Check") -> Check | I72: 1
A73: Devon Energy Corp | B73: 25179M103 | C73: 46022 | D73: 014934 | E73: DEVON ENERGY CORP | F73: DVN | G73: 1090012 | H73: =IF(E73=A73,1,"Check") -> 1 | I73: 1
A74: DigitalBridge Group Inc | B74: 25401T603 | C74: 45657 | D74: 183603 | E74: DIGITALBRIDGE GROUP INC | F74: DBRG | G74: 1679688 | H74: =IF(E74=A74,1,"Check") -> 1 | I74: 1
A75: Dominion Energy Inc | B75: 25746U109 | C75: 46022 | D75: 004029 | E75: DOMINION ENERGY INC | F75: D | G75: 715957 | H75: =IF(E75=A75,1,"Check") -> 1 | I75: 1
A76: Dow Inc | B76: 260557103 | C76: 46022 | D76: 034443 | E76: DOW INC | F76: DOW | G76: 1751788 | H76: =IF(E76=A76,1,"Check") -> 1 | I76: 1
A77: DuPont de Nemours Inc | B77: 26614N102 | C77: 46022 | D77: 004060 | E77: DUPONT DE NEMOURS INC | F77: DD | G77: 1666700 | H77: =IF(E77=A77,1,"Check") -> 1 | I77: 1
A78: Eagle Bulk Shipping Inc | B78: Y2187A150 | C78: 45291 | D78: 163685 | E78: EAGLE BULK SHIPPING INC | F78: EGLE.3 | G78: 1322439 | H78: =IF(E78=A78,1,"Check") -> 1 | I78: 1
A79: Ecolab Inc | B79: 278865100 | C79: 46022 | D79: 004213 | E79: ECOLAB INC | F79: ECL | G79: 31462 | H79: =IF(E79=A79,1,"Check") -> 1 | I79: 1
A80: eHealth Inc | B80: 28238P109 | C80: 45657 | D80: 174389 | E80: EHEALTH INC | F80: EHTH | G80: 1333493 | H80: =IF(E80=A80,1,"Check") -> 1 | I80: 1
A81: Energy Recovery | B81: 29270J100 | C81: 46022 | D81: 179738 | E81: ENERGY RECOVERY INC | F81: ERII | G81: 1421517 | H81: =IF(E81=A81,1,"Check") -> Check | I81: 1
A82: Envista Holdings Corp | B82: 29415F104 | C82: 46022 | D82: 035497 | E82: ENVISTA HOLDINGS CORP | F82: NVST | G82: 1757073 | H82: =IF(E82=A82,1,"Check") -> 1 | I82: 1
A83: Enviva | B83: 29415B103 | C83: 45291 | D83: 023296 | E83: ENVIVA INC | F83: EVVAQ | G83: 1592057 | H83: =IF(E83=A83,1,"Check") -> Check | I83: 1
A84: EQT Corp | B84: 26884L109 | C84: 46022 | D84: 004430 | E84: EQT CORP | F84: EQT | G84: 33213 | H84: =IF(E84=A84,1,"Check") -> 1 | I84: 1
A85: Equitrans Midstream Corp | B85: 294600101 | C85: 45291 | D85: 034337 | E85: EQUITRANS MID CORP | F85: ETRN | G85: 1747009 | H85: =IF(E85=A85,1,"Check") -> Check | I85: 1
A86: Essential Utilities Inc | B86: 29670G102 | C86: 45657 | D86: 008542 | E86: ESSENTIAL UTILITIES INC | F86: WTRG | G86: 78128 | H86: =IF(E86=A86,1,"Check") -> 1 | I86: 1
A87: Essex Property Trust Inc | B87: 297178105 | C87: 46022 | D87: 030293 | E87: ESSEX PROPERTY TRUST | F87: ESS | G87: 920522 | H87: =IF(E87=A87,1,"Check") -> Check | I87: 1
A88: Estee Lauder Cos Inc/The | B88: 518439104 | C88: 45838 | D88: 061567 | E88: ESTEE LAUDER COMPANIES INC | F88: EL | G88: 1001250 | H88: =IF(E88=A88,1,"Check") -> Check | I88: 1
A89: Exelon Corp | B89: 30161N101 | C89: 46022 | D89: 008539 | E89: EXELON CORP | F89: EXC | G89: 1109357 | H89: =IF(E89=A89,1,"Check") -> 1 | I89: 1
A90: FedEx Corp | B90: 31428X106 | C90: 45808 | D90: 004598 | E90: FEDEX CORP | F90: FDX | G90: 1048911 | H90: =IF(E90=A90,1,"Check") -> 1 | I90: 1
A91: Fifth Third Bancorp | B91: 316773100 | C91: 46022 | D91: 004640 | E91: FIFTH THIRD BANCORP | F91: FITB | G91: 35527 | H91: =IF(E91=A91,1,"Check") -> 1 | I91: 1
A92: Flex Ltd | B92: Y2573F102 | C92: 45747 | D92: 030170 | E92: FLEX LTD | F92: FLEX | G92: 866374 | H92: =IF(E92=A92,1,"Check") -> 1 | I92: 1
A93: Flowserve Corp | B93: 34354P105 | C93: 46022 | D93: 004108 | E93: FLOWSERVE CORP | F93: FLS | G93: 30625 | H93: =IF(E93=A93,1,"Check") -> 1 | I93: 1
A94: Foot Locker Inc | B94: 344849104 | C94: 45688 | D94: 011584 | E94: FOOT LOCKER INC | F94: FL | G94: 850209 | H94: =IF(E94=A94,1,"Check") -> 1 | I94: 1
A95: General Mills Inc | B95: 370334104 | C95: 45808 | D95: 005071 | E95: GENERAL MILLS INC | F95: GIS | G95: 40704 | H95: =IF(E95=A95,1,"Check") -> 1 | I95: 1
A96: General Motors Co (GM) | B96: 37045V100 | C96: 46022 | D96: 005073 | E96: GENERAL MOTORS CO | F96: GM | G96: 1467858 | H96: =IF(E96=A96,1,"Check") -> Check | I96: 1
A97: Gentherm Inc | B97: 37253A103 | C97: 46022 | D97: 028408 | E97: GENTHERM INC | F97: THRM | G97: 903129 | H97: =IF(E97=A97,1,"Check") -> 1 | I97: 1
A98: Graphic Packaging Holding Co | B98: 388689101 | C98: 46022 | D98: 025389 | E98: GRAPHIC PACKAGING HOLDING CO | F98: GPK | G98: 1408075 | H98: =IF(E98=A98,1,"Check") -> 1 | I98: 1
A99: Greenbrier Cos Inc/The | B99: 393657101 | C99: 45900 | D99: 030463 | E99: GREENBRIER COS INC (THE) | F99: GBX | G99: 923120 | H99: =IF(E99=A99,1,"Check") -> Check | I99: 1
A100: Greif Inc. | B100: 397624107 | C100: 45930 | D100: 005338 | E100: GREIF INC -CL A | F100: GEF | G100: 43920 | H100: =IF(E100=A100,1,"Check") -> Check | I100: 1
...

Sheet Compustat Controls
A1: lineinmaster | B1: SASB Sample Name | C1: reporting year | D1: cusip | E1: latestannualdatadate | F1: gvkey | G1: conm | H1: tic | I1: cik | J1: datadate | K1: at | L1: ceq | M1: che | N1: lt | O1: gp | P1: ni | Q1: sale | R1: csho | S1: prcc_f | T1: lnat | U1: roa | V1: lev | W1: gpm | X1: cash | Y1: loss | Z1: btm | AA1: Note
A2: 10 | B2: AdvanSix Inc | C2: 2020 | D2: 00773T101 | E2: 46022 | F2: 28070 | G2: ADVANSIX INC | H2: ASIX | I2: 1673985 | J2: 2020-12-31 | K2: 1263.407 | L2: 444.12299 | M2: 10.606 | N2: 819.284 | O2: 190.98801 | P2: 46.077 | Q2: 1157.917 | R2: 28.033001 | S2: 19.99 | T2: 7.1415672 | U2: 0.036470432 | V2: 0.64847195 | W2: 0.16494101 | X2: 0.008394761 | Y2: 0 | Z2: 0.79253942
A3: 11 | B3: Aflac Inc | C3: 2018 | D3: 1055102 | E3: 46022 | F3: 1449 | G3: AFLAC INC | H3: AFL | I3: 4977 | J3: 2018-12-31 | K3: 140406 | L3: 23462 | M3: 5530 | N3: 116944 | O3: 4338 | P3: 2920 | Q3: 21768 | R3: 755.28601 | S3: 45.560001 | T3: 11.852294 | U3: 0.020796832 | V3: 0.83289886 | W3: 0.19928335 | X3: 0.039385781 | Y3: 0 | Z3: 0.68182021
A4: 12 | B4: Agilent Technologies Inc | C4: 2020 | D4: 00846U101 | E4: 45961 | F4: 126554 | G4: AGILENT TECHNOLOGIES INC | H4: A | I4: 1090872 | J4: 2020-10-31 | K4: 9627 | L4: 4873 | M4: 1441 | N4: 4754 | O4: 3068 | P4: 719 | Q4: 5339 | R4: 306.198 | S4: 102.09 | T4: 9.172327 | U4: 0.074685782 | V4: 0.49381948 | W4: 0.57463944 | X4: 0.14968318 | Y4: 0 | Z4: 0.15588735
A5: 14 | B5: AGNC Investment Corp | C5: 2020 | D5: 00123Q104 | E5: 46022 | F5: 179889 | G5: AGNC INVESTMENT CORP | H5: AGNC | I5: 1423689 | J5: 2020-12-31 | K5: 81817 | L5: 9590 | M5: 2324 | N5: 70738 | O5: 2871 | P5: -266 | Q5: 2964 | R5: 539.46899 | S5: 15.6 | T5: 11.312241 | U5: -0.0032511582 | V5: 0.86458802 | W5: 0.96862346 | X5: 0.028404854 | Y5: 1 | Z5: 1.1395346
A6: 15 | B6: AIG - American International Group Inc | C6: 2020 | D6: 26874784 | E6: 46022 | F6: 1487 | G6: AMERICAN INTERNATIONAL GROUP | H6: AIG | I6: 5272 | J6: 2020-12-31 | K6: 586481 | L6: 65877 | M6: 31987 | N6: 519282 | O6: 6985 | P6: -5944 | Q6: 43358 | R6: 861.55798 | S6: 37.860001 | T6: 13.281896 | U6: -0.010135026 | V6: 0.88541996 | W6: 0.16110061 | X6: 0.054540556 | Y6: 1 | Z6: 2.0196154
A7: 17 | B7: Akamai Technologies Inc | C7: 2020 | D7: 00971T101 | E7: 46022 | F7: 125595 | G7: AKAMAI TECHNOLOGIES INC | H7: AKAM | I7: 1086222 | J7: 2020-12-31 | K7: 7764.1299 | L7: 4251.2959 | M7: 1098.073 | N7: 3512.834 | O7: 2385.7749 | P7: 557.05402 | Q7: 3198.1489 | R7: 162.71001 | S7: 104.99 | T7: 8.9572697 | U7: 0.071747124 | V7: 0.45244399 | W7: 0.74598616 | X7: 0.14142898 | Y7: 0 | Z7: 0.24886233
A8: 21 | B8: Albemarle Corp | C8: 2019 | D8: 12653101 | E8: 46022 | F8: 29751 | G8: ALBEMARLE CORP | H8: ALB | I8: 915913 | J8: 2019-12-31 | K8: 9860.8633 | L8: 3932.25 | M8: 613.10999 | N8: 5767.2832 | O8: 1472.962 | P8: 533.22803 | Q8: 3589.427 | R8: 106.04 | S8: 73.040001 | T8: 9.1963291 | U8: 0.054075189 | V8: 0.58486593 | W8: 0.41036132 | X8: 0.062176097 | Y8: 0 | Z8: 0.50770408
A9: 27 | B9: Alliance Data Systems Corp | C9: 2020 | D9: 18581108 | E9: 46022 | F9: 143974 | G9: BREAD FINANCIAL HOLDINGS INC | H9: BFH | I9: 1101215 | J9: 2020-12-31 | K9: 22547.1 | L9: 1521.6 | M9: 4146.2002 | N9: 21025.5 | O9: 2491.6001 | P9: 213.7 | Q9: 4521.3999 | R9: 49.700001 | S9: 74.099998 | T9: 10.023362 | U9: 0.0094779376 | V9: 0.93251461 | W9: 0.55106831 | X9: 0.18389063 | Y9: 0 | Z9: 0.41316727
A10: 28 | B10: Alliance Data Systems Corp | C10: 2019 | D10: 18581108 | E10: 46022 | F10: 143974 | G10: BREAD FINANCIAL HOLDINGS INC | H10: BFH | I10: 1101215 | J10: 2019-12-31 | K10: 26494.801 | L10: 1588.3 | M10: 4550.8999 | N10: 24906.5 | O10: 2967.6001 | P10: 278 | Q10: 5581.2998 | R10: 47.599998 | S10: 112.2 | T10: 10.184704 | U10: 0.010492625 | V10: 0.94005233 | W10: 0.53170413 | X10: 0.17176577 | Y10: 0 | Z10: 0.29739439
A11: 29 | B11: Alliant Energy Corp | C11: 2020 | D11: 18802108 | E11: 46022 | F11: 11554 | G11: ALLIANT ENERGY CORP | H11: LNT | I11: 352541 | J11: 2020-12-31 | K11: 17710 | L11: 5688 | M11: 54 | N11: 11822 | O11: 1348 | P11: 624 | Q11: 3416 | R11: 249.868 | S11: 51.529999 | T11: 9.7818851 | U11: 0.035234332 | V11: 0.66753244 | W11: 0.39461359 | X11: 0.0030491247 | Y11: 0 | Z11: 0.44176248
A12: 30 | B12: Allison Transmission Holdings Inc | C12: 2020 | D12: 01973R101 | E12: 46022 | F12: 177966 | G12: ALLISON TRANSMISSION HLDGS | H12: ALSN | I12: 1411207 | J12: 2020-12-31 | K12: 4477 | L12: 756 | M12: 310 | N12: 3721 | O12: 1151 | P12: 299 | Q12: 2081 | R12: 112.033 | S12: 43.130001 | T12: 8.4067087 | U12: 0.066785797 | V12: 0.83113694 | W12: 0.55309945 | X12: 0.069242798 | Y12: 0 | Z12: 0.1564575
A13: 35 | B13: Ameren Corp | C13: 2020 | D13: 23608102 | E13: 46022 | F13: 10860 | G13: AMEREN CORP | H13: AEE | I13: 1002910 | J13: 2020-12-31 | K13: 32030 | L13: 8938 | M13: 156 | N13: 22950 | O13: 2375 | P13: 871 | Q13: 5794 | R13: 253.3 | S13: 78.059998 | T13: 10.374428 | U13: 0.027193256 | V13: 0.71651578 | W13: 0.4099068 | X13: 0.0048704338 | Y13: 0 | Z13: 0.45203975
... A26: 58 | B26: Apache Corp | C26: 2019 | D26: 03743Q108 | E26: 46022 | F26: 1678 | G26: APA CORP | H26: APA | I26: 1841666 | J26: 2019-12-31 | K26: 18107 | L26: 3255 | M26: 247 | N26: 13087 | O26: 1520 | P26: -3553 | Q26: 6280 | R26: 376.06299 | S26: 25.59 | T26: 9.8040543 | U26: -0.19622245 | V26: 0.72275913 | W26: 0.24203822 | X26: 0.013641133 | Y26: 1 | Z26: 0.33823621
A27: 69 | B27: Arconic Corp | C27: 2019 | D27: 03966V107 | E27: 44926 | F27: 35978 | G27: ARCONIC CORP | H27: ARNC | I27: 1790982 | J27: 2019-12-31 | K27: 4741 | L27: 2714 | M27: 72 | N27: 2013 | O27: 1007 | P27: 225 | Q27: 7277 | R27: 109.02 | S27: 6.9200001 | T27: 8.4640036 | U27: 0.047458343 | V27: 0.42459396 | W27: 0.1383812 | X27: 0.015186669 | Y27: 0 | Z27: 3.5974734 | AA27: The company starts to trade in 2020 April, the shares outstanding in March 2019 is replaced as 109,021,376 (disclosed in its 2020 10-K https://www.sec.gov/Archives/edgar/data/1790982/000179098220000022/arconic10k.htm). The stock price is replaced as 6.92, the closing price of the first day of trade (April 1, 2020)
A28: 70 | B28: Arcosa, Inc | C28: 2020 | D28: 39653100 | E28: 46022 | F28: 328795 | G28: ARCOSA INC | H28: ACA | I28: 1739445 | J28: 2020-12-31 | K28: 2646.7 | L28: 1892.2 | M28: 95.800003 | N28: 754.5 | O28: 506.79999 | P28: 106.6 | Q28: 1935.6 | R28: 48.200001 | S28: 54.93 | T28: 7.8810687 | U28: 0.040276572 | V28: 0.28507197 | W28: 0.26183096 | X28: 0.03619602 | Y28: 0 | Z28: 0.71467793
A29: 71 | B29: Arena Pharmaceuticals Inc | C29: 2020 | D29: 40047607 | E29: 44561 | F29: 138122 | G29: ARENA PHARMACEUTICALS INC | H29: ARNA | I29: 1080709 | J29: 2020-12-31 | K29: 1190.72 | L29: 1080.469 | M29: 1104.041 | N29: 110.251 | O29: -422.78101 | P29: -404.73401 | Q29: 0.31900001 | R29: 58.611 | S29: 76.830002 | T29: 7.0823135 | U29: -0.33990696 | V29: 0.092591882 | W29: -1325.3323 | X29: 0.92720461 | Y29: 1 | Z29: 0.23993982
A30: 75 | B30: Ashland LLC | C30: 2019 | D30: 44186104 | E30: 45930 | F30: 1794 | G30: ASHLAND INC | H30: ASH | I30: 1674862 | J30: 2019-09-30 | K30: 7251 | L30: 3571 | M30: 256 | N30: 3680 | O30: 980 | P30: 505 | Q30: 2493 | R30: 60 | S30: 77.050003 | T30: 8.888895 | U30: 0.069645569 | V30: 0.50751621 | W30: 0.39310068 | X30: 0.035305474 | Y30: 0 | Z30: 0.7724421
A31: 78 | B31: Atkore International | C31: 2020 | D31: 47649108 | E31: 45930 | F31: 27014 | G31: ATKORE INTERNATIONAL GROUP INC | H31: ATKR | I31: 1666138 | J31: 2020-09-30 | K31: 1558.525 | L31: 378.41 | M31: 284.47101 | N31: 1180.115 | O31: 533.52197 | P31: 152.302 | Q31: 1765.421 | R31: 47.407001 | S31: 22.73 | T31: 7.3514953 | U31: 0.097721882 | V31: 0.75719988 | W31: 0.30220664 | X31: 0.18252578 | Y31: 0 | Z31: 0.35117266
A32: 82 | B32: AvalonBay Communities Inc | C32: 2020 | D32: 53484101 | E32: 46022 | F32: 29875 | G32: AVALONBAY COMMUNITIES INC | H32: AVB | I32: 915912 | J32: 2020-12-31 | K32: 19199.145 | L32: 10751.583 | M32: 313.53201 | N32: 8444.293 | O32: 776.86499 | P32: 827.63 | Q32: 2307.2981 | R32: 139.52699 | S32: 160.42999 | T32: 9.8626213 | U32: 0.043107651 | V32: 0.43982652 | W32: 0.33669901 | X32: 0.01633052 | Y32: 0 | Z32: 0.48031771
A33: 89 | B33: Barnes Group Inc | C33: 2020 | D33: 67806109 | E33: 45291 | F33: 2049 | G33: BARNES GROUP INC | H33: B.2 | I33: 9984 | J33: 2020-12-31 | K33: 2676.2261 | L33: 1382.677 | M33: 84.088997 | N33: 1293.549 | O33: 490.80899 | P33: 63.375 | Q33: 1124.391 | R33: 50.640999 | S33: 50.689999 | T33: 7.8921628 | U33: 0.023680735 | V33: 0.48334816 | W33: 0.43651095 | X33: 0.031420738 | Y33: 0 | Z33: 0.53863704
A34: 90 | B34: Baxter International Inc | C34: 2019 | D34: 71813109 | E34: 46022 | F34: 2086 | G34: BAXTER INTERNATIONAL INC | H34: BAX | I34: 10456 | J34: 2019-12-31 | K34: 18193 | L34: 7882 | M34: 3335 | N34: 10281 | O34: 5705 | P34: 1001 | Q34: 11362 | R34: 506.155 | S34: 83.620003 | T34: 9.8087921 | U34: 0.055021163 | V34: 0.56510746 | W34: 0.50211233 | X34: 0.18331227 | Y34: 0 | Z34: 0.18622704
A35: 91 | B35: Becton Dickinson and Co | C35: 2020 | D35: 75887109 | E35: 45930 | F35: 2111 | G35: BECTON DICKINSON & CO | H35: BDX | I35: 10795 | J35: 2020-09-30 | K35: 54012 | L35: 23763 | M35: 2937 | N35: 30247 | O35: 9875 | P35: 874 | Q35: 17117 | R35: 290.017 | S35: 232.67999 | T35: 10.896961 | U35: 0.01618159 | V35: 0.56000519 | W35: 0.57691187 | X35: 0.054376803 | Y35: 0 | Z35: 0.35214278
A36: 94 | B36: Berry Plastics Group Inc | C36: 2020 | D36: 08579X101 | E36: 45657 | F36: 13431 | G36: BERRY CORP | H36: BRY | I36: 1705873 | J36: 2020-12-31 | K36: 1419.8101 | L36: 714.03601 | M36: 80.556999 | N36: 705.77399 | O36: -12.098 | P36: -262.89499 | Q36: 523.83301 | R36: 79.929001 | S36: 3.6800001 | T36: 7.2582784 | U36: -0.18516208 | V36: 0.49709043 | W36: -0.023095146 | X36: 0.05673787 | Y36: 1 | Z36: 2.4275484
A37: 98 | B37: Blackbaud, Inc. | C37: 2020 | D37: 09227Q100 | E37: 46022 | F37: 260893 | G37: BLACKBAUD INC | H37: BLKB | I37: 1280058 | J37: 2020-12-31 | K37: 2044.734 | L37: 426.14999 | M37: 644.96899 | N37: 1618.584 | O37: 579.27399 | P37: 7.717 | Q37: 913.21899 | R37: 48.849998 | S37: 57.560001 | T37: 7.623023 | U37: 0.0037740851 | V37: 0.79158658 | W37: 0.63432097 | X37: 0.3154293 | Y37: 0 | Z37: 0.1515574
A38: 102 | B38: Bloom Energy Corp | C38: 2020 | D38: 93712107 | E38: 46022 | F38: 33668 | G38: BLOOM ENERGY CORP | H38: BE | I38: 1664703 | J38: 2020-12-31 | K38: 1454.387 | L38: 78.823997 | M38: 299.41699 | N38: 1312.991 | O38: 218.07201 | P38: -157.55299 | Q38: 794.24701 | R38: 168.00301 | S38: 28.66 | T38: 7.2823396 | U38: -0.10832949 | V38: 0.90277964 | W38: 0.27456447 | X38: 0.20587161 | Y38: 1 | Z38: 0.016370624
A39: 119 | B39: Bunge Ltd | C39: 2020 | D39: H11356104 | E39: 46022 | F39: 144435 | G39: BUNGE GLOBAL SA | H39: BG | I39: 1996862 | J39: 2020-12-31 | K39: 23655 | L39: 5379 | M39: 1544 | N39: 17035 | O39: 3169 | P39: 1145 | Q39: 41355 | R39: 139.78999 | S39: 65.580002 | T39: 10.07133 | U39: 0.048404142 | V39: 0.72014374 | W39: 0.076629184 | X39: 0.065271616 | Y39: 0 | Z39: 0.58675128
... A47: 130 | B47: Cardinal Health Inc | C47: 2020 | D47: 14149Y108 | E47: 45838 | F47: 2751 | G47: CARDINAL HEALTH INC | H47: CAH | I47: 721371 | J47: 2020-06-30 | K47: 40766 | L47: 1789 | M47: 2771 | N47: 38974 | O47: 7268 | P47: -3696 | Q47: 152922 | R47: 293 | S47: 52.189999 | T47: 10.615603 | U47: -0.090663791 | V47: 0.95604181 | W47: 0.047527499 | X47: 0.067973308 | Y47: 1 | Z47: 0.1169918
A48: 131 | B48: Carrier Global Corp | C48: 2019 | D48: 14448C104 | E48: 46022 | F48: 36191 | G48: CARRIER GLOBAL CORP | H48: CARR | I48: 1783180 | J48: 2019-12-31 | K48: 22406 | L48: 14102 | M48: 957 | N48: 7971 | O48: 5790 | P48: 2116 | Q48: 18608 | R48: 866.15997 | S48: 16.92 | T48: 10.017084 | U48: 0.094438992 | V48: 0.35575292 | W48: 0.31115648 | X48: 0.042711772 | Y48: 0 | Z48: 0.96223742 | AA48: starts to trade on April 3 2020 -> The shares outstanding is replaced as 866,158,910 shares as if on the spin-off day (in 10-K https://www.sec.gov/ix?doc=/Archives/edgar/data/0001783180/000178318021000011/carr-20201231.htm), the stock price is replaced as 16.92, the closing price of the first date of trading (April 3, 2020)
A49: 132 | B49: Catalent Inc | C49: 2021 | D49: 148806102 | E49: 45473 | F49: 20228 | G49: CATALENT INC | H49: CTLT | I49: 1596783 | J49: 2021-06-30 | K49: 9112 | L49: 3915 | M49: 967 | N49: 4838 | O49: 1673 | P49: 585 | Q49: 3998 | R49: 170.549 | S49: 108.12 | T49: 9.1173477 | U49: 0.064201057 | V49: 0.53094822 | W49: 0.41845924 | X49: 0.10612379 | Y49: 0 | Z49: 0.21231298
A50: 133 | B50: Catalent Inc | C50: 2019 | D50: 148806102 | E50: 45473 | F50: 20228 | G50: CATALENT INC | H50: CTLT | I50: 1596783 | J50: 2019-06-30 | K50: 6184 | L50: 1681.6 | M50: 345.39999 | N50: 3895.8 | O50: 1033.7 | P50: 137.39999 | Q50: 2518 | R50: 145.73801 | S50: 54.209999 | T50: 8.7297201 | U50: 0.022218628 | V50: 0.62998062 | W50: 0.41052422 | X50: 0.055853814 | Y50: 0 | Z50: 0.21284844
A51: 134 | B51: Caterpillar Inc | C51: 2020 | D51: 149123101 | E51: 46022 | F51: 2817 | G51: CATERPILLAR INC | H51: CAT | I51: 18230 | J51: 2020-12-31 | K51: 78324 | L51: 15331 | M51: 9502 | N51: 62946 | O51: 14384 | P51: 2998 | Q51: 41748 | R51: 545.30402 | S51: 182.02 | T51: 11.268609 | U51: 0.0382769 | V51: 0.8036617 | W51: 0.34454346 | X51: 0.12131658 | Y51: 0 | Z51: 0.15445881
A52: 142 | B52: Century Communities Inc | C52: 2020 | D52: 156504300 | E52: 46022 | F52: 18004 | G52: CENTURY COMMUNITIES INC | H52: CCS | I52: 1576940 | J52: 2020-12-31 | K52: 2845.093 | L52: 1280.705 | M52: 421.23001 | N52: 1564.3879 | O52: 630.302 | P52: 206.157 | Q52: 3161.1919 | R52: 33.351002 | S52: 43.779999 | T52: 7.953351 | U52: 0.072460547 | V52: 0.54985476 | W52: 0.19938746 | X52: 0.14805491 | Y52: 0 | Z52: 0.87713099
A53: 146 | B53: CH Robinson Worldwide Inc | C53: 2020 | D53: 12541W209 | E53: 45657 | F53: 65609 | G53: C H ROBINSON WORLDWIDE INC | H53: CHRW | I53: 1043277 | J53: 2020-12-31 | K53: 5144.2578 | L53: 1879.933 | M53: 243.79601 | N53: 3264.325 | O53: 2513.9839 | P53: 506.42099 | Q53: 16207.106 | R53: 134.298 | S53: 93.870003 | T53: 8.5456362 | U53: 0.09844394 | V53: 0.63455701 | W53: 0.15511614 | X53: 0.047391873 | Y53: 0 | Z53: 0.14912346
A54: 147 | B54: Charah Solutions Inc | C54: 2020 | D54: 15957P303 | E54: 44926 | F54: 33596 | G54: CHARAH SOLUTIONS | H54: CHRA | I54: 1730346 | J54: 2020-12-31 | K54: 280.95999 | L54: 19.906 | M54: 29.211 | N54: 233.22099 | O54: 41.938 | P54: -55.862999 | Q54: 232.377 | R54: 30.077 | S54: 2.8699999 | T54: 5.6382122 | U54: -0.19882901 | V54: 0.83008611 | W54: 0.18047397 | X54: 0.10396854 | Y54: 1 | Z54: 0.23060441
A55: 149 | B55: Chart Industries Inc | C55: 2020 | D55: 16115Q308 | E55: 45657 | F55: 25964 | G55: CHART INDUSTRIES INC | H55: GTLS | I55: 892553 | J55: 2020-12-31 | K55: 2570.5 | L55: 1572.7 | M55: 126.1 | N55: 991.20001 | O55: 376.60001 | P55: 308.10001 | Q55: 1177.1 | R55: 35.424999 | S55: 117.79 | T55: 7.8518558 | U55: 0.11985995 | V55: 0.38560593 | W55: 0.31993884 | X55: 0.049056605 | Y55: 0 | Z55: 0.37690127
A56: 152 | B56: Chemours Co/The | C56: 2019 | D56: 163851108 | E56: 46022 | F56: 22741 | G56: CHEMOURS CO | H56: CC | I56: 1627223 | J56: 2019-12-31 | K56: 7258 | L56: 689 | M56: 943 | N56: 6563 | O56: 1524 | P56: -52 | Q56: 5526 | R56: 163.57401 | S56: 18.09 | T56: 8.8898592 | U56: -0.0071645081 | V56: 0.90424359 | W56: 0.27578717 | X56: 0.12992559 | Y56: 1 | Z56: 0.23284471
A57: 154 | B57: Cheniere Energy Partners LP | C57: 2020 | D57: 16411Q101 | E57: 43830 | F57: 176914 | G57: CHENIERE ENERGY PARTNERS LP | H57: CQP | I57: 1383650 | J57: 2020-12-31 | K57: 19145 | L57: 539 | M57: 1307 | N57: 18606 | O57: 2827 | P57: 1183 | Q57: 6167 | R57: 484 | S57: 35.25 | T57: 9.8597965 | U57: 0.061791591 | V57: 0.97184646 | W57: 0.45840764 | X57: 0.068268478 | Y57: 0 | Z57: 0.031592522
A58: 157 | B58: Chipotle Mexican Grill Inc | C58: 2020 | D58: 169656105 | E58: 46022 | F58: 165914 | G58: CHIPOTLE MEXICAN GRILL INC | H58: CMG | I58: 1058090 | J58: 2020-12-31 | K58: 5982.896 | L58: 2020.135 | M58: 951.60303 | N58: 3962.761 | O58: 1035.65 | P58: 355.76599 | Q58: 5984.6338 | R58: 28.000999 | S58: 1386.71 | T58: 8.69666 | U58: 0.059463844 | V58: 0.66234827 | W58: 0.17305152 | X58: 0.15905392 | Y58: 0 | Z58: 0.052026093
A59: 164 | B59: Citigroup Inc (Citi) | C59: 2020 | D59: 172967424 | E59: 46022 | F59: 3243 | G59: CITIGROUP INC | H59: C | I59: 831001 | J59: 2020-12-31 | K59: 2260090 | L59: 179962 | M59: 605047 | N59: 2059890 | O59: 25573 | P59: 11047 | Q59: 88839 | R59: 2082.0901 | S59: 61.66 | T59: 14.630916 | U59: 0.0048878584 | V59: 0.91141945 | W59: 0.2878578 | X59: 0.26770926 | Y59: 0 | Z59: 1.4017732
A60: 165 | B60: Citizens Financial Group Inc | C60: 2020 | D60: 174610105 | E60: 46022 | F60: 21825 | G60: CITIZENS FINANCIAL GROUP INC | H60: CFG | I60: 759944 | J60: 2020-12-31 | K60: 183349 | L60: 20708 | M60: 13039 | N60: 160676 | O60: 5289 | P60: 1057 | Q60: 7676 | R60: 427.20999 | S60: 35.759998 | T60: 12.119146 | U60: 0.0057649617 | V60: 0.87633967 | W60: 0.68903077 | X60: 0.07111574 | Y60: 0 | Z60: 1.3554991
... A212: 626 | B212: Pioneer Natural Resources Co | C212: 2019 | D212: 723787107 | E212: 45291 | F212: 14359 | G212: PIONEER NATURAL RESOURCES CO | H212: PXD | I212: 1038357 | J212: 2019-12-31 | K212: 19067 | L212: 12119 | M212: 705 | N212: 6948 | O212: 3889 | P212: 756 | Q212: 9671 | R212: 165.547 | S212: 151.37 | T212: 9.8557148 | U212: 0.039649658 | V212: 0.36439922 | W212: 0.40213007 | X212: 0.036974877 | Y212: 0 | Z212: 0.4836216
A213: 628 | B213: Plains GP Holdings LP | C213: 2020 | D213: 72651A207 | E213: 45657 | F213: 18468 | G213: PLAINS GP HOLDINGS LP | H213: PAGP | I213: 1581990 | J213: 2020-12-31 | K213: 25951 | L213: 1464 | M213: 63 | N213: 14761 | O213: 1783 | P213: -568 | Q213: 23290 | R213: 194.05099 | S213: 8.4499998 | T213: 10.163965 | U213: -0.021887403 | V213: 0.56880271 | W213: 0.076556459 | X213: 0.002427652 | Y213: 1 | Z213: 0.89282942 | AA213: No book value of equity -> book value of equity (CEQ) is replaced as SEQ (stockholders equity-parent)
A214: 633 | B214: Potlatch Corp | C214: 2020 | D214: 737630103 | E214: 45657 | F214: 8692 | G214: POTLATCHDELTIC CORP | H214: PCH | I214: 1338749 | J214: 2020-12-31 | K214: 2381.0649 | L214: 1304.953 | M214: 252.34 | N214: 1076.1121 | O214: 429.41 | P214: 166.83 | Q214: 1040.9301 | R214: 66.875999 | S214: 50.02 | T214: 7.7753029 | U214: 0.07006529 | V214: 0.45194569 | W214: 0.41252533 | X214: 0.10597779 | Y214: 0 | Z214: 0.39010444
A215: 634 | B215: Potlatch Corp | C215: 2019 | D215: 737630103 | E215: 45657 | F215: 8692 | G215: POTLATCHDELTIC CORP | H215: PCH | I215: 1338749 | J215: 2019-12-31 | K215: 2235.0591 | L215: 1226.8311 | M215: 83.309998 | N215: 1008.228 | O215: 215.44901 | P215: 55.660999 | Q215: 827.09802 | R215: 67.221001 | S215: 43.27 | T215: 7.7120228 | U215: 0.024903592 | V215: 0.4510968 | W215: 0.26048788 | X215: 0.037274182 | Y215: 0 | Z215: 0.4217867
A216: 635 | B216: PPG Industries Inc | C216: 2020 | D216: 693506107 | E216: 46022 | F216: 8247 | G216: PPG INDUSTRIES INC | H216: PPG | I216: 79879 | J216: 2020-12-31 | K216: 19556 | L216: 5689 | M216: 1928 | N216: 13741 | O216: 6064 | P216: 1059 | Q216: 13841 | R216: 236.686 | S216: 144.22 | T216: 9.8810377 | U216: 0.05415218 | V216: 0.70264882 | W216: 0.43811864 | X216: 0.098588668 | Y216: 0 | Z216: 0.16666248
A217: 636 | B217: PPG Industries Inc | C217: 2019 | D217: 693506107 | E217: 46022 | F217: 8247 | G217: PPG INDUSTRIES INC | H217: PPG | I217: 79879 | J217: 2019-12-31 | K217: 17708 | L217: 5284 | M217: 1278 | N217: 12305 | O217: 6501 | P217: 1243 | Q217: 15154 | R217: 235.67999 | S217: 133.49001 | T217: 9.7817717 | U217: 0.070194259 | V217: 0.69488364 | W217: 0.42899564 | X217: 0.072170772 | Y217: 0 | Z217: 0.16795439
A218: 637 | B218: PPL Corp | C218: 2019 | D218: 69351T106 | E218: 46022 | F218: 8455 | G218: PPL CORP | H218: PPL | I218: 922224 | J218: 2019-12-31 | K218: 45680 | L218: 12991 | M218: 818 | N218: 32689 | O218: 4044 | P218: 1746 | Q218: 7769 | R218: 767.23297 | S218: 35.880001 | T218: 10.729416 | U218: 0.038222417 | V218: 0.7156086 | W218: 0.52053028 | X218: 0.01790718 | Y218: 0 | Z218: 0.47191402
A219: 638 | B219: PPL Corp | C219: 2018 | D219: 69351T106 | E219: 46022 | F219: 8455 | G219: PPL CORP | H219: PPL | I219: 922224 | J219: 2018-12-31 | K219: 43396 | L219: 11657 | M219: 624 | N219: 31739 | O219: 3959 | P219: 1827 | Q219: 7785 | R219: 720.323 | S219: 28.33 | T219: 10.678123 | U219: 0.042100653 | V219: 0.73138076 | W219: 0.50854206 | X219: 0.014379205 | Y219: 0 | Z219: 0.57123256
A220: 641 | B220: Procter & Gamble Co/The | C220: 2020 | D220: 742718109 | E220: 45838 | F220: 8762 | G220: PROCTER & GAMBLE CO | H220: PG | I220: 80424 | J220: 2020-06-30 | K220: 120700 | L220: 46704 | M220: 16181 | N220: 73822 | O220: 39327 | P220: 13027 | Q220: 70950 | R220: 2479.7461 | S220: 119.57 | T220: 11.701063 | U220: 0.10792875 | V220: 0.6116156 | W220: 0.55429173 | X220: 0.13405965 | Y220: 0 | Z220: 0.15751599
A221: 643 | B221: Prudential Financial Inc | C221: 2020 | D221: 744320102 | E221: 46022 | F221: 143356 | G221: PRUDENTIAL FINANCIAL INC | H221: PRU | I221: 1137774 | J221: 2020-12-31 | K221: 940722 | L221: 67425 | M221: 61904 | N221: 872512 | O221: 13588 | P221: -374 | Q221: 57031 | R221: 396.43701 | S221: 78.07 | T221: 13.754403 | U221: -0.00039756697 | V221: 0.92749184 | W221: 0.23825638 | X221: 0.065804772 | Y221: 1 | Z221: 2.1785252
A222: 644 | B222: Prudential Financial Inc | C222: 2019 | D222: 744320102 | E222: 46022 | F222: 143356 | G222: PRUDENTIAL FINANCIAL INC | H222: PRU | I222: 1137774 | J222: 2019-12-31 | K222: 896552 | L222: 63115 | M222: 60267 | N222: 832833 | O222: 18539 | P222: 4186 | Q222: 64845 | R222: 398.832 | S222: 93.739998 | T222: 13.706311 | U222: 0.0046689985 | V222: 0.92892885 | W222: 0.28589714 | X222: 0.067220867 | Y222: 0 | Z222: 1.6881757
A223: 648 | B223: Public Storage | C223: 2020 | D223: 74460D109 | E223: 46022 | F223: 10096 | G223: PUBLIC STORAGE | H223: PSA | I223: 1393311 | J223: 2020-12-31 | K223: 11816.546 | L223: 4766.3672 | M223: 282.60001 | N223: 3239.647 | O223: 1597.1689 | P223: 1357.213 | Q223: 3017.8879 | R223: 174.582 | S223: 230.92999 | T223: 9.3772564 | U223: 0.114857 | V223: 0.27416193 | W223: 0.52923399 | X223: 0.023915619 | Y223: 0 | Z223: 0.11822455
A224: 649 | B224: Public Storage | C224: 2019 | D224: 74460D109 | E224: 46022 | F224: 10096 | G224: PUBLIC STORAGE | H224: PSA | I224: 1393311 | J224: 2019-12-31 | K224: 11365.444 | L224: 4997.9111 | M224: 433.55399 | N224: 2285.7771 | O224: 1635.105 | P224: 1520.5341 | Q224: 2944.8059 | R224: 174.41901 | S224: 212.96001 | T224: 9.3383331 | U224: 0.13378571 | V224: 0.20111638 | W224: 0.55525053 | X224: 0.038146682 | Y224: 0 | Z224: 0.13455401
A225: 652 | B225: PVH Corp | C225: 2020 | D225: 693656100 | E225: 45688 | F225: 8551 | G225: PVH CORP | H225: PVH | I225: 78239 | J225: 2020-01-31 | K225: 13631 | L225: 5811.5 | M225: 503.39999 | N225: 7821.5 | O225: 5417.7998 | P225: 417.29999 | Q225: 9909 | R225: 72.292999 | S225: 87.169998 | T225: 9.5201015 | U225: 0.030614041 | V225: 0.57380235 | W225: 0.54675543 | X225: 0.036930524 | Y225: 0 | Z225: 0.92219967
... A305: 866 | B305: Zoetis Inc | C305: 2019 | D305: 98978V103 | E305: 46022 | F305: 13721 | G305: ZOETIS INC | H305: ZTS | I305: 1555280 | J305: 2019-12-31 | K305: 11545 | L305: 2708 | M305: 1934 | N305: 8837 | O305: 4620 | P305: 1500 | Q305: 6276 | R305: 475.52802 | S305: 132.35001 | T305: 9.3540077 | U305: 0.12992637 | V305: 0.76543957 | W305: 0.73613769 | X305: 0.16751841 | Y305: 0 | Z305: 0.043027744

Sheet Metrics
A1: Industry | B1: Topics | C1: Code | D1: Quantitative | E1: Metrics | F1: MonetaryLoss
A2: ADVERTISING & MARKETING | B2: Data Privacy | C2: SV-AD-220a.1 | D2: 0 | E2: Discussion of policies and practices relating to behavioral advertising and consumer privacy
B3: Data Privacy | C3: SV-AD-220a.2 | D3: 1 | E3: Percentage of online advertising impressions that are targeted to custom audiences
B4: Data Privacy | C4: SV-AD-220a.3 | D4: 1 | E4: Total amount of monetary losses as a result of legal proceedings associated with consumer privacy | F4: 1
B5: Advertising Integrity | C5: SV-AD-270a.1 | D5: 1 | E5: Total amount of monetary losses as a result of legal proceedings associated with false, deceptive, or unfair advertising | F5: 1
B6: Advertising Integrity | C6: SV-AD-270a.2 | D6: 1 | E6: Percentage of campaigns reviewed for adherence with the Advertising Self- Regulatory Council (ASRC) procedures, percentage of those in compliance
B7: Advertising Integrity | C7: SV-AD-270a.3 | D7: 1 | E7: Percentage of campaigns that promote alcohol or tobacco products
B8: Workforce Diversity & Inclusion | C8: SV-AD-330a.1 | D8: 1 | E8: Percentage of gender and racial/ethnic group representation for (1) management, (2) professionals, and (3) all other employees
A9: AEROSPACE & DEFENSE | B9: Energy Management | C9: RT-AE-130a.1 | D9: 1 | E9: (1) Total energy consumed, (2) percentage grid electricity, (3) percentage renewable
B10: Hazardous Waste Management | C10: RT-AE-150a.1 | D10: 1 | E10: Amount of hazardous waste generated, percentage recycled
B11: Hazardous Waste Management | C11: RT-AE-150a.2 | D11: 1 | E11: Number and aggregate quantity of reportable spills, quantity recovered
B12: Data Security | C12: RT-AE-230a.1 | D12: 1 | E12: (1) Number of data breaches, (2) percentage involving confidential information
B13: Data Security | C13: RT-AE-230a.2 | D13: 0 | E13: Description of approach to identifying and addressing data security risks in (1) company operations and (2) products
B14: Product Safety | C14: RT-AE-250a.1 | D14: 1 | E14: Number of recalls issued, total units recalled
B15: Product Safety | C15: RT-AE-250a.2 | D15: 1 | E15: Number of counterfeit parts detected, percentage avoided
B16: Product Safety | C16: RT-AE-250a.3 | D16: 1 | E16: Number of Airworthiness Directives received, total units affected
B17: Product Safety | C17: RT-AE-250a.4 | D17: 1 | E17: Total amount of monetary losses as a result of legal proceedings associated with product safety | F17: 1
B18: Fuel Economy & Emissions in Use-phase | C18: RT-AE-410a.1 | D18: 1 | E18: Revenue from alternative energy-related products
B19: Fuel Economy & Emissions in Use-phase | C19: RT-AE-410a.2 | D19: 0 | E19: Description of approach and discussion of strategy to address fuel economy and greenhouse gas (GHG) emissions of products
B20: Materials Sourcing | C20: RT-AE-440a.1 | D20: 0 | E20: Description of the management of risks associated with the use of critical materials
B21: Business Ethics | C21: RT-AE-510a.1 | D21: 1 | E21: Total amount of monetary losses as a result of legal proceedings associated with incidents of corruption, bribery, and/or illicit international trade | F21: 1
B22: Business Ethics | C22: RT-AE-510a.2 | D22: 1 | E22: Revenue from countries ranked in the “E” or“F” Band of Transparency International’sGovernment Defence Anti-Corruption Index
B23: Business Ethics | C23: RT-AE-510a.3 | D23: 0 | E23: Discussion of processes to manage business ethics risks throughout the value chain
A24: AGRICULTURAL PRODUCTS | B24: Greenhouse Gas Emissions | C24: FB-AG-110a.1 | D24: 1 | E24: Gross global Scope 1 emissions
B25: Greenhouse Gas Emissions | C25: FB-AG-110a.2 | D25: 0 | E25: Discussion of long-term and short-term strategy or plan to manage Scope 1 emissions, emissions reduction targets, and an analysis of performance against those targets
B26: Greenhouse Gas Emissions | C26: FB-AG-110a.3 | D26: 1 | E26: Fleet fuel consumed, percentage renewable
B27: Energy Management | C27: FB-AG-130a.1 | D27: 1 | E27: (1) Operational energy consumed, (2) percentage grid electricity, (3) percentage renewable
B28: Water Management | C28: FB-AG-140a.1 | D28: 1 | E28: (1) Total water withdrawn, (2) total water consumed, percentage of each in regions with High or Extremely High Baseline Water Stress
B29: Water Management | C29: FB-AG-140a.2 | D29: 0 | E29: Description of water management risks and discussion of strategies and practices to mitigate those risks
B30: Water Management | C30: FB-AG-140a.3 | D30: 1 | E30: Number of incidents of non-compliance associated with water quantity and/or quality permits, standards, and regulations
B31: Food Safety | C31: FB-AG-250a.1 | D31: 1 | E31: Global Food Safety Initiative (GFSI) audit (1) non-conformance rate and (2) associated corrective action rate for (a) major and (b) minor non-conformances
B32: Food Safety | C32: FB-AG-250a.2 | D32: 1 | E32: Percentage of agricultural products sourced from suppliers certified to a Global Food Safety Initiative (GFSI) recognized food safety certification program
B33: Food Safety | C33: FB-AG-250a.3 | D33: 1 | E33: (1) Number of recalls issued and (2) total amount of food product recalled
B34: Workforce Health & Safety | C34: FB-AG-320a.1 | D34: 1 | E34: (1) Total recordable incident rate (TRIR), (2) fatality rate, and (3) near miss frequency rate (NMFR) for (a) direct employees and (b) seasonal and migrant employees
B35: Environmental & Social Impacts of Ingredient Supply Chain | C35: FB-AG-430a.1 | D35: 1 | E35: Percentage of agricultural products sourced that are certified to a third-party environmental and/or social standard, and percentages by standard
B36: Environmental & Social Impacts of Ingredient Supply Chain | C36: FB-AG-430a.2 | D36: 1 | E36: Suppliers’ social and environmental responsibility audit (1) non-conformance rate and (2) associated corrective action rate for (a) major and (b) minor non-conformances
... B40: Ingredient Sourcing | C40: FB-AG-440a.2 | D40: 1 | E40: Percentage of agricultural products sourced from regions with High or Extremely High Baseline Water Stress
A41: AIR FREIGHT & LOGISTICS | B41: Greenhouse Gas Emissions | C41: TR-AF-110a.1 | D41: 1 | E41: Gross global Scope 1 emissions
B42: Greenhouse Gas Emissions | C42: TR-AF-110a.2 | D42: 0 | E42: Discussion of long-term and short-term strategy or plan to manage Scope 1 emissions, emissions reduction targets, and an analysis of performance against those targets
B43: Greenhouse Gas Emissions | C43: TR-AF-110a.3 | D43: 1 | E43: Fuel consumed by (1) road transport, percentage (a) natural gas and (b) renewable, and (2) air transport, percentage (a) alternative and (b) sustainable
B44: Air Quality | C44: TR-AF-120a.1 | D44: 1 | E44: Air emissions of the following pollutants: (1) NOx (excluding N2O), (2) SOx, and (3) particulate matter (PM10)
B45: Labor Practices | C45: TR-AF-310a.1 | D45: 1 | E45: Percentage of drivers classified as independent contractors
B46: Labor Practices | C46: TR-AF-310a.2 | D46: 1 | E46: Total amount of monetary losses as a result of legal proceedings associated with labor law violations | F46: 1
B47: Employee Health & Safety | C47: TR-AF-320a.1 | D47: 1 | E47: (1) Total recordable incident rate (TRIR) and (2) fatality rate for (a) direct employees and (b) contract employees
B48: Supply Chain Management | C48: TR-AF-430a.1 | D48: 1 | E48: Percentage of carriers with BASIC percentiles above the FMCSA intervention threshold
B49: Supply Chain Management | C49: TR-AF-430a.2 | D49: 1 | E49: Total greenhouse gas (GHG) footprint across transport modes
B50: Accident & Safety Management | C50: TR-AF-540a.1 | D50: 0 | E50: Description of implementation and outcomes of a Safety Management System
B51: Accident & Safety Management | C51: TR-AF-540a.2 | D51: 1 | E51: Number of aviation accidents
B52: Accident & Safety Management | C52: TR-AF-540a.3 | D52: 1 | E52: Number of road accidents and incidents
B53: Accident & Safety Management | C53: TR-AF-540a.4 | D53: 1 | E53: Safety Measurement System BASIC percentiles for: (1) Unsafe Driving, (2) Hours-of-Service Compliance, (3) Driver Fitness, (4) Controlled Substances/Alcohol, (5) Vehicle Maintenance, and (6) Hazardous Materials Compliance
A54: AIRLINES | B54: Greenhouse Gas Emissions | C54: TR-AL-110a.1 | D54: 1 | E54: Gross global Scope 1 emissions
B55: Greenhouse Gas Emissions | C55: TR-AL-110a.2 | D55: 0 | E55: Discussion of long-term and short-term strategy or plan to manage Scope 1 emissions, emissions reduction targets, and an analysis of performance against those targets
B56: Greenhouse Gas Emissions | C56: TR-AL-110a.3 | D56: 1 | E56: (1) Total fuel consumed, (2) percentage alternative, (3) percentage sustainable
B57: Labor Practices | C57: TR-AL-310a.1 | D57: 1 | E57: Percentage of active workforce covered under collective bargaining agreements
B58: Labor Practices | C58: TR-AL-310a.2 | D58: 1 | E58: (1) Number of work stoppages and (2) total days idle
B59: Competitive Behavior | C59: TR-AL-520a.1 | D59: 1 | E59: Total amount of monetary losses as a result of legal proceedings associated with anti-competitive behavior regulations | F59: 1
B60: Accident & Safety Management | C60: TR-AL-540a.1 | D60: 0 | E60: Description of implementation and outcomes of a Safety Management System
B61: Accident & Safety Management | C61: TR-AL-540a.2 | D61: 1 | E61: Number of aviation accidents
B62: Accident & Safety Management | C62: TR-AL-540a.3 | D62: 1 | E62: Number of governmental enforcement actions of aviation safety regulations
A63: ALCOHOLIC BEVERAGES | B63: Energy Management | C63: FB-AB-130a.1 | D63: 1 | E63: (1) Total energy consumed, (2) percentage grid electricity, (3) percentage renewable
B64: Water Management | C64: FB-AB-140a.1 | D64: 1 | E64: (1) Total water withdrawn, (2) total water consumed, percentage of each in regions with High or Extremely High Baseline Water Stress
B65: Water Management | C65: FB-AB-140a.2 | D65: 0 | E65: Description of water management risks and discussion of strategies and practices to mitigate those risks
B66: Responsible Drinking & Marketing | C66: FB-AB-270a.1 | D66: 1 | E66: Percentage of total advertising impressions made on individuals at or above the legal drinking age
B67: Responsible Drinking & Marketing | C67: FB-AB-270a.2 | D67: 1 | E67: Number of incidents of non-compliance with industry or regulatory labeling and/or marketing codes
B68: Responsible Drinking & Marketing | C68: FB-AB-270a.3 | D68: 1 | E68: Total amount of monetary losses as a result of legal proceedings associated with marketing and/or labeling practices
B69: Responsible Drinking & Marketing | C69: FB-AB-270a.4 | D69: 0 | E69: Description of efforts to promote responsible consumption of alcohol
B70: Packaging Lifecycle Management | C70: FB-AB-410a.1 | D70: 1 | E70: (1) Total weight of packaging, (2) percentage made from recycled and/or renewable materials, and (3) percentage that is recyclable, reusable, and/or compostable
B71: Packaging Lifecycle Management | C71: FB-AB-410a.2 | D71: 0 | E71: Discussion of strategies to reduce the environmental impact of packaging throughout its lifecycle | F71: 1
B72: Environmental & Social Impacts of Ingredient Supply Chain | C72: FB-AB-430a.1 | D72: 1 | E72: Suppliers’ social and environmental responsibility audit (1) non-conformance rate and (2) associated corrective action rate for (a) major and (b) minor non-conformances
B73: Ingredient Sourcing | C73: FB-AB-440a.1 | D73: 1 | E73: Percentage of beverage ingredients sourced from regions with High or Extremely High Baseline Water Stress
B74: Ingredient Sourcing | C74: FB-AB-440a.2 | D74: 0 | E74: List of priority beverage ingredients and description of sourcing risks due to environmental and social considerations
A75: APPAREL, ACCESSORIES & FOOTWEAR | B75: Management of Chemicals in Products | C75: CG-AA-250a.1 | D75: 0 | E75: Discussion of processes to maintain compliance with restricted substances regulations | N75: Note: CG-AA-440a.1 is equivalent to CG-AA-440a.3; CG-AA-440a.2 is equivalent to CG-AA-440a.4 (Company might choose either one pair)
B76: Management of Chemicals in Products | C76: CG-AA-250a.2 | D76: 0 | E76: Discussion of processes to assess and manage risks and/or hazards associated with chemicals in products
B77: Environmental Impacts in the Supply Chain | C77: CG-AA-430a.1 | D77: 1 | E77: Percentage of (1) Tier 1 supplier facilities and (2) supplier facilities beyond Tier 1 in compliance with wastewater discharge permits and/or contractual agreements
B78: Environmental Impacts in the Supply Chain | C78: CG-AA-430a.2 | D78: 1 | E78: Percentage of (1) Tier 1 supplier facilities and (2) supplier facilities beyond Tier 1 that have completed the Sustainable Apparel Coalition’s Higg Facility Environmental Module (Higg FEM) assessment or an equivalent environmental data assessment
B79: Labor Conditions in the Supply Chain | C79: CG-AA-430b.1 | D79: 1 | E79: Percentage of (1) Tier 1 supplier facilities and (2) supplier facilities beyond Tier 1 that have been audited to a labor code of conduct, (3) percentage of total audits conducted by a third-party auditor
B80: Labor Conditions in the Supply Chain | C80: CG-AA-430b.2 | D80: 1 | E80: Priority non-conformance rate and associated corrective action rate for suppliers’ labor code of conduct audits
B81: Labor Conditions in the Supply Chain | C81: CG-AA-430b.3 | D81: 0 | E81: Description of the greatest (1) labor and (2) environmental, health, and safety risks in the supply chain
B82: Raw Materials Sourcing | C82: CG-AA-440a.1 | D82: 0 | E82: Description of environmental and social risks associated with sourcing priority raw materials
B83: Raw Materials Sourcing | C83: CG-AA-440a.2 | D83: 1 | E83: Percentage of raw materials third-party certified to an environmental and/or social sustainability standard, by standard
B84: Raw Materials Sourcing | C84: CG-AA-440a.3 | D84: 0 | E84: (1) List of priority raw materials; for each priority raw material: (2) environmental and/or social factor (s) most likely to threaten sourcing, (3) discussion on business risks and/or opportunities associated with environmental and/or social factors, and (4) management strategy for addressing business risks and opportunities
B85: Raw Materials Sourcing | C85: CG-AA-440a.4 | D85: 1 | E85: (1) Amount of priority raw materials purchased, by material, and (2) amount of each priority raw material that is certified to a third-party environmental and/or social standard, by standard
A86: APPLIANCE MANUFACTURING | B86: Product Safety | C86: CG-AM-250a.1 | D86: 1 | E86: Number of (1) recalls issued and (2) total units recalled
B87: Product Safety | C87: CG-AM-250a.2 | D87: 0 | E87: Discussion of process to identify and manage safety risks associated with the use of its products
B88: Product Safety | C88: CG-AM-250a.3 | D88: 1 | E88: Total amount of monetary losses as a result of legal proceedings associated with product safety | F88: 1
B89: Product Lifecycle Environmental Impacts | C89: CG-AM-410a.1 | D89: 1 | E89: Percentage of eligible products by revenue certified to the ENERGY STAR® program
B90: Product Lifecycle Environmental Impacts | C90: CG-AM-410a.2 | D90: 1 | E90: Percentage of eligible products certified to an Association of Home Appliance Manufacturers (AHAM) sustainability standard
B91: Product Lifecycle Environmental Impacts | C91: CG-AM-410a.3 | D91: 0 | E91: Description of efforts to manage products’ end-of-life impacts
A92: ASSET MANAGEMENT & CUSTODY | B92: Transparent Information & Fair Advice for Customers | C92: FN-AC-270a.1 | D92: 1 | E92: (1) Number and (2) percentage of covered employees with a record of investment-related investigations, consumer-initiated complaints, private civil litigations, or other regulatory proceedings
B93: Transparent Information & Fair Advice for Customers | C93: FN-AC-270a.2 | D93: 1 | E93: Total amount of monetary losses as a result of legal proceedings associated with marketing and communication of financial product-related information to new and returning customers | F93: 1
B94: Transparent Information & Fair Advice for Customers | C94: FN-AC-270a.3 | D94: 0 | E94: Description of approach to informing customers about products and services
B95: Employee Diversity & Inclusion | C95: FN-AC-330a.1 | D95: 1 | E95: Percentage of gender and racial/ethnic group representation for (1) executive management, (2) non-executive management, (3) professionals, and (4) all other employees
B96: Incorporation of Environmental, Social, and Governance Factors in Investment Management & Advisory | C96: FN-AC-410a.1 | D96: 1 | E96: Amount of assets under management, by asset class, that employ (1) integration of environmental, social, and governance (ESG) issues, (2) sustainability themed investing, and (3) screening
B97: Incorporation of Environmental, Social, and Governance Factors in Investment Management & Advisory | C97: FN-AC-410a.2 | D97: 0 | E97: Description of approach to incorporation of environmental, social, and governance (ESG) factors in investment and/or wealth management processes and strategies
B98: Incorporation of Environmental, Social, and Governance Factors in Investment Management & Advisory | C98: FN-AC-410a.3 | D98: 0 | E98: Description of proxy voting and investee engagement policies and procedures
B99: Business Ethics | C99: FN-AC-510a.1 | D99: 1 | E99: Total amount of monetary losses as a result of legal proceedings associated with fraud, insider trading, anti-trust, anti-competitive behavior, market manipulation, malpractice, or other related financial industry laws or regulations | F99: 1
B100: Business Ethics | C100: FN-AC-510a.2 | D100: 0 | E100: Description of whistleblower policies and procedures
B101: Systemic Risk Management | C101: FN-AC-550a.1 | D101: 1 | E101: Percentage of open-end fund assets under management by category of liquidity classification | I101: Updated in 2021
B102: Systemic Risk Management | C102: FN-AC-550a.2 | D102: 0 | E102: Description of approach to incorporation of liquidity risk management programs into portfolio strategy and redemption risk management | I102: Updated in 2021
B103: Systemic Risk Management | C103: FN-AC-550a.3 | D103: 1 | E103: Total exposure to securities financing transactions | I103: Updated in 2021
...

Sheet List of Sample Metrics
A1: Line in Master | B1: Company | C1: Industry | D1: Code | E1: Metrics | F1: Reported
A2: =Sample!A2 -> 10 | B2: =Sample!B2 -> AdvanSix Inc | C2: CHEMICALS | D2: RT-CH-110a.1 | E2: Gross global Scope 1 emissions, percentage covered under emissions-limiting regulations | F2: 1
D3: RT-CH-110a.2 | E3: Discussion of long-term and short-term strategy or plan to manage Scope 1 emissions, emissions reduction targets, and an analysis of performance against those targets | F3: 1
D4: RT-CH-120a.1 | E4: Air emissions of the following pollutants: (1) NOX (excluding N2O), (2) SOX, (3) volatile organic compounds (VOCs), and (4) hazardous air pollutants (HAPs) | F4: 1
D5: RT-CH-130a.1 | E5: (1) Total energy consumed, (2) percentage grid electricity, (3) percentage renewable, (4) total self-generated energy | F5: 1
D6: RT-CH-140a.1 | E6: (1) Total water withdrawn, (2) total water consumed, percentage of each in regions with High or Extremely High Baseline Water Stress | F6: 1
D7: RT-CH-140a.2 | E7: Number of incidents of non-compliance associated with water quality permits, standards, and regulations | F7: 0
D8: RT-CH-140a.3 | E8: Description of water management risks and discussion of strategies and practices to mitigate those risks | F8: 0
D9: RT-CH-150a.1 | E9: Amount of hazardous waste generated, percentage recycled | F9: 1
D10: RT-CH-210a.1 | E10: Discussion of engagement processes to manage risks and opportunities associated with community interests | F10: 1
D11: RT-CH-320a.1 | E11: (1) Total recordable incident rate (TRIR) and (2) fatality rate for (a) direct employees and (b) contract employees | F11: 1
D12: RT-CH-320a.2 | E12: Description of efforts to assess, monitor, and reduce exposure of employees and contract workers to long-term (chronic) health risks | F12: 1
D13: RT-CH-410a.1 | E13: Revenue from products designed for use-phase resource efficiency | F13: 0
D14: RT-CH-410b.1 | E14: (1) Percentage of products that contain Globally Harmonized System of Classification and Labeling of Chemicals (GHS) Category 1 and 2 Health and Environmental Hazardous Substances, (2) percentage of such products that have undergone a hazard assessment | F14: 0
... D19: RT-CH-540a.2 | E19: Number of transport incidents | F19: 0
A20: =Sample!A3 -> 11 | B20: =Sample!B3 -> Aflac Inc | C20: INSURANCE | D20: FN-IN-270a.1 | E20: Total amount of monetary losses as a result of legal proceedings associated with marketing and communication of insurance product-related information to new and returning customers | F20: 1
D21: FN-IN-270a.2 | E21: Complaints-to-claims ratio | F21: 0
D22: FN-IN-270a.3 | E22: Customer retention rate | F22: 0
D23: FN-IN-270a.4 | E23: Description of approach to informing customers about products | F23: 1
D24: FN-IN-410a.1 | E24: Total invested assets, by industry and asset class | F24: 1
D25: FN-IN-410a.2 | E25: Description of approach to incorporation of environmental, social, and governance (ESG) factors in investment management processes and strategies | F25: 1
D26: FN-IN-410b.1 | E26: Net premiums written related to energy efficiency and low carbon technology | F26: 0
D27: FN-IN-410b.2 | E27: Discussion of products and/or product features that incentivize health, safety, and/or environmentally responsible actions and/or behaviors | F27: 0
D28: FN-IN-450a.1 | E28: Probable Maximum Loss (PML) of insured products from weather-related natural catastrophes | F28: 0
D29: FN-IN-450a.2 | E29: Total amount of monetary losses attributable to insurance payouts from (1) modeled natural catastrophes and (2) non-modeled natural catastrophes, by type of event and geographic segment (net and gross of reinsurance) | F29: 0
D30: FN-IN-450a.3 | E30: Description of approach to incorporation of environmental risks into (1) the underwriting process for individual contracts and (2) the management of firm-level risks and capital adequacy | F30: 0
D31: FN-IN-550a.1 | E31: Exposure to derivative instruments by category: (1) total potential exposure to non-centrally cleared derivatives, (2) total fair value of acceptable collateral posted with the Central Clearinghouse, and (3) total potential exposure to centrally cleared derivatives | F31: 0
D32: FN-IN-550a.2 | E32: Total fair value of securities lending collateral assets | F32: 0
D33: FN-IN-550a.3 | E33: Description of approach to managing capital- and liquidity-related risks associated with systemic non-insurance activities | F33: 0
A34: =Sample!A4 -> 12 | B34: =Sample!B4 -> Agilent Technologies Inc | C34: MEDICAL EQUIPMENT & SUPPLIES | D34: HC-MS-240a.1 | E34: Ratio of weighted average rate of net price increases (for all products) to the annual increase in the U.S. Consumer Price Index | F34: 1
D35: HC-MS-240a.2 | E35: Description of how price information for each product is disclosed to customers or to their agents | F35: 1
D36: HC-MS-250a.1 | E36: Number of recalls issued, total units recalled | F36: 1
D37: HC-MS-250a.2 | E37: List of products listed in the FDA’s MedWatch Safety Alerts for Human Medical Products database | F37: 1
D38: HC-MS-250a.3 | E38: Number of fatalities related to products as reported in the FDA Manufacturer and User Facility Device Experiencedatabase | F38: 1
D39: HC-MS-250a.4 | E39: Number of FDA enforcement actions taken in response to violations of current Good Manufacturing Practices (cGMP), by type | F39: 1
D40: HC-MS-270a.1 | E40: Total amount of monetary losses as a result of legal proceedings associated with bribery or corruption | F40: 1
D41: HC-MS-270a.2 | E41: Description of code of ethics governing promotion of off-label use of products | F41: 1
D42: HC-MS-410a.1 | E42: Discussion of process to assess and manage environmental and human health considerations associated with chemicals in products, and meet demand for sustainable products | F42: 1
D43: HC-MS-410a.2 | E43: Total amount of products accepted for take-back and reused, recycled, or donated, broken down by: (1) devices and equipment and (2) supplies | F43: 1
D44: HC-MS-430a.1 | E44: Percentage of (1) entity's facilities and (2) Tier I suppliers' facilities participating in third-party audit programs for manufacturing and product quality | F44: 1
D45: HC-MS-430a.2 | E45: Description of efforts to maintain traceability within the distribution chain | F45: 1
D46: HC-MS-430a.3 | E46: Description of the management of risks associated with the use of critical materials | F46: 1
... D48: HC-MS-510a.2 | E48: Description of code of ethics governing interactions with health care professionals | F48: 1
A49: =Sample!A5 -> 14 | B49: =Sample!B5 -> AGNC Investment Corp | C49: ASSET MANAGEMENT & CUSTODY | D49: FN-AC-510a.1 | E49: Total amount of monetary losses as a result of legal proceedings associated with fraud, insider trading, anti-trust, anti-competitive behavior, market manipulation, malpractice, or other related financial industry laws or regulations | F49: 1
D50: FN-AC-510a.2 | E50: Description of whistleblower policies and procedures | F50: 1
D51: FN-AC-330a.1 | E51: Percentage of gender and racial/ethnic group representation for (1) executive management, (2) non-executive management, (3) professionals, and (4) all other employees | F51: 1
D52: FN-AC-410a.1 | E52: Amount of assets under management, by asset class, that employ (1) integration of environmental, social, and governance (ESG) issues, (2) sustainability themed investing, and (3) screening | F52: 1
D53: FN-AC-410a.2 | E53: Description of approach to incorporation of environmental, social, and governance (ESG) factors in investment and/or wealth management processes and strategies | F53: 1
D54: FN-AC-410a.3 | E54: Description of proxy voting and investee engagement policies and procedures | F54: 1
D55: FN-AC-270a.1 | E55: (1) Number and (2) percentage of covered employees with a record of investment-related investigations, consumer-initiated complaints, private civil litigations, or other regulatory proceedings | F55: 1
D56: FN-AC-270a.2 | E56: Total amount of monetary losses as a result of legal proceedings associated with marketing and communication of financial product-related information to new and returning customers | F56: 1
D57: FN-AC-270a.3 | E57: Description of approach to informing customers about products and services | F57: 1
D58: FN-AC-550a.2 | E58: Description of approach to incorporation of liquidity risk management programs into portfolio strategy and redemption risk management | F58: 2
D59: FN-AC-550a.3 | E59: Total exposure to securities financing transactions | F59: 2
D60: FN-AC-550a.4 | E60: Net exposure to written credit derivatives | F60: 2
A61: =Sample!A6 -> 15 | B61: =Sample!B6 -> AIG - American International Group Inc | C61: INSURANCE | D61: FN-IN-450a.1 | E61: Probable Maximum Loss (PML) of insured products from weather-related natural catastrophes | F61: 1
D62: FN-IN-450a.2 | E62: Total amount of monetary losses attributable to insurance payouts from (1) modeled natural catastrophes and (2) non-modeled natural catastrophes, by type of event and geographic segment (net and gross of reinsurance) | F62: 1
D63: FN-IN-450a.3 | E63: Description of approach to incorporation of environmental risks into (1) the underwriting process for individual contracts and (2) the management of firm-level risks and capital adequacy | F63: 1
D64: FN-IN-410a.1 | E64: Total invested assets, by industry and asset class | F64: 1
D65: FN-IN-410a.2 | E65: Description of approach to incorporation of environmental, social, and governance (ESG) factors in investment management processes and strategies | F65: 1
D66: FN-IN-410b.1 | E66: Net premiums written related to energy efficiency and low carbon technology | F66: 1
D67: FN-IN-410b.2 | E67: Discussion of products and/or product features that incentivize health, safety, and/or environmentally responsible actions and/or behaviors | F67: 1
D68: FN-IN-550a.1 | E68: Exposure to derivative instruments by category: (1) total potential exposure to non-centrally cleared derivatives, (2) total fair value of acceptable collateral posted with the Central Clearinghouse, and (3) total potential exposure to centrally cleared derivatives | F68: 1
D69: FN-IN-550a.2 | E69: Total fair value of securities lending collateral assets | F69: 1
D70: FN-IN-550a.3 | E70: Description of approach to managing capital- and liquidity-related risks associated with systemic non-insurance activities | F70: 1
D71: FN-IN-270a.1 | E71: Total amount of monetary losses as a result of legal proceedings associated with marketing and communication of insurance product-related information to new and returning customers | F71: 0
D72: FN-IN-270a.2 | E72: Complaints-to-claims ratio | F72: 0
D73: FN-IN-270a.3 | E73: Customer retention rate | F73: 0
D74: FN-IN-270a.4 | E74: Description of approach to informing customers about products | F74: 1
C75: ASSET MANAGEMENT & CUSTODY | D75: FN-AC-510a.1 | E75: Total amount of monetary losses as a result of legal proceedings associated with fraud, insider trading, anti-trust, anti-competitive behavior, market manipulation, malpractice, or other related financial industry laws or regulations | F75: 0
D76: FN-AC-510a.2 | E76: Description of whistleblower policies and procedures | F76: 1
D77: FN-AC-330a.1 | E77: Percentage of gender and racial/ethnic group representation for (1) executive management, (2) non-executive management, (3) professionals, and (4) all other employees | F77: 1
D78: FN-AC-410a.1 | E78: Amount of assets under management, by asset class, that employ (1) integration of environmental, social, and governance (ESG) issues, (2) sustainability themed investing, and (3) screening | F78: 1
D79: FN-AC-410a.2 | E79: Description of approach to incorporation of environmental, social, and governance (ESG) factors in investment and/or wealth management processes and strategies | F79: 1
D80: FN-AC-410a.3 | E80: Description of proxy voting and investee engagement policies and procedures | F80: 0
D81: FN-AC-270a.1 | E81: (1) Number and (2) percentage of covered employees with a record of investment-related investigations, consumer-initiated complaints, private civil litigations, or other regulatory proceedings | F81: 0
D82: FN-AC-270a.2 | E82: Total amount of monetary losses as a result of legal proceedings associated with marketing and communication of financial product-related information to new and returning customers | F82: 0
D83: FN-AC-270a.3 | E83: Description of approach to informing customers about products and services | F83: 0
A84: =Sample!A7 -> 17 | B84: =Sample!B7 -> Akamai Technologies Inc | C84: SOFTWARE & IT SERVICES | D84: TC-SI-220a.1 | E84: Description of policies and practices relating to behavioral advertising and user privacy | F84: 0
D85: TC-SI-220a.2 | E85: Number of users whose information is used for secondary purposes | F85: 0
D86: TC-SI-220a.3 | E86: Total amount of monetary losses as a result of legal proceedings associated with user privacy | F86: 0
D87: TC-SI-220a.4 | E87: (1) Number of law enforcement requests for user information, (2) number of users whose information was requested, (3) percentage resulting in disclosure | F87: 0
D88: TC-SI-220a.5 | E88: List of countries where core products or services are subject to government-required monitoring, blocking, content filtering, or censoring | F88: 0
D89: TC-SI-230a.1 | E89: (1) Number of data breaches, (2) percentage involving personally identifiable information (PII), (3) number of users affected | F89: 0
D90: TC-SI-230a.2 | E90: Description of approach to identifying and addressing data security risks, including use of third-party cybersecurity standards | F90: 0
D91: TC-SI-130a.1 | E91: (1) Total energy consumed, (2) percentage grid electricity, (3) percentage renewable | F91: 1
D92: TC-SI-130a.2 | E92: (1) Total water withdrawn, (2) total water consumed, percentage of each in regions with High or Extremely High Baseline Water Stress | F92: 1
D93: TC-SI-130a.3 | E93: Discussion of the integration of environmental considerations into strategic planning for data center needs | F93: 0
D94: TC-SI-520a.1 | E94: Total amount of monetary losses as a result of legal proceedings associated with anti-competitive behavior regulations | F94: 0
D95: TC-SI-550a.1 | E95: Number of (1) performance issues and (2) service disruptions; (3) total customer downtime | F95: 0
D96: TC-SI-550a.2 | E96: Description of business continuity risks related to disruptions of operations | F96: 0
... D99: TC-SI-330a.3 | E99: Percentage of gender and racial/ethnic group representation for (1) management, (2) technical staff, and (3) all other employees | F99: 0
A100: =Sample!A8 -> 21 | B100: =Sample!B8 -> Albemarle Corp | C100: CHEMICALS | D100: RT-CH-120a.1 | E100: Air emissions of the following pollutants: (1) NOX (excluding N2O), (2) SOX, (3) volatile organic compounds (VOCs), and (4) hazardous air pollutants (HAPs) | F100: 1
D101: RT-CH-210a.1 | E101: Discussion of engagement processes to manage risks and opportunities associated with community interests | F101: 0
D102: RT-CH-130a.1 | E102: (1) Total energy consumed, (2) percentage grid electricity, (3) percentage renewable, (4) total self-generated energy | F102: 1
D103: RT-CH-410c.1 | E103: Percentage of products by revenue that contain genetically modified organisms (GMOs) | F103: 0
D104: RT-CH-110a.1 | E104: Gross global Scope 1 emissions, percentage covered under emissions-limiting regulations | F104: 1
D105: RT-CH-110a.2 | E105: Discussion of long-term and short-term strategy or plan to manage Scope 1 emissions, emissions reduction targets, and an analysis of performance against those targets | F105: 1
D106: RT-CH-150a.1 | E106: Amount of hazardous waste generated, percentage recycled | F106: 1
D107: RT-CH-530a.1 | E107: Discussion of corporate positions related to government regulations and/or policy proposals that address environmental and social factors affecting the industry | F107: 0
...
