Workbook

Sheet Sample
A1: Line in Master | B1: Company Name | C1: Year | D1: Reporting Period | E1: Reporting Year | F1: Publication Year | G1: Press Release Date
A2: 10 | B2: AdvanSix Inc | C2: 2021 | D2: 2020 calendar year | E2: 2020 | F2: 2021 | G2: 44326
A3: 11 | B3: Aflac Inc | C3: 2020 | D3: 2018 | E3: 2018 | F3: 2020 | G3: 43894
A4: 12 | B4: Agilent Technologies Inc | C4: 2021 | D4: 11/1/2019 - 10/31/2020 | E4: 2020 | F4: 2021 | G4: 44399
A5: 14 | B5: AGNC Investment Corp | C5: 2021 | D5: 2020 calendar year | E5: 2020 | F5: 2021 | G5: 44270
A6: 15 | B6: AIG - American International Group Inc | C6: 2021 | D6: 2020 calendar year | E6: 2020 | F6: 2021 | G6: 44377
A7: 17 | B7: Akamai Technologies Inc | C7: 2021 | D7: 2020 calendar year | E7: 2020 | F7: 2021 | G7: 44221
A8: 21 | B8: Albemarle Corp | C8: 2020 | D8: 2019 calendar year | E8: 2019 | F8: 2020 | G8: 44063
A9: 27 | B9: Alliance Data Systems Corp | C9: 2020 | D9: 2020 calendar year | E9: 2020 | F9: 2020 | G9: 43991
A10: 28 | B10: Alliance Data Systems Corp | C10: 2019 | D10: 2019 calendar year | E10: 2019 | F10: 2019 | G10: 43643
A11: 29 | B11: Alliant Energy Corp | C11: 2020 | D11: 2020 | E11: 2020 | F11: 2020 | G11: 44397
A12: 30 | B12: Allison Transmission Holdings Inc | C12: 2021 | D12: 2020 | E12: 2020 | F12: 2021 | G12: 44305
A13: 35 | B13: Ameren Corp | C13: 2021 | D13: 2020 calendar year | E13: 2020 | F13: 2021 | G13: 44322
A14: 36 | B14: American Airlines Group Inc | C14: 2020 | D14: 2019 calendar year | E14: 2019 | F14: 2020 | G14: 44119
A15: 39 | B15: American Express Co | C15: 2020 | D15: 2019 calendar year | E15: 2019 | F15: 2020 | G15: 44104
A16: 40 | B16: American Homes 4 Rent | C16: 2021 | D16: 2020 calendar year | E16: 2020 | F16: 2021 | G16: 44314
A17: 42 | B17: American Tower Corp | C17: 2020 | D17: 2019 calendar year | E17: 2019 | F17: 2020 | G17: 44036
A18: 48 | B18: Amphenol Corp | C18: 2021 | D18: 2020 calendar year | E18: 2020 | F18: 2021 | G18: 44361
A19: 49 | B19: Amphenol Corp | C19: 2020 | D19: 2019 calendar year | E19: 2019 | F19: 2020 | G19: 43985
A20: 50 | B20: Amphenol Corp | C20: 2019 | D20: 2018 calendar year | E20: 2018 | F20: 2019 | G20: 43711
A21: 51 | B21: Amyris Inc | C21: 2021 | D21: 2020 calendar year | E21: 2020 | F21: 2021 | G21: 44390
A22: 52 | B22: Annaly Capital Management Inc | C22: 2021 | D22: 2020 calendar year | E22: 2020 | F22: 2021 | G22: 44385
A23: 53 | B23: Annaly Capital Management Inc | C23: 2020 | D23: 2019 calendar year | E23: 2019 | F23: 2020 | G23: 44112
A24: 55 | B24: Antero Midstream | C24: 2020 | D24: 2019 | E24: 2019 | F24: 2020 | G24: 44109
A25: 56 | B25: Antero Resources Corp | C25: 2020 | D25: 2019 | E25: 2019 | F25: 2020 | G25: 44109
A26: 58 | B26: Apache Corp | C26: 2020 | D26: 2019 calendar year | E26: 2019 | F26: 2020 | G26: 44104
A27: 69 | B27: Arconic Corp | C27: 2020 | D27: 2019 | E27: 2019 | F27: 2020 | G27: 43993
A28: 70 | B28: Arcosa, Inc | C28: 2021 | D28: 2020 | E28: 2020 | F28: 2021 | G28: 44305
A29: 71 | B29: Arena Pharmaceuticals Inc | C29: 2021 | D29: 2020 | E29: 2020 | F29: 2021 | G29: 44305
A30: 75 | B30: Ashland LLC | C30: 2021 | D30: 2019 | E30: 2019 | F30: 2021 | G30: 44104
A31: 78 | B31: Atkore International | C31: 2021 | D31: 10/1/2018-9/1/2020 | E31: 2020 | F31: 2021 | G31: 44221
A32: 82 | B32: AvalonBay Communities Inc | C32: 2021 | D32: 2020 calendar year | E32: 2020 | F32: 2021 | G32: 44390
A33: 89 | B33: Barnes Group Inc | C33: 2021 | D33: 2020 calendar year | E33: 2020 | F33: 2021 | G33: 44291
A34: 90 | B34: Baxter International Inc | C34: 2020 | D34: 2019 calendar year | E34: 2019 | F34: 2020 | G34: 44151
A35: 91 | B35: Becton Dickinson and Co | C35: 2021 | D35: 10/1/2019-9/30/2020 | E35: 2020 | F35: 2021 | G35: 44369
A36: 94 | B36: Berry Plastics Group Inc | C36: 2021 | D36: 2020 | E36: 2020 | F36: 2021 | G36: 44259
A37: 98 | B37: Blackbaud, Inc. | C37: 2021 | D37: 2020 calendar year | E37: 2020 | F37: 2021 | G37: 44305
A38: 102 | B38: Bloom Energy Corp | C38: 2021 | D38: 2020 | E38: 2020 | F38: 2021 | G38: 44301
A39: 119 | B39: Bunge Ltd | C39: 2021 | D39: 2020 calendar year | E39: 2020 | F39: 2021 | G39: 44342
A40: 120 | B40: Burlington Stores Inc | C40: 2020 | D40: 2020 fiscal year (1/30/202020-1/30/2021) | E40: 2021 | F40: 2020 | G40: 44431
A41: 121 | B41: Cabot Corp | C41: 2021 | D41: 2020 calendar year | E41: 2020 | F41: 2021 | G41: 44375
A42: 123 | B42: Cabot Oil & Gas Corp | C42: 2020 | D42: 2019 calendar year | E42: 2019 | F42: 2020 | G42: 44012
A43: 124 | B43: Calavo Growers Inc | C43: 2021 | D43: 2020 calendar year | E43: 2020 | F43: 2021 | G43: 44393
A44: 126 | B44: California Water Service Group | C44: 2021 | D44: 2020 calendar year | E44: 2020 | F44: 2021 | G44: 44301
A45: 127 | B45: Callon Petroleum Co | C45: 2021 | D45: 2020 calendar year | E45: 2020 | F45: 2021 | G45: 44405
A46: 128 | B46: Callon Petroleum Co | C46: 2020 | D46: 2019 calendar year | E46: 2019 | F46: 2020 | G46: 44103
A47: 130 | B47: Cardinal Health Inc | C47: 2021 | D47: 7/1/2019-6/30/2020 | E47: 2020 | F47: 2021 | G47: 44225
A48: 131 | B48: Carrier Global Corp | C48: 2020 | D48: 2019 calendar year | E48: 2019 | F48: 2020 | G48: 44039
A49: 132 | B49: Catalent Inc | C49: 2021 | D49: 7/1/2020-6/30/2021 | E49: 2021 | F49: 2021 | G49: 44329
A50: 133 | B50: Catalent Inc | C50: 2020 | D50: 7/1/2018-6/30/2019 | E50: 2019 | F50: 2020 | G50: 43934
... A53: 146 | B53: CH Robinson Worldwide Inc | C53: 2021 | D53: 2020 calendar year | E53: 2020 | F53: 2021 | G53: 44327
A54: 147 | B54: Charah Solutions Inc | C54: 2021 | D54: 2020 | E54: 2020 | F54: 2021 | G54: 44270
A55: 149 | B55: Chart Industries Inc | C55: 2021 | D55: 2020 | E55: 2020 | F55: 2021 | G55: 44293
A56: 152 | B56: Chemours Co/The | C56: 2020 | D56: 2019 calendar year | E56: 2019 | F56: 2020 | G56: 44104
A57: 154 | B57: Cheniere Energy Partners LP | C57: 2021 | D57: 2020 calendar year | E57: 2020 | F57: 2021 | G57: 44376
A58: 157 | B58: Chipotle Mexican Grill Inc | C58: 2021 | D58: 2020 calendar year | E58: 2020 | F58: 2021 | G58: 44301
A59: 164 | B59: Citigroup Inc (Citi) | C59: 2021 | D59: 2020 calendar year | E59: 2020 | F59: 2021 | G59: 44312
A60: 165 | B60: Citizens Financial Group Inc | C60: 2021 | D60: 2020 calendar year | E60: 2020 | F60: 2021 | G60: 44376
A61: 173 | B61: CNX Resources Corp | C61: 2021 | D61: 2020 calendar year | E61: 2020 | F61: 2021 | G61: 44399
A62: 176 | B62: Coeur Mining Inc | C62: 2020 | D62: 2019 | E62: 2019 | F62: 2020 | G62: 43949
A63: 178 | B63: Columbia Sportswear Co | C63: 2021 | D63: 2020 calendar year | E63: 2020 | F63: 2021 | G63: 44405
A64: 184 | B64: CommScope Holding Co Inc | C64: 2021 | D64: 2020 calendar year | E64: 2020 | F64: 2021 | G64: 44354
A65: 188 | B65: ConAgra Foods Inc | C65: 2020 | D65: 2020 Fiscal year (5/25/2019 - 5/25/2020) | E65: 2020 | F65: 2020 | G65: 44193
A66: 190 | B66: Conduent Inc. | C66: 2021 | D66: 2020 calendar year | E66: 2020 | F66: 2021 | G66: 44228
A67: 194 | B67: Cooper Cos Inc/The | C67: 2021 | D67: 10/1/2019-5/1/2020 | E67: 2020 | F67: 2021 | G67: 44362
A68: 195 | B68: Cooper-Standard Holdings Inc | C68: 2021 | D68: 2020 calendar year | E68: 2020 | F68: 2021 | G68: 44335
A69: 200 | B69: Crestwood Equity Partners LP | C69: 2021 | D69: 2020 calendar year | E69: 2020 | F69: 2021 | G69: 44354
A70: 201 | B70: Crestwood Equity Partners LP | C70: 2020 | D70: 2019 calendar year | E70: 2019 | F70: 2020 | G70: 43985
A71: 202 | B71: Crown Castle International Corp | C71: 2020 | D71: 2019 calendar year | E71: 2019 | F71: 2020 | G71: 44183
A72: 205 | B72: CSX Corp | C72: 2020 | D72: 2019 calendar year | E72: 2019 | F72: 2020 | G72: 44043
A73: 206 | B73: Cummins Inc. | C73: 2020 | D73: 2019 calendar year | E73: 2019 | F73: 2020 | G73: 44028
A74: 207 | B74: Cushman & Wakefield PLC | C74: 2021 | D74: 2020 calendar year | E74: 2020 | F74: 2021 | G74: 44385
... A102: 304 | B102: Flex Ltd | C102: 2020 | D102: 2019 calendar year | E102: 2019 | F102: 2020 | G102: 44055
A103: 306 | B103: Flowserve Corp | C103: 2020 | D103: 2019 | E103: 2019 | F103: 2020 | G103: 44144
A104: 310 | B104: Foot Locker Inc | C104: 2021 | D104: 2/3/2019-1/30/2021 | E104: 2021 | F104: 2021 | G104: 44294
A105: 325 | B105: General Mills Inc | C105: 2021 | D105: 5/30/2020-5/30/2021 | E105: 2021 | F105: 2021 | G105: 44308
A106: 326 | B106: General Mills Inc | C106: 2020 | D106: 5/21/2018-5/21/2019 | E106: 2019 | F106: 2020 | G106: 43941
A107: 328 | B107: General Motors Co (GM) | C107: 2021 | D107: 2020 | E107: 2020 | F107: 2021 | G107: 44316
A108: 329 | B108: General Motors Co (GM) | C108: 2020 | D108: 2019 | E108: 2019 | F108: 2020 | G108: 44028
A109: 330 | B109: General Motors Co (GM) | C109: 2019 | D109: 2018 | E109: 2018 | F109: 2019 | G109: 43643
A110: 333 | B110: Gentherm Inc | C110: 2021 | D110: 2020 calendar year | E110: 2020 | F110: 2021 | G110: 44293
A111: 341 | B111: Graphic Packaging Holding Co | C111: 2021 | D111: 2020 calendar year | E111: 2020 | F111: 2021 | G111: 44413
A112: 342 | B112: Graphic Packaging Holding Co | C112: 2020 | D112: 2019 calendar year | E112: 2019 | F112: 2020 | G112: 44155
A113: 343 | B113: Greenbrier Cos Inc/The | C113: 2020 | D113: 9/1/2018– 8/1/ 2020 | E113: 2020 | F113: 2020 | G113: 44137
A114: 344 | B114: Greif Inc. | C114: 2021 | D114: 11/1/2019 - 10/31/2020 | E114: 2020 | F114: 2021 | G114: 44346
A115: 346 | B115: Guess?, Inc. | C115: 2021 | D115: 2021 | E115: 2021 | F115: 2021 | G115: 44397
A116: 353 | B116: Harsco Corp | C116: 2021 | D116: 2020 calendar year | E116: 2020 | F116: 2021 | G116: 44335
A117: 354 | B117: Harsco Corp | C117: 2020 | D117: 2019 calendar year | E117: 2019 | F117: 2020 | G117: 44039
A118: 356 | B118: Hawaiian Electric Industries Inc | C118: 2021 | D118: 2020 | E118: 2020 | F118: 2021 | G118: 44308
A119: 358 | B119: Hawaiian Holdings Inc | C119: 2020 | D119: 2019 | E119: 2019 | F119: 2020 | G119: 44181
A120: 359 | B120: Healthpeak Properties Inc | C120: 2021 | D120: 2020 calendar year | E120: 2020 | F120: 2021 | G120: 44390
A121: 360 | B121: Healthpeak Properties Inc | C121: 2020 | D121: 2019 calendar year | E121: 2019 | F121: 2020 | G121: 44018
A122: 366 | B122: Hershey Co/The | C122: 2021 | D122: 2020 | E122: 2020 | F122: 2021 | G122: 44349
A123: 367 | B123: Hershey Co/The | C123: 2020 | D123: 2019 | E123: 2019 | F123: 2020 | G123: 43984
A124: 368 | B124: Hess Corp | C124: 2021 | D124: 2020 calendar year | E124: 2020 | F124: 2021 | G124: 44398
A125: 370 | B125: Hess Corp | C125: 2019 | D125: 2018 calendar year | E125: 2018 | F125: 2019 | G125: 43654
A126: 372 | B126: Hewlett Packard Enterprise Co | C126: 2020 | D126: 10/1/2018-10/31/2019 | E126: 2019 | F126: 2020 | G126: 43997
A127: 379 | B127: Hologic Inc | C127: 2021 | D127: 2020 | E127: 2020 | F127: 2021 | G127: 44231
A128: 381 | B128: Home Depot Inc/The | C128: 2020 | D128: 2/4/2019-2/2/2020 | E128: 2020 | F128: 2020 | G128: 44035
A129: 389 | B129: Howmet Aerospace Inc | C129: 2021 | D129: 2020 calendar year | E129: 2020 | F129: 2021 | G129: 44335
...

Sheet Compustat Links
A1: SASB Sample Name | B1: cusip | C1: Latest Annual datadate | D1: gvkey | E1: conm | F1: tic | G1: cik | H1: Name Match | I1: Checked? (1 if the SASB name does match with Compustat name) | J1: Note
A2: AdvanSix Inc | B2: 00773T101 | C2: 46022 | D2: 028070 | E2: ADVANSIX INC | F2: ASIX | G2: 1673985 | H2: =IF(E2=A2,1,"Check") -> 1 | I2: 1
A3: Aflac Inc | B3: 1055102 | C3: 46022 | D3: 001449 | E3: AFLAC INC | F3: AFL | G3: 4977 | H3: =IF(E3=A3,1,"Check") -> 1 | I3: 1
A4: Agilent Technologies Inc | B4: 00846U101 | C4: 45961 | D4: 126554 | E4: AGILENT TECHNOLOGIES INC | F4: A | G4: 1090872 | H4: =IF(E4=A4,1,"Check") -> 1 | I4: 1
A5: AGNC Investment Corp | B5: 00123Q104 | C5: 46022 | D5: 179889 | E5: AGNC INVESTMENT CORP | F5: AGNC | G5: 1423689 | H5: =IF(E5=A5,1,"Check") -> 1 | I5: 1
A6: AIG - American International Group Inc | B6: 26874784 | C6: 46022 | D6: 001487 | E6: AMERICAN INTERNATIONAL GROUP | F6: AIG | G6: 5272 | H6: =IF(E6=A6,1,"Check") -> Check | I6: 1
A7: Akamai Technologies Inc | B7: 00971T101 | C7: 46022 | D7: 125595 | E7: AKAMAI TECHNOLOGIES INC | F7: AKAM | G7: 1086222 | H7: =IF(E7=A7,1,"Check") -> 1 | I7: 1
A8: Albemarle Corp | B8: 12653101 | C8: 46022 | D8: 029751 | E8: ALBEMARLE CORP | F8: ALB | G8: 915913 | H8: =IF(E8=A8,1,"Check") -> 1 | I8: 1
A9: Alliance Data Systems Corp | B9: 18581108 | C9: 46022 | D9: 143974 | E9: BREAD FINANCIAL HOLDINGS INC | F9: BFH | G9: 1101215 | H9: =IF(E9=A9,1,"Check") -> Check | I9: Name change Alliance Data Systems Corporation -> Bread Financial in 2022
A10: Alliant Energy Corp | B10: 18802108 | C10: 46022 | D10: 011554 | E10: ALLIANT ENERGY CORP | F10: LNT | G10: 352541 | H10: =IF(E10=A10,1,"Check") -> 1 | I10: 1
A11: Allison Transmission Holdings Inc | B11: 01973R101 | C11: 46022 | D11: 177966 | E11: ALLISON TRANSMISSION HLDGS | F11: ALSN | G11: 1411207 | H11: =IF(E11=A11,1,"Check") -> Check | I11: 1
A12: Ameren Corp | B12: 23608102 | C12: 46022 | D12: 010860 | E12: AMEREN CORP | F12: AEE | G12: 1002910 | H12: =IF(E12=A12,1,"Check") -> 1 | I12: 1
A13: American Airlines Group Inc | B13: 02376R102 | C13: 46022 | D13: 001045 | E13: AMERICAN AIRLINES GROUP INC | F13: AAL | G13: 6201 | H13: =IF(E13=A13,1,"Check") -> 1 | I13: 1
A14: American Express Co | B14: 25816109 | C14: 46022 | D14: 001447 | E14: AMERICAN EXPRESS CO | F14: AXP | G14: 4962 | H14: =IF(E14=A14,1,"Check") -> 1 | I14: 1
A15: American Homes 4 Rent | B15: 02665T306 | C15: 46022 | D15: 017639 | E15: AMERICAN HOMES 4 RENT | F15: AMH | G15: 1562401 | H15: =IF(E15=A15,1,"Check") -> 1 | I15: 1
A16: American Tower Corp | B16: 03027X100 | C16: 46022 | D16: 105365 | E16: AMERICAN TOWER CORP | F16: AMT | G16: 1053507 | H16: =IF(E16=A16,1,"Check") -> 1 | I16: 1
A17: Amphenol Corp | B17: 32095101 | C17: 46022 | D17: 014282 | E17: AMPHENOL CORP | F17: APH | G17: 820313 | H17: =IF(E17=A17,1,"Check") -> 1 | I17: 1
A18: Amyris Inc | B18: 03236M200 | C18: 44926 | D18: 184717 | E18: AMYRIS INC | F18: AMRSQ | G18: 1365916 | H18: =IF(E18=A18,1,"Check") -> 1 | I18: 1
A19: Annaly Capital Management Inc | B19: 35710839 | C19: 46022 | D19: 065556 | E19: ANNALY CAPITAL MANAGEMENT | F19: NLY | G19: 1043219 | H19: =IF(E19=A19,1,"Check") -> Check | I19: 1
A20: Antero Midstream | B20: 03676B102 | C20: 46022 | D20: 031109 | E20: ANTERO MIDSTREAM CORP | F20: AM | G20: 1623925 | H20: =IF(E20=A20,1,"Check") -> Check | I20: name change - Antero Midstream became Antero Midstream Partners LP in 2014 after IPO
A21: Antero Resources Corp | B21: 03674X106 | C21: 46022 | D21: 018465 | E21: ANTERO RESOURCES CORP | F21: AR | G21: 1433270 | H21: =IF(E21=A21,1,"Check") -> 1 | I21: 1
A22: Apache Corp | B22: 03743Q108 | C22: 46022 | D22: 001678 | E22: APA CORP | F22: APA | G22: 1841666 | H22: =IF(E22=A22,1,"Check") -> Check | I22: Apache Corporation is a direct, wholly-owned subsidiary of APA
A23: Arconic Corp | B23: 03966V107 | C23: 44926 | D23: 035978 | E23: ARCONIC CORP | F23: ARNC | G23: 1790982 | H23: =IF(E23=A23,1,"Check") -> 1 | I23: 1 | J23: The company starts to trade in 2020 April, the shares outstanding in March 2019 is replaced as 109,021,376 (disclosed in its 2020 10-K https://www.sec.gov/Archives/edgar/data/1790982/000179098220000022/arconic10k.htm). The stock price is replaced as 6.92, the closing price of the first day of trade (April 1, 2020)
A24: Arcosa, Inc | B24: 39653100 | C24: 46022 | D24: 328795 | E24: ARCOSA INC | F24: ACA | G24: 1739445 | H24: =IF(E24=A24,1,"Check") -> Check | I24: 1
A25: Arena Pharmaceuticals Inc | B25: 40047607 | C25: 44561 | D25: 138122 | E25: ARENA PHARMACEUTICALS INC | F25: ARNA | G25: 1080709 | H25: =IF(E25=A25,1,"Check") -> 1 | I25: 1
A26: Ashland LLC | B26: 44186104 | C26: 45930 | D26: 001794 | E26: ASHLAND INC | F26: ASH | G26: 1674862 | H26: =IF(E26=A26,1,"Check") -> Check | I26: 1
A27: Atkore International | B27: 47649108 | C27: 45930 | D27: 027014 | E27: ATKORE INTERNATIONAL GROUP INC | F27: ATKR | G27: 1666138 | H27: Check | I27: 1 | J27: Update
A28: AvalonBay Communities Inc | B28: 53484101 | C28: 46022 | D28: 029875 | E28: AVALONBAY COMMUNITIES INC | F28: AVB | G28: 915912 | H28: =IF(E28=A28,1,"Check") -> 1 | I28: 1
A29: Barnes Group Inc | B29: 67806109 | C29: 45291 | D29: 002049 | E29: BARNES GROUP INC | F29: B.2 | G29: 9984 | H29: =IF(E29=A29,1,"Check") -> 1 | I29: 1
A30: Baxter International Inc | B30: 71813109 | C30: 46022 | D30: 002086 | E30: BAXTER INTERNATIONAL INC | F30: BAX | G30: 10456 | H30: =IF(E30=A30,1,"Check") -> 1 | I30: 1
A31: Becton Dickinson and Co | B31: 75887109 | C31: 45930 | D31: 002111 | E31: BECTON DICKINSON & CO | F31: BDX | G31: 10795 | H31: =IF(E31=A31,1,"Check") -> Check | I31: 1
A32: Berry Plastics Group Inc | B32: 08579X101 | C32: 45657 | D32: 013431 | E32: BERRY CORP | F32: BRY | G32: 1705873 | H32: =IF(E32=A32,1,"Check") -> Check | I32: Name change - Berry Plastics Group, Inc. changed its name to Berry Global Group, Inc. in 2017
A33: Blackbaud, Inc. | B33: 09227Q100 | C33: 46022 | D33: 260893 | E33: BLACKBAUD INC | F33: BLKB | G33: 1280058 | H33: =IF(E33=A33,1,"Check") -> Check | I33: 1
A34: Bloom Energy Corp | B34: 93712107 | C34: 46022 | D34: 033668 | E34: BLOOM ENERGY CORP | F34: BE | G34: 1664703 | H34: =IF(E34=A34,1,"Check") -> 1 | I34: 1
A35: Bunge Ltd | B35: H11356104 | C35: 46022 | D35: 144435 | E35: BUNGE GLOBAL SA | F35: BG | G35: 1996862 | H35: =IF(E35=A35,1,"Check") -> Check | I35: Name change - Bunge Ltd changed to Bunge Global SA
A36: Burlington Stores Inc | B36: 122017106 | C36: 46053 | D36: 018675 | E36: BURLINGTON STORES INC | F36: BURL | G36: 1579298 | H36: =IF(E36=A36,1,"Check") -> 1 | I36: 1
A37: Cabot Corp | B37: 127055101 | C37: 45930 | D37: 002593 | E37: CABOT CORP | F37: CBT | G37: 16040 | H37: =IF(E37=A37,1,"Check") -> 1 | I37: 1
A38: Cabot Oil & Gas Corp | B38: 127097103 | C38: 46022 | D38: 020548 | E38: COTERRA ENERGY INC | F38: CTRA | G38: 858470 | H38: =IF(E38=A38,1,"Check") -> Check | I38: Name change - Cabot Oil & Gas changed to Coterra Energy
A39: Calavo Growers Inc | B39: 128246105 | C39: 45961 | D39: 147708 | E39: CALAVO GROWERS INC | F39: CVGW | G39: 1133470 | H39: =IF(E39=A39,1,"Check") -> 1 | I39: 1
A40: California Water Service Group | B40: 130788102 | C40: 46022 | D40: 002628 | E40: CALIFORNIA WATER SERVICE GP | F40: CWT | G40: 1035201 | H40: =IF(E40=A40,1,"Check") -> Check | I40: 1
A41: Callon Petroleum Co | B41: 13123X508 | C41: 45291 | D41: 015060 | E41: CALLON PETROLEUM CO/DE | F41: CPE | G41: 928022 | H41: =IF(E41=A41,1,"Check") -> Check | I41: 1
A42: Cardinal Health Inc | B42: 14149Y108 | C42: 45838 | D42: 002751 | E42: CARDINAL HEALTH INC | F42: CAH | G42: 721371 | H42: =IF(E42=A42,1,"Check") -> 1 | I42: 1
A43: Carrier Global Corp | B43: 14448C104 | C43: 46022 | D43: 036191 | E43: CARRIER GLOBAL CORP | F43: CARR | G43: 1783180 | H43: =IF(E43=A43,1,"Check") -> 1 | I43: 1 | J43: starts to trade on April 3 2020 -> The shares outstainding is replaced as 866,158,910 shares as if on the spin-off day (in 10-K https://www.sec.gov/ix?doc=/Archives/edgar/data/0001783180/000178318021000011/carr-20201231.htm), the stock price is replaced as the closing price of the first date of trading (April 3, 2020)
A44: Catalent Inc | B44: 148806102 | C44: 45473 | D44: 020228 | E44: CATALENT INC | F44: CTLT | G44: 1596783 | H44: =IF(E44=A44,1,"Check") -> 1 | I44: 1
A45: Caterpillar Inc | B45: 149123101 | C45: 46022 | D45: 002817 | E45: CATERPILLAR INC | F45: CAT | G45: 18230 | H45: =IF(E45=A45,1,"Check") -> 1 | I45: 1
A46: Century Communities Inc | B46: 156504300 | C46: 46022 | D46: 018004 | E46: CENTURY COMMUNITIES INC | F46: CCS | G46: 1576940 | H46: =IF(E46=A46,1,"Check") -> 1 | I46: 1
A47: CH Robinson Worldwide Inc | B47: 12541W209 | C47: 45657 | D47: 065609 | E47: C H ROBINSON WORLDWIDE INC | F47: CHRW | G47: 1043277 | H47: =IF(E47=A47,1,"Check") -> Check | I47: 1
A48: Charah Solutions Inc | B48: 15957P303 | C48: 44926 | D48: 033596 | E48: CHARAH SOLUTIONS | F48: CHRA | G48: 1730346 | H48: =IF(E48=A48,1,"Check") -> Check | I48: 1
A49: Chart Industries Inc | B49: 16115Q308 | C49: 45657 | D49: 025964 | E49: CHART INDUSTRIES INC | F49: GTLS | G49: 892553 | H49: =IF(E49=A49,1,"Check") -> 1 | I49: 1
A50: Chemours Co/The | B50: 163851108 | C50: 46022 | D50: 022741 | E50: CHEMOURS CO | F50: CC | G50: 1627223 | H50: =IF(E50=A50,1,"Check") -> Check | I50: 1
A51: Cheniere Energy Partners LP | B51: 16411Q101 | C51: 43830 | D51: 176914 | E51: CHENIERE ENERGY PARTNERS LP | F51: CQP | G51: 1383650 | H51: =IF(E51=A51,1,"Check") -> 1 | I51: 1
A52: Chipotle Mexican Grill Inc | B52: 169656105 | C52: 46022 | D52: 165914 | E52: CHIPOTLE MEXICAN GRILL INC | F52: CMG | G52: 1058090 | H52: =IF(E52=A52,1,"Check") -> 1 | I52: 1
A53: Citigroup Inc (Citi) | B53: 172967424 | C53: 46022 | D53: 003243 | E53: CITIGROUP INC | F53: C | G53: 831001 | H53: =IF(E53=A53,1,"Check") -> Check | I53: 1
A54: Citizens Financial Group Inc | B54: 174610105 | C54: 46022 | D54: 021825 | E54: CITIZENS FINANCIAL GROUP INC | F54: CFG | G54: 759944 | H54: =IF(E54=A54,1,"Check") -> 1 | I54: 1
A55: CNX Resources Corp | B55: 12653C108 | C55: 46022 | D55: 120093 | E55: CNX RESOURCES CORP | F55: CNX | G55: 1070412 | H55: =IF(E55=A55,1,"Check") -> 1 | I55: 1
A56: Coeur Mining Inc | B56: 192108504 | C56: 46022 | D56: 003153 | E56: COEUR MINING INC | F56: CDE | G56: 215466 | H56: =IF(E56=A56,1,"Check") -> 1 | I56: 1
A57: Columbia Sportswear Co | B57: 198516106 | C57: 46022 | D57: 105936 | E57: COLUMBIA SPORTSWEAR CO | F57: COLM | G57: 1050797 | H57: =IF(E57=A57,1,"Check") -> 1 | I57: 1
A58: CommScope Holding Co Inc | B58: 20337X109 | C58: 45657 | D58: 018036 | E58: VISTANCE NETWORKS INC | F58: VISN | G58: 1517228 | H58: =IF(E58=A58,1,"Check") -> Check | I58: Restructure - CommScope Holding Company, Inc. has restructured and became VISTANCE NETWORKS INC in 2026
A59: ConAgra Foods Inc | B59: 205887102 | C59: 45808 | D59: 003362 | E59: CONAGRA BRANDS INC | F59: CAG | G59: 23217 | H59: =IF(E59=A59,1,"Check") -> Check | I59: name change - In 2016, ConAgra changed its name to "Conagra Brands"
A60: Conduent Inc. | B60: 206787103 | C60: 46022 | D60: 028719 | E60: CONDUENT INC | F60: CNDT | G60: 1677703 | H60: =IF(E60=A60,1,"Check") -> Check | I60: 1
A61: Cooper Cos Inc/The | B61: 216648501 | C61: 45961 | D61: 003504 | E61: COOPER COS INC (THE) | F61: COO | G61: 711404 | H61: =IF(E61=A61,1,"Check") -> Check | I61: 1
A62: Cooper-Standard Holdings Inc | B62: 21676P103 | C62: 46022 | D62: 163765 | E62: COOPER-STANDARD HOLDINGS INC | F62: CPS | G62: 1320461 | H62: =IF(E62=A62,1,"Check") -> 1 | I62: 1
A63: Crestwood Equity Partners LP | B63: 226344208 | C63: 44926 | D63: 162894 | E63: CRESTWOOD EQUITY PARTNERS LP | F63: CEQP | G63: 1136352 | H63: =IF(E63=A63,1,"Check") -> 1 | I63: 1
A64: Crown Castle International Corp | B64: 22822V101 | C64: 46022 | D64: 113490 | E64: CROWN CASTLE INC | F64: CCI | G64: 1051470 | H64: =IF(E64=A64,1,"Check") -> Check | I64: name change - Crown Castle International Corp changed its name to Crown Castle Inc on August 1, 2022
A65: CSX Corp | B65: 126408103 | C65: 46022 | D65: 002574 | E65: CSX CORP | F65: CSX | G65: 277948 | H65: =IF(E65=A65,1,"Check") -> 1 | I65: 1
A66: Cummins Inc. | B66: 231021106 | C66: 46022 | D66: 003650 | E66: CUMMINS INC | F66: CMI | G66: 26172 | H66: =IF(E66=A66,1,"Check") -> Check | I66: 1
A67: Cushman & Wakefield PLC | B67: G2717C106 | C67: 46022 | D67: 033809 | E67: CUSHMAN & WAKEFIELD | F67: CWK | G67: 1628369 | H67: =IF(E67=A67,1,"Check") -> Check | I67: 1
A68: CVS Health Corp | B68: 126650100 | C68: 46022 | D68: 007241 | E68: CVS HEALTH CORP | F68: CVS | G68: 64803 | H68: =IF(E68=A68,1,"Check") -> 1 | I68: 1
A69: CyrusOne Inc | B69: 23283R100 | C69: 44561 | D69: 016116 | E69: CYRUSONE INC | F69: CONE | G69: 1553023 | H69: =IF(E69=A69,1,"Check") -> 1 | I69: 1
A70: Danaher Corp | B70: 235851102 | C70: 46022 | D70: 003735 | E70: DANAHER CORP | F70: DHR | G70: 313616 | H70: =IF(E70=A70,1,"Check") -> 1 | I70: 1
A71: Darling Ingredients Inc. | B71: 237266101 | C71: 45657 | D71: 030651 | E71: DARLING INGREDIENTS INC | F71: DAR | G71: 916540 | H71: =IF(E71=A71,1,"Check") -> Check | I71: 1
A72: Deere & Co. | B72: 244199105 | C72: 45961 | D72: 003835 | E72: DEERE & CO | F72: DE | G72: 315189 | H72: =IF(E72=A72,1,"Check") -> Check | I72: 1
A73: Devon Energy Corp | B73: 25179M103 | C73: 46022 | D73: 014934 | E73: DEVON ENERGY CORP | F73: DVN | G73: 1090012 | H73: =IF(E73=A73,1,"Check") -> 1 | I73: 1
A74: DigitalBridge Group Inc | B74: 25401T603 | C74: 45657 | D74: 183603 | E74: DIGITALBRIDGE GROUP INC | F74: DBRG | G74: 1679688 | H74: =IF(E74=A74,1,"Check") -> 1 | I74: 1
A75: Dominion Energy Inc | B75: 25746U109 | C75: 46022 | D75: 004029 | E75: DOMINION ENERGY INC | F75: D | G75: 715957 | H75: =IF(E75=A75,1,"Check") -> 1 | I75: 1
A76: Dow Inc | B76: 260557103 | C76: 46022 | D76: 034443 | E76: DOW INC | F76: DOW | G76: 1751788 | H76: =IF(E76=A76,1,"Check") -> 1 | I76: 1
A77: DuPont de Nemours Inc | B77: 26614N102 | C77: 46022 | D77: 004060 | E77: DUPONT DE NEMOURS INC | F77: DD | G77: 1666700 | H77: =IF(E77=A77,1,"Check") -> 1 | I77: 1
A78: Eagle Bulk Shipping Inc | B78: Y2187A150 | C78: 45291 | D78: 163685 | E78: EAGLE BULK SHIPPING INC | F78: EGLE.3 | G78: 1322439 | H78: =IF(E78=A78,1,"Check") -> 1 | I78: 1
A79: Ecolab Inc | B79: 278865100 | C79: 46022 | D79: 004213 | E79: ECOLAB INC | F79: ECL | G79: 31462 | H79: =IF(E79=A79,1,"Check") -> 1 | I79: 1
A80: eHealth Inc | B80: 28238P109 | C80: 45657 | D80: 174389 | E80: EHEALTH INC | F80: EHTH | G80: 1333493 | H80: =IF(E80=A80,1,"Check") -> 1 | I80: 1
A81: Energy Recovery | B81: 29270J100 | C81: 46022 | D81: 179738 | E81: ENERGY RECOVERY INC | F81: ERII | G81: 1421517 | H81: =IF(E81=A81,1,"Check") -> Check | I81: 1
A82: Envista Holdings Corp | B82: 29415F104 | C82: 46022 | D82: 035497 | E82: ENVISTA HOLDINGS CORP | F82: NVST | G82: 1757073 | H82: =IF(E82=A82,1,"Check") -> 1 | I82: 1
A83: Enviva | B83: 29415B103 | C83: 45291 | D83: 023296 | E83: ENVIVA INC | F83: EVVAQ | G83: 1592057 | H83: =IF(E83=A83,1,"Check") -> Check | I83: 1
A84: EQT Corp | B84: 26884L109 | C84: 46022 | D84: 004430 | E84: EQT CORP | F84: EQT | G84: 33213 | H84: =IF(E84=A84,1,"Check") -> 1 | I84: 1
A85: Equitrans Midstream Corp | B85: 294600101 | C85: 45291 | D85: 034337 | E85: EQUITRANS MID CORP | F85: ETRN | G85: 1747009 | H85: =IF(E85=A85,1,"Check") -> Check | I85: 1
A86: Essential Utilities Inc | B86: 29670G102 | C86: 45657 | D86: 008542 | E86: ESSENTIAL UTILITIES INC | F86: WTRG | G86: 78128 | H86: =IF(E86=A86,1,"Check") -> 1 | I86: 1
A87: Essex Property Trust Inc | B87: 297178105 | C87: 46022 | D87: 030293 | E87: ESSEX PROPERTY TRUST | F87: ESS | G87: 920522 | H87: =IF(E87=A87,1,"Check") -> Check | I87: 1
A88: Estee Lauder Cos Inc/The | B88: 518439104 | C88: 45838 | D88: 061567 | E88: ESTEE LAUDER COMPANIES INC | F88: EL | G88: 1001250 | H88: =IF(E88=A88,1,"Check") -> Check | I88: 1
A89: Exelon Corp | B89: 30161N101 | C89: 46022 | D89: 008539 | E89: EXELON CORP | F89: EXC | G89: 1109357 | H89: =IF(E89=A89,1,"Check") -> 1 | I89: 1
A90: FedEx Corp | B90: 31428X106 | C90: 45808 | D90: 004598 | E90: FEDEX CORP | F90: FDX | G90: 1048911 | H90: =IF(E90=A90,1,"Check") -> 1 | I90: 1
A91: Fifth Third Bancorp | B91: 316773100 | C91: 46022 | D91: 004640 | E91: FIFTH THIRD BANCORP | F91: FITB | G91: 35527 | H91: =IF(E91=A91,1,"Check") -> 1 | I91: 1
A92: Flex Ltd | B92: Y2573F102 | C92: 45747 | D92: 030170 | E92: FLEX LTD | F92: FLEX | G92: 866374 | H92: =IF(E92=A92,1,"Check") -> 1 | I92: 1
A93: Flowserve Corp | B93: 34354P105 | C93: 46022 | D93: 004108 | E93: FLOWSERVE CORP | F93: FLS | G93: 30625 | H93: =IF(E93=A93,1,"Check") -> 1 | I93: 1
A94: Foot Locker Inc | B94: 344849104 | C94: 45688 | D94: 011584 | E94: FOOT LOCKER INC | F94: FL | G94: 850209 | H94: =IF(E94=A94,1,"Check") -> 1 | I94: 1
A95: General Mills Inc | B95: 370334104 | C95: 45808 | D95: 005071 | E95: GENERAL MILLS INC | F95: GIS | G95: 40704 | H95: =IF(E95=A95,1,"Check") -> 1 | I95: 1
A96: General Motors Co (GM) | B96: 37045V100 | C96: 46022 | D96: 005073 | E96: GENERAL MOTORS CO | F96: GM | G96: 1467858 | H96: =IF(E96=A96,1,"Check") -> Check | I96: 1
A97: Gentherm Inc | B97: 37253A103 | C97: 46022 | D97: 028408 | E97: GENTHERM INC | F97: THRM | G97: 903129 | H97: =IF(E97=A97,1,"Check") -> 1 | I97: 1
A98: Graphic Packaging Holding Co | B98: 388689101 | C98: 46022 | D98: 025389 | E98: GRAPHIC PACKAGING HOLDING CO | F98: GPK | G98: 1408075 | H98: =IF(E98=A98,1,"Check") -> 1 | I98: 1
A99: Greenbrier Cos Inc/The | B99: 393657101 | C99: 45900 | D99: 030463 | E99: GREENBRIER COS INC (THE) | F99: GBX | G99: 923120 | H99: =IF(E99=A99,1,"Check") -> Check | I99: 1
A100: Greif Inc. | B100: 397624107 | C100: 45930 | D100: 005338 | E100: GREIF INC -CL A | F100: GEF | G100: 43920 | H100: =IF(E100=A100,1,"Check") -> Check | I100: 1
...

Sheet Compustat Controls
A1: lineinmaster | B1: SASB Sample Name | C1: reporting year | D1: cusip | E1: latestannualdatadate | F1: gvkey | G1: conm | H1: tic | I1: cik | J1: datadate | K1: at | L1: ceq | M1: che | N1: lt | O1: gp | P1: ni | Q1: sale | R1: csho | S1: prcc_f | T1: lnat | U1: roa | V1: lev | W1: gpm | X1: cash | Y1: loss | Z1: btm | AA1: Note
A2: 10 | B2: AdvanSix Inc | C2: 2020 | D2: 00773T101 | E2: 46022 | F2: 28070 | G2: ADVANSIX INC | H2: ASIX | I2: 1673985 | J2: 2020-12-31 | K2: 1263.407 | L2: 444.12299 | M2: 10.606 | N2: 819.284 | O2: 190.98801 | P2: 46.077 | Q2: 1157.917 | R2: 28.033001 | S2: 19.99 | T2: 7.1415672 | U2: 0.036470432 | V2: 0.64847195 | W2: 0.16494101 | X2: 0.008394761 | Y2: 0 | Z2: 0.79253942
A3: 11 | B3: Aflac Inc | C3: 2018 | D3: 1055102 | E3: 46022 | F3: 1449 | G3: AFLAC INC | H3: AFL | I3: 4977 | J3: 2018-12-31 | K3: 140406 | L3: 23462 | M3: 5530 | N3: 116944 | O3: 4338 | P3: 2920 | Q3: 21768 | R3: 755.28601 | S3: 45.560001 | T3: 11.852294 | U3: 0.020796832 | V3: 0.83289886 | W3: 0.19928335 | X3: 0.039385781 | Y3: 0 | Z3: 0.68182021
A4: 12 | B4: Agilent Technologies Inc | C4: 2020 | D4: 00846U101 | E4: 45961 | F4: 126554 | G4: AGILENT TECHNOLOGIES INC | H4: A | I4: 1090872 | J4: 2020-10-31 | K4: 9627 | L4: 4873 | M4: 1441 | N4: 4754 | O4: 3068 | P4: 719 | Q4: 5339 | R4: 306.198 | S4: 102.09 | T4: 9.172327 | U4: 0.074685782 | V4: 0.49381948 | W4: 0.57463944 | X4: 0.14968318 | Y4: 0 | Z4: 0.15588735
A5: 14 | B5: AGNC Investment Corp | C5: 2020 | D5: 00123Q104 | E5: 46022 | F5: 179889 | G5: AGNC INVESTMENT CORP | H5: AGNC | I5: 1423689 | J5: 2020-12-31 | K5: 81817 | L5: 9590 | M5: 2324 | N5: 70738 | O5: 2871 | P5: -266 | Q5: 2964 | R5: 539.46899 | S5: 15.6 | T5: 11.312241 | U5: -0.0032511582 | V5: 0.86458802 | W5: 0.96862346 | X5: 0.028404854 | Y5: 1 | Z5: 1.1395346
A6: 15 | B6: AIG - American International Group Inc | C6: 2020 | D6: 26874784 | E6: 46022 | F6: 1487 | G6: AMERICAN INTERNATIONAL GROUP | H6: AIG | I6: 5272 | J6: 2020-12-31 | K6: 586481 | L6: 65877 | M6: 31987 | N6: 519282 | O6: 6985 | P6: -5944 | Q6: 43358 | R6: 861.55798 | S6: 37.860001 | T6: 13.281896 | U6: -0.010135026 | V6: 0.88541996 | W6: 0.16110061 | X6: 0.054540556 | Y6: 1 | Z6: 2.0196154
A7: 17 | B7: Akamai Technologies Inc | C7: 2020 | D7: 00971T101 | E7: 46022 | F7: 125595 | G7: AKAMAI TECHNOLOGIES INC | H7: AKAM | I7: 1086222 | J7: 2020-12-31 | K7: 7764.1299 | L7: 4251.2959 | M7: 1098.073 | N7: 3512.834 | O7: 2385.7749 | P7: 557.05402 | Q7: 3198.1489 | R7: 162.71001 | S7: 104.99 | T7: 8.9572697 | U7: 0.071747124 | V7: 0.45244399 | W7: 0.74598616 | X7: 0.14142898 | Y7: 0 | Z7: 0.24886233
A8: 21 | B8: Albemarle Corp | C8: 2019 | D8: 12653101 | E8: 46022 | F8: 29751 | G8: ALBEMARLE CORP | H8: ALB | I8: 915913 | J8: 2019-12-31 | K8: 9860.8633 | L8: 3932.25 | M8: 613.10999 | N8: 5767.2832 | O8: 1472.962 | P8: 533.22803 | Q8: 3589.427 | R8: 106.04 | S8: 73.040001 | T8: 9.1963291 | U8: 0.054075189 | V8: 0.58486593 | W8: 0.41036132 | X8: 0.062176097 | Y8: 0 | Z8: 0.50770408
A9: 27 | B9: Alliance Data Systems Corp | C9: 2020 | D9: 18581108 | E9: 46022 | F9: 143974 | G9: BREAD FINANCIAL HOLDINGS INC | H9: BFH | I9: 1101215 | J9: 2020-12-31 | K9: 22547.1 | L9: 1521.6 | M9: 4146.2002 | N9: 21025.5 | O9: 2491.6001 | P9: 213.7 | Q9: 4521.3999 | R9: 49.700001 | S9: 74.099998 | T9: 10.023362 | U9: 0.0094779376 | V9: 0.93251461 | W9: 0.55106831 | X9: 0.18389063 | Y9: 0 | Z9: 0.41316727
A10: 28 | B10: Alliance Data Systems Corp | C10: 2019 | D10: 18581108 | E10: 46022 | F10: 143974 | G10: BREAD FINANCIAL HOLDINGS INC | H10: BFH | I10: 1101215 | J10: 2019-12-31 | K10: 26494.801 | L10: 1588.3 | M10: 4550.8999 | N10: 24906.5 | O10: 2967.6001 | P10: 278 | Q10: 5581.2998 | R10: 47.599998 | S10: 112.2 | T10: 10.184704 | U10: 0.010492625 | V10: 0.94005233 | W10: 0.53170413 | X10: 0.17176577 | Y10: 0 | Z10: 0.29739439
A11: 29 | B11: Alliant Energy Corp | C11: 2020 | D11: 18802108 | E11: 46022 | F11: 11554 | G11: ALLIANT ENERGY CORP | H11: LNT | I11: 352541 | J11: 2020-12-31 | K11: 17710 | L11: 5688 | M11: 54 | N11: 11822 | O11: 1348 | P11: 624 | Q11: 3416 | R11: 249.868 | S11: 51.529999 | T11: 9.7818851 | U11: 0.035234332 | V11: 0.66753244 | W11: 0.39461359 | X11: 0.0030491247 | Y11: 0 | Z11: 0.44176248
A12: 30 | B12: Allison Transmission Holdings Inc | C12: 2020 | D12: 01973R101 | E12: 46022 | F12: 177966 | G12: ALLISON TRANSMISSION HLDGS | H12: ALSN | I12: 1411207 | J12: 2020-12-31 | K12: 4477 | L12: 756 | M12: 310 | N12: 3721 | O12: 1151 | P12: 299 | Q12: 2081 | R12: 112.033 | S12: 43.130001 | T12: 8.4067087 | U12: 0.066785797 | V12: 0.83113694 | W12: 0.55309945 | X12: 0.069242798 | Y12: 0 | Z12: 0.1564575
A13: 35 | B13: Ameren Corp | C13: 2020 | D13: 23608102 | E13: 46022 | F13: 10860 | G13: AMEREN CORP | H13: AEE | I13: 1002910 | J13: 2020-12-31 | K13: 32030 | L13: 8938 | M13: 156 | N13: 22950 | O13: 2375 | P13: 871 | Q13: 5794 | R13: 253.3 | S13: 78.059998 | T13: 10.374428 | U13: 0.027193256 | V13: 0.71651578 | W13: 0.4099068 | X13: 0.0048704338 | Y13: 0 | Z13: 0.45203975
... A26: 58 | B26: Apache Corp | C26: 2019 | D26: 03743Q108 | E26: 46022 | F26: 1678 | G26: APA CORP | H26: APA | I26: 1841666 | J26: 2019-12-31 | K26: 18107 | L26: 3255 | M26: 247 | N26: 13087 | O26: 1520 | P26: -3553 | Q26: 6280 | R26: 376.06299 | S26: 25.59 | T26: 9.8040543 | U26: -0.19622245 | V26: 0.72275913 | W26: 0.24203822 | X26: 0.013641133 | Y26: 1 | Z26: 0.33823621
A27: 69 | B27: Arconic Corp | C27: 2019 | D27: 03966V107 | E27: 44926 | F27: 35978 | G27: ARCONIC CORP | H27: ARNC | I27: 1790982 | J27: 2019-12-31 | K27: 4741 | L27: 2714 | M27: 72 | N27: 2013 | O27: 1007 | P27: 225 | Q27: 7277 | R27: 109.02 | S27: 6.9200001 | T27: 8.4640036 | U27: 0.047458343 | V27: 0.42459396 | W27: 0.1383812 | X27: 0.015186669 | Y27: 0 | Z27: 3.5974734 | AA27: The company starts to trade in 2020 April, the shares outstanding in March 2019 is replaced as 109,021,376 (disclosed in its 2020 10-K https://www.sec.gov/Archives/edgar/data/1790982/000179098220000022/arconic10k.htm). The stock price is replaced as 6.92, the closing price of the first day of trade (April 1, 2020)
A28: 70 | B28: Arcosa, Inc | C28: 2020 | D28: 39653100 | E28: 46022 | F28: 328795 | G28: ARCOSA INC | H28: ACA | I28: 1739445 | J28: 2020-12-31 | K28: 2646.7 | L28: 1892.2 | M28: 95.800003 | N28: 754.5 | O28: 506.79999 | P28: 106.6 | Q28: 1935.6 | R28: 48.200001 | S28: 54.93 | T28: 7.8810687 | U28: 0.040276572 | V28: 0.28507197 | W28: 0.26183096 | X28: 0.03619602 | Y28: 0 | Z28: 0.71467793
A29: 71 | B29: Arena Pharmaceuticals Inc | C29: 2020 | D29: 40047607 | E29: 44561 | F29: 138122 | G29: ARENA PHARMACEUTICALS INC | H29: ARNA | I29: 1080709 | J29: 2020-12-31 | K29: 1190.72 | L29: 1080.469 | M29: 1104.041 | N29: 110.251 | O29: -422.78101 | P29: -404.73401 | Q29: 0.31900001 | R29: 58.611 | S29: 76.830002 | T29: 7.0823135 | U29: -0.33990696 | V29: 0.092591882 | W29: -1325.3323 | X29: 0.92720461 | Y29: 1 | Z29: 0.23993982
A30: 75 | B30: Ashland LLC | C30: 2019 | D30: 44186104 | E30: 45930 | F30: 1794 | G30: ASHLAND INC | H30: ASH | I30: 1674862 | J30: 2019-09-30 | K30: 7251 | L30: 3571 | M30: 256 | N30: 3680 | O30: 980 | P30: 505 | Q30: 2493 | R30: 60 | S30: 77.050003 | T30: 8.888895 | U30: 0.069645569 | V30: 0.50751621 | W30: 0.39310068 | X30: 0.035305474 | Y30: 0 | Z30: 0.7724421
A31: 78 | B31: Atkore International | C31: 2020 | D31: 47649108 | E31: 45930 | F31: 27014 | G31: ATKORE INTERNATIONAL GROUP INC | H31: ATKR | I31: 1666138 | J31: 2020-09-30 | K31: 1558.525 | L31: 378.41 | M31: 284.47101 | N31: 1180.115 | O31: 533.52197 | P31: 152.302 | Q31: 1765.421 | R31: 47.407001 | S31: 22.73 | T31: 7.3514953 | U31: 0.097721882 | V31: 0.75719988 | W31: 0.30220664 | X31: 0.18252578 | Y31: 0 | Z31: 0.35117266
A32: 82 | B32: AvalonBay Communities Inc | C32: 2020 | D32: 53484101 | E32: 46022 | F32: 29875 | G32: AVALONBAY COMMUNITIES INC | H32: AVB | I32: 915912 | J32: 2020-12-31 | K32: 19199.145 | L32: 10751.583 | M32: 313.53201 | N32: 8444.293 | O32: 776.86499 | P32: 827.63 | Q32: 2307.2981 | R32: 139.52699 | S32: 160.42999 | T32: 9.8626213 | U32: 0.043107651 | V32: 0.43982652 | W32: 0.33669901 | X32: 0.01633052 | Y32: 0 | Z32: 0.48031771
A33: 89 | B33: Barnes Group Inc | C33: 2020 | D33: 67806109 | E33: 45291 | F33: 2049 | G33: BARNES GROUP INC | H33: B.2 | I33: 9984 | J33: 2020-12-31 | K33: 2676.2261 | L33: 1382.677 | M33: 84.088997 | N33: 1293.549 | O33: 490.80899 | P33: 63.375 | Q33: 1124.391 | R33: 50.640999 | S33: 50.689999 | T33: 7.8921628 | U33: 0.023680735 | V33: 0.48334816 | W33: 0.43651095 | X33: 0.031420738 | Y33: 0 | Z33: 0.53863704
A34: 90 | B34: Baxter International Inc | C34: 2019 | D34: 71813109 | E34: 46022 | F34: 2086 | G34: BAXTER INTERNATIONAL INC | H34: BAX | I34: 10456 | J34: 2019-12-31 | K34: 18193 | L34: 7882 | M34: 3335 | N34: 10281 | O34: 5705 | P34: 1001 | Q34: 11362 | R34: 506.155 | S34: 83.620003 | T34: 9.8087921 | U34: 0.055021163 | V34: 0.56510746 | W34: 0.50211233 | X34: 0.18331227 | Y34: 0 | Z34: 0.18622704
A35: 91 | B35: Becton Dickinson and Co | C35: 2020 | D35: 75887109 | E35: 45930 | F35: 2111 | G35: BECTON DICKINSON & CO | H35: BDX | I35: 10795 | J35: 2020-09-30 | K35: 54012 | L35: 23763 | M35: 2937 | N35: 30247 | O35: 9875 | P35: 874 | Q35: 17117 | R35: 290.017 | S35: 232.67999 | T35: 10.896961 | U35: 0.01618159 | V35: 0.56000519 | W35: 0.57691187 | X35: 0.054376803 | Y35: 0 | Z35: 0.35214278
A36: 94 | B36: Berry Plastics Group Inc | C36: 2020 | D36: 08579X101 | E36: 45657 | F36: 13431 | G36: BERRY CORP | H36: BRY | I36: 1705873 | J36: 2020-12-31 | K36: 1419.8101 | L36: 714.03601 | M36: 80.556999 | N36: 705.77399 | O36: -12.098 | P36: -262.89499 | Q36: 523.83301 | R36: 79.929001 | S36: 3.6800001 | T36: 7.2582784 | U36: -0.18516208 | V36: 0.49709043 | W36: -0.023095146 | X36: 0.05673787 | Y36: 1 | Z36: 2.4275484
A37: 98 | B37: Blackbaud, Inc. | C37: 2020 | D37: 09227Q100 | E37: 46022 | F37: 260893 | G37: BLACKBAUD INC | H37: BLKB | I37: 1280058 | J37: 2020-12-31 | K37: 2044.734 | L37: 426.14999 | M37: 644.96899 | N37: 1618.584 | O37: 579.27399 | P37: 7.717 | Q37: 913.21899 | R37: 48.849998 | S37: 57.560001 | T37: 7.623023 | U37: 0.0037740851 | V37: 0.79158658 | W37: 0.63432097 | X37: 0.3154293 | Y37: 0 | Z37: 0.1515574
A38: 102 | B38: Bloom Energy Corp | C38: 2020 | D38: 93712107 | E38: 46022 | F38: 33668 | G38: BLOOM ENERGY CORP | H38: BE | I38: 1664703 | J38: 2020-12-31 | K38: 1454.387 | L38: 78.823997 | M38: 299.41699 | N38: 1312.991 | O38: 218.07201 | P38: -157.55299 | Q38: 794.24701 | R38: 168.00301 | S38: 28.66 | T38: 7.2823396 | U38: -0.10832949 | V38: 0.90277964 | W38: 0.27456447 | X38: 0.20587161 | Y38: 1 | Z38: 0.016370624
A39: 119 | B39: Bunge Ltd | C39: 2020 | D39: H11356104 | E39: 46022 | F39: 144435 | G39: BUNGE GLOBAL SA | H39: BG | I39: 1996862 | J39: 2020-12-31 | K39: 23655 | L39: 5379 | M39: 1544 | N39: 17035 | O39: 3169 | P39: 1145 | Q39: 41355 | R39: 139.78999 | S39: 65.580002 | T39: 10.07133 | U39: 0.048404142 | V39: 0.72014374 | W39: 0.076629184 | X39: 0.065271616 | Y39: 0 | Z39: 0.58675128
... A47: 130 | B47: Cardinal Health Inc | C47: 2020 | D47: 14149Y108 | E47: 45838 | F47: 2751 | G47: CARDINAL HEALTH INC | H47: CAH | I47: 721371 | J47: 2020-06-30 | K47: 40766 | L47: 1789 | M47: 2771 | N47: 38974 | O47: 7268 | P47: -3696 | Q47: 152922 | R47: 293 | S47: 52.189999 | T47: 10.615603 | U47: -0.090663791 | V47: 0.95604181 | W47: 0.047527499 | X47: 0.067973308 | Y47: 1 | Z47: 0.1169918
A48: 131 | B48: Carrier Global Corp | C48: 2019 | D48: 14448C104 | E48: 46022 | F48: 36191 | G48: CARRIER GLOBAL CORP | H48: CARR | I48: 1783180 | J48: 2019-12-31 | K48: 22406 | L48: 14102 | M48: 957 | N48: 7971 | O48: 5790 | P48: 2116 | Q48: 18608 | R48: 866.15997 | S48: 16.92 | T48: 10.017084 | U48: 0.094438992 | V48: 0.35575292 | W48: 0.31115648 | X48: 0.042711772 | Y48: 0 | Z48: 0.96223742 | AA48: starts to trade on April 3 2020 -> The shares outstainding is replaced as 866,158,910 shares as if on the spin-off day (in 10-K https://www.sec.gov/ix?doc=/Archives/edgar/data/0001783180/000178318021000011/carr-20201231.htm), the stock price is replaced as 16.92, the closing price of the first date of trading (April 3, 2020)
A49: 132 | B49: Catalent Inc | C49: 2021 | D49: 148806102 | E49: 45473 | F49: 20228 | G49: CATALENT INC | H49: CTLT | I49: 1596783 | J49: 2021-06-30 | K49: 9112 | L49: 3915 | M49: 967 | N49: 4838 | O49: 1673 | P49: 585 | Q49: 3998 | R49: 170.549 | S49: 108.12 | T49: 9.1173477 | U49: 0.064201057 | V49: 0.53094822 | W49: 0.41845924 | X49: 0.10612379 | Y49: 0 | Z49: 0.21231298
A50: 133 | B50: Catalent Inc | C50: 2019 | D50: 148806102 | E50: 45473 | F50: 20228 | G50: CATALENT INC | H50: CTLT | I50: 1596783 | J50: 2019-06-30 | K50: 6184 | L50: 1681.6 | M50: 345.39999 | N50: 3895.8 | O50: 1033.7 | P50: 137.39999 | Q50: 2518 | R50: 145.73801 | S50: 54.209999 | T50: 8.7297201 | U50: 0.022218628 | V50: 0.62998062 | W50: 0.41052422 | X50: 0.055853814 | Y50: 0 | Z50: 0.21284844
A51: 134 | B51: Caterpillar Inc | C51: 2020 | D51: 149123101 | E51: 46022 | F51: 2817 | G51: CATERPILLAR INC | H51: CAT | I51: 18230 | J51: 2020-12-31 | K51: 78324 | L51: 15331 | M51: 9502 | N51: 62946 | O51: 14384 | P51: 2998 | Q51: 41748 | R51: 545.30402 | S51: 182.02 | T51: 11.268609 | U51: 0.0382769 | V51: 0.8036617 | W51: 0.34454346 | X51: 0.12131658 | Y51: 0 | Z51: 0.15445881
A52: 142 | B52: Century Communities Inc | C52: 2020 | D52: 156504300 | E52: 46022 | F52: 18004 | G52: CENTURY COMMUNITIES INC | H52: CCS | I52: 1576940 | J52: 2020-12-31 | K52: 2845.093 | L52: 1280.705 | M52: 421.23001 | N52: 1564.3879 | O52: 630.302 | P52: 206.157 | Q52: 3161.1919 | R52: 33.351002 | S52: 43.779999 | T52: 7.953351 | U52: 0.072460547 | V52: 0.54985476 | W52: 0.19938746 | X52: 0.14805491 | Y52: 0 | Z52: 0.87713099
A53: 146 | B53: CH Robinson Worldwide Inc | C53: 2020 | D53: 12541W209 | E53: 45657 | F53: 65609 | G53: C H ROBINSON WORLDWIDE INC | H53: CHRW | I53: 1043277 | J53: 2020-12-31 | K53: 5144.2578 | L53: 1879.933 | M53: 243.79601 | N53: 3264.325 | O53: 2513.9839 | P53: 506.42099 | Q53: 16207.106 | R53: 134.298 | S53: 93.870003 | T53: 8.5456362 | U53: 0.09844394 | V53: 0.63455701 | W53: 0.15511614 | X53: 0.047391873 | Y53: 0 | Z53: 0.14912346
A54: 147 | B54: Charah Solutions Inc | C54: 2020 | D54: 15957P303 | E54: 44926 | F54: 33596 | G54: CHARAH SOLUTIONS | H54: CHRA | I54: 1730346 | J54: 2020-12-31 | K54: 280.95999 | L54: 19.906 | M54: 29.211 | N54: 233.22099 | O54: 41.938 | P54: -55.862999 | Q54: 232.377 | R54: 30.077 | S54: 2.8699999 | T54: 5.6382122 | U54: -0.19882901 | V54: 0.83008611 | W54: 0.18047397 | X54: 0.10396854 | Y54: 1 | Z54: 0.23060441
A55: 149 | B55: Chart Industries Inc | C55: 2020 | D55: 16115Q308 | E55: 45657 | F55: 25964 | G55: CHART INDUSTRIES INC | H55: GTLS | I55: 892553 | J55: 2020-12-31 | K55: 2570.5 | L55: 1572.7 | M55: 126.1 | N55: 991.20001 | O55: 376.60001 | P55: 308.10001 | Q55: 1177.1 | R55: 35.424999 | S55: 117.79 | T55: 7.8518558 | U55: 0.11985995 | V55: 0.38560593 | W55: 0.31993884 | X55: 0.049056605 | Y55: 0 | Z55: 0.37690127
A56: 152 | B56: Chemours Co/The | C56: 2019 | D56: 163851108 | E56: 46022 | F56: 22741 | G56: CHEMOURS CO | H56: CC | I56: 1627223 | J56: 2019-12-31 | K56: 7258 | L56: 689 | M56: 943 | N56: 6563 | O56: 1524 | P56: -52 | Q56: 5526 | R56: 163.57401 | S56: 18.09 | T56: 8.8898592 | U56: -0.0071645081 | V56: 0.90424359 | W56: 0.27578717 | X56: 0.12992559 | Y56: 1 | Z56: 0.23284471
A57: 154 | B57: Cheniere Energy Partners LP | C57: 2020 | D57: 16411Q101 | E57: 43830 | F57: 176914 | G57: CHENIERE ENERGY PARTNERS LP | H57: CQP | I57: 1383650 | J57: 2020-12-31 | K57: 19145 | L57: 539 | M57: 1307 | N57: 18606 | O57: 2827 | P57: 1183 | Q57: 6167 | R57: 484 | S57: 35.25 | T57: 9.8597965 | U57: 0.061791591 | V57: 0.97184646 | W57: 0.45840764 | X57: 0.068268478 | Y57: 0 | Z57: 0.031592522
A58: 157 | B58: Chipotle Mexican Grill Inc | C58: 2020 | D58: 169656105 | E58: 46022 | F58: 165914 | G58: CHIPOTLE MEXICAN GRILL INC | H58: CMG | I58: 1058090 | J58: 2020-12-31 | K58: 5982.896 | L58: 2020.135 | M58: 951.60303 | N58: 3962.761 | O58: 1035.65 | P58: 355.76599 | Q58: 5984.6338 | R58: 28.000999 | S58: 1386.71 | T58: 8.69666 | U58: 0.059463844 | V58: 0.66234827 | W58: 0.17305152 | X58: 0.15905392 | Y58: 0 | Z58: 0.052026093
A59: 164 | B59: Citigroup Inc (Citi) | C59: 2020 | D59: 172967424 | E59: 46022 | F59: 3243 | G59: CITIGROUP INC | H59: C | I59: 831001 | J59: 2020-12-31 | K59: 2260090 | L59: 179962 | M59: 605047 | N59: 2059890 | O59: 25573 | P59: 11047 | Q59: 88839 | R59: 2082.0901 | S59: 61.66 | T59: 14.630916 | U59: 0.0048878584 | V59: 0.91141945 | W59: 0.2878578 | X59: 0.26770926 | Y59: 0 | Z59: 1.4017732
A60: 165 | B60: Citizens Financial Group Inc | C60: 2020 | D60: 174610105 | E60: 46022 | F60: 21825 | G60: CITIZENS FINANCIAL GROUP INC | H60: CFG | I60: 759944 | J60: 2020-12-31 | K60: 183349 | L60: 20708 | M60: 13039 | N60: 160676 | O60: 5289 | P60: 1057 | Q60: 7676 | R60: 427.20999 | S60: 35.759998 | T60: 12.119146 | U60: 0.0057649617 | V60: 0.87633967 | W60: 0.68903077 | X60: 0.07111574 | Y60: 0 | Z60: 1.3554991
... A212: 626 | B212: Pioneer Natural Resources Co | C212: 2019 | D212: 723787107 | E212: 45291 | F212: 14359 | G212: PIONEER NATURAL RESOURCES CO | H212: PXD | I212: 1038357 | J212: 2019-12-31 | K212: 19067 | L212: 12119 | M212: 705 | N212: 6948 | O212: 3889 | P212: 756 | Q212: 9671 | R212: 165.547 | S212: 151.37 | T212: 9.8557148 | U212: 0.039649658 | V212: 0.36439922 | W212: 0.40213007 | X212: 0.036974877 | Y212: 0 | Z212: 0.4836216
A213: 628 | B213: Plains GP Holdings LP | C213: 2020 | D213: 72651A207 | E213: 45657 | F213: 18468 | G213: PLAINS GP HOLDINGS LP | H213: PAGP | I213: 1581990 | J213: 2020-12-31 | K213: 25951 | L213: 1464 | M213: 63 | N213: 14761 | O213: 1783 | P213: -568 | Q213: 23290 | R213: 194.05099 | S213: 8.4499998 | T213: 10.163965 | U213: -0.021887403 | V213: 0.56880271 | W213: 0.076556459 | X213: 0.002427652 | Y213: 1 | Z213: 0.89282942 | AA213: No book value of equity -> book value of equity (CEQ) is replaced as SEQ (stockholders equity-parent)
A214: 633 | B214: Potlatch Corp | C214: 2020 | D214: 737630103 | E214: 45657 | F214: 8692 | G214: POTLATCHDELTIC CORP | H214: PCH | I214: 1338749 | J214: 2020-12-31 | K214: 2381.0649 | L214: 1304.953 | M214: 252.34 | N214: 1076.1121 | O214: 429.41 | P214: 166.83 | Q214: 1040.9301 | R214: 66.875999 | S214: 50.02 | T214: 7.7753029 | U214: 0.07006529 | V214: 0.45194569 | W214: 0.41252533 | X214: 0.10597779 | Y214: 0 | Z214: 0.39010444
A215: 634 | B215: Potlatch Corp | C215: 2019 | D215: 737630103 | E215: 45657 | F215: 8692 | G215: POTLATCHDELTIC CORP | H215: PCH | I215: 1338749 | J215: 2019-12-31 | K215: 2235.0591 | L215: 1226.8311 | M215: 83.309998 | N215: 1008.228 | O215: 215.44901 | P215: 55.660999 | Q215: 827.09802 | R215: 67.221001 | S215: 43.27 | T215: 7.7120228 | U215: 0.024903592 | V215: 0.4510968 | W215: 0.26048788 | X215: 0.037274182 | Y215: 0 | Z215: 0.4217867
A216: 635 | B216: PPG Industries Inc | C216: 2020 | D216: 693506107 | E216: 46022 | F216: 8247 | G216: PPG INDUSTRIES INC | H216: PPG | I216: 79879 | J216: 2020-12-31 | K216: 19556 | L216: 5689 | M216: 1928 | N216: 13741 | O216: 6064 | P216: 1059 | Q216: 13841 | R216: 236.686 | S216: 144.22 | T216: 9.8810377 | U216: 0.05415218 | V216: 0.70264882 | W216: 0.43811864 | X216: 0.098588668 | Y216: 0 | Z216: 0.16666248
A217: 636 | B217: PPG Industries Inc | C217: 2019 | D217: 693506107 | E217: 46022 | F217: 8247 | G217: PPG INDUSTRIES INC | H217: PPG | I217: 79879 | J217: 2019-12-31 | K217: 17708 | L217: 5284 | M217: 1278 | N217: 12305 | O217: 6501 | P217: 1243 | Q217: 15154 | R217: 235.67999 | S217: 133.49001 | T217: 9.7817717 | U217: 0.070194259 | V217: 0.69488364 | W217: 0.42899564 | X217: 0.072170772 | Y217: 0 | Z217: 0.16795439
A218: 637 | B218: PPL Corp | C218: 2019 | D218: 69351T106 | E218: 46022 | F218: 8455 | G218: PPL CORP | H218: PPL | I218: 922224 | J218: 2019-12-31 | K218: 45680 | L218: 12991 | M218: 818 | N218: 32689 | O218: 4044 | P218: 1746 | Q218: 7769 | R218: 767.23297 | S218: 35.880001 | T218: 10.729416 | U218: 0.038222417 | V218: 0.7156086 | W218: 0.52053028 | X218: 0.01790718 | Y218: 0 | Z218: 0.47191402
A219: 638 | B219: PPL Corp | C219: 2018 | D219: 69351T106 | E219: 46022 | F219: 8455 | G219: PPL CORP | H219: PPL | I219: 922224 | J219: 2018-12-31 | K219: 43396 | L219: 11657 | M219: 624 | N219: 31739 | O219: 3959 | P219: 1827 | Q219: 7785 | R219: 720.323 | S219: 28.33 | T219: 10.678123 | U219: 0.042100653 | V219: 0.73138076 | W219: 0.50854206 | X219: 0.014379205 | Y219: 0 | Z219: 0.57123256
A220: 641 | B220: Procter & Gamble Co/The | C220: 2020 | D220: 742718109 | E220: 45838 | F220: 8762 | G220: PROCTER & GAMBLE CO | H220: PG | I220: 80424 | J220: 2020-06-30 | K220: 120700 | L220: 46704 | M220: 16181 | N220: 73822 | O220: 39327 | P220: 13027 | Q220: 70950 | R220: 2479.7461 | S220: 119.57 | T220: 11.701063 | U220: 0.10792875 | V220: 0.6116156 | W220: 0.55429173 | X220: 0.13405965 | Y220: 0 | Z220: 0.15751599
A221: 643 | B221: Prudential Financial Inc | C221: 2020 | D221: 744320102 | E221: 46022 | F221: 143356 | G221: PRUDENTIAL FINANCIAL INC | H221: PRU | I221: 1137774 | J221: 2020-12-31 | K221: 940722 | L221: 67425 | M221: 61904 | N221: 872512 | O221: 13588 | P221: -374 | Q221: 57031 | R221: 396.43701 | S221: 78.07 | T221: 13.754403 | U221: -0.00039756697 | V221: 0.92749184 | W221: 0.23825638 | X221: 0.065804772 | Y221: 1 | Z221: 2.1785252
A222: 644 | B222: Prudential Financial Inc | C222: 2019 | D222: 744320102 | E222: 46022 | F222: 143356 | G222: PRUDENTIAL FINANCIAL INC | H222: PRU | I222: 1137774 | J222: 2019-12-31 | K222: 896552 | L222: 63115 | M222: 60267 | N222: 832833 | O222: 18539 | P222: 4186 | Q222: 64845 | R222: 398.832 | S222: 93.739998 | T222: 13.706311 | U222: 0.0046689985 | V222: 0.92892885 | W222: 0.28589714 | X222: 0.067220867 | Y222: 0 | Z222: 1.6881757
A223: 648 | B223: Public Storage | C223: 2020 | D223: 74460D109 | E223: 46022 | F223: 10096 | G223: PUBLIC STORAGE | H223: PSA | I223: 1393311 | J223: 2020-12-31 | K223: 11816.546 | L223: 4766.3672 | M223: 282.60001 | N223: 3239.647 | O223: 1597.1689 | P223: 1357.213 | Q223: 3017.8879 | R223: 174.582 | S223: 230.92999 | T223: 9.3772564 | U223: 0.114857 | V223: 0.27416193 | W223: 0.52923399 | X223: 0.023915619 | Y223: 0 | Z223: 0.11822455
A224: 649 | B224: Public Storage | C224: 2019 | D224: 74460D109 | E224: 46022 | F224: 10096 | G224: PUBLIC STORAGE | H224: PSA | I224: 1393311 | J224: 2019-12-31 | K224: 11365.444 | L224: 4997.9111 | M224: 433.55399 | N224: 2285.7771 | O224: 1635.105 | P224: 1520.5341 | Q224: 2944.8059 | R224: 174.41901 | S224: 212.96001 | T224: 9.3383331 | U224: 0.13378571 | V224: 0.20111638 | W224: 0.55525053 | X224: 0.038146682 | Y224: 0 | Z224: 0.13455401
A225: 652 | B225: PVH Corp | C225: 2020 | D225: 693656100 | E225: 45688 | F225: 8551 | G225: PVH CORP | H225: PVH | I225: 78239 | J225: 2020-01-31 | K225: 13631 | L225: 5811.5 | M225: 503.39999 | N225: 7821.5 | O225: 5417.7998 | P225: 417.29999 | Q225: 9909 | R225: 72.292999 | S225: 87.169998 | T225: 9.5201015 | U225: 0.030614041 | V225: 0.57380235 | W225: 0.54675543 | X225: 0.036930524 | Y225: 0 | Z225: 0.92219967
... A305: 866 | B305: Zoetis Inc | C305: 2019 | D305: 98978V103 | E305: 46022 | F305: 13721 | G305: ZOETIS INC | H305: ZTS | I305: 1555280 | J305: 2019-12-31 | K305: 11545 | L305: 2708 | M305: 1934 | N305: 8837 | O305: 4620 | P305: 1500 | Q305: 6276 | R305: 475.52802 | S305: 132.35001 | T305: 9.3540077 | U305: 0.12992637 | V305: 0.76543957 | W305: 0.73613769 | X305: 0.16751841 | Y305: 0 | Z305: 0.043027744

Sheet Metrics
A1: Industry | B1: Topics | C1: Code | D1: Quantitative | E1: Metrics | F1: MonetaryLoss
A2: ADVERTISING & MARKETING | B2: Data Privacy | C2: SV-AD-220a.1 | D2: 0 | E2: Discussion of policies and practices relating to behavioral advertising and consumer privacy
B3: Data Privacy | C3: SV-AD-220a.2 | D3: 1 | E3: Percentage of online advertising impressions that are targeted to custom audiences
B4: Data Privacy | C4: SV-AD-220a.3 | D4: 1 | E4: Total amount of monetary losses as a result of legal proceedings associated with consumer privacy | F4: 1
B5: Advertising Integrity | C5: SV-AD-270a.1 | D5: 1 | E5: Total amount of monetary losses as a result of legal proceedings associated with false, deceptive, or unfair advertising | F5: 1
B6: Advertising Integrity | C6: SV-AD-270a.2 | D6: 1 | E6: Percentage of campaigns reviewed for adherence with the Advertising Self- Regulatory Council (ASRC) procedures, percentage of those in compliance
B7: Advertising Integrity | C7: SV-AD-270a.3 | D7: 1 | E7: Percentage of campaigns that promote alcohol or tobacco products
B8: Workforce Diversity & Inclusion | C8: SV-AD-330a.1 | D8: 1 | E8: Percentage of gender and racial/ethnic group representation for (1) management, (2) professionals, and (3) all other employees
A9: AEROSPACE & DEFENSE | B9: Energy Management | C9: RT-AE-130a.1 | D9: 1 | E9: (1) Total energy consumed, (2) percentage grid electricity, (3) percentage renewable
B10: Hazardous Waste Management | C10: RT-AE-150a.1 | D10: 1 | E10: Amount of hazardous waste generated, percentage recycled
B11: Hazardous Waste Management | C11: RT-AE-150a.2 | D11: 1 | E11: Number and aggregate quantity of reportable spills, quantity recovered
B12: Data Security | C12: RT-AE-230a.1 | D12: 1 | E12: (1) Number of data breaches, (2) percentage involving confidential information
B13: Data Security | C13: RT-AE-230a.2 | D13: 0 | E13: Description of approach to identifying and addressing data security risks in (1) company operations and (2) products
B14: Product Safety | C14: RT-AE-250a.1 | D14: 1 | E14: Number of recalls issued, total units recalled
B15: Product Safety | C15: RT-AE-250a.2 | D15: 1 | E15: Number of counterfeit parts detected, percentage avoided
B16: Product Safety | C16: RT-AE-250a.3 | D16: 1 | E16: Number of Airworthiness Directives received, total units affected
B17: Product Safety | C17: RT-AE-250a.4 | D17: 1 | E17: Total amount of monetary losses as a result of legal proceedings associated with product safety | F17: 1
B18: Fuel Economy & Emissions in Use-phase | C18: RT-AE-410a.1 | D18: 1 | E18: Revenue from alternative energy-related products
B19: Fuel Economy & Emissions in Use-phase | C19: RT-AE-410a.2 | D19: 0 | E19: Description of approach and discussion of strategy to address fuel economy and greenhouse gas (GHG) emissions of products
B20: Materials Sourcing | C20: RT-AE-440a.1 | D20: 0 | E20: Description of the management of risks associated with the use of critical materials
B21: Business Ethics | C21: RT-AE-510a.1 | D21: 1 | E21: Total amount of monetary losses as a result of legal proceedings associated with incidents of corruption, bribery, and/or illicit international trade | F21: 1
B22: Business Ethics | C22: RT-AE-510a.2 | D22: 1 | E22: Revenue from countries ranked in the “E” or“F” Band of Transparency International’sGovernment Defence Anti-Corruption Index
B23: Business Ethics | C23: RT-AE-510a.3 | D23: 0 | E23: Discussion of processes to manage business ethics risks throughout the value chain
A24: AGRICULTURAL PRODUCTS | B24: Greenhouse Gas Emissions | C24: FB-AG-110a.1 | D24: 1 | E24: Gross global Scope 1 emissions
B25: Greenhouse Gas Emissions | C25: FB-AG-110a.2 | D25: 0 | E25: Discussion of long-term and short-term strategy or plan to manage Scope 1 emissions, emissions reduction targets, and an analysis of performance against those targets
B26: Greenhouse Gas Emissions | C26: FB-AG-110a.3 | D26: 1 | E26: Fleet fuel consumed, percentage renewable
B27: Energy Management | C27: FB-AG-130a.1 | D27: 1 | E27: (1) Operational energy consumed, (2) percentage grid electricity, (3) percentage renewable
B28: Water Management | C28: FB-AG-140a.1 | D28: 1 | E28: (1) Total water withdrawn, (2) total water consumed, percentage of each in regions with High or Extremely High Baseline Water Stress
B29: Water Management | C29: FB-AG-140a.2 | D29: 0 | E29: Description of water management risks and discussion of strategies and practices to mitigate those risks
B30: Water Management | C30: FB-AG-140a.3 | D30: 1 | E30: Number of incidents of non-compliance associated with water quantity and/or quality permits, standards, and regulations
B31: Food Safety | C31: FB-AG-250a.1 | D31: 1 | E31: Global Food Safety Initiative (GFSI) audit (1) non-conformance rate and (2) associated corrective action rate for (a) major and (b) minor non-conformances
B32: Food Safety | C32: FB-AG-250a.2 | D32: 1 | E32: Percentage of agricultural products sourced from suppliers certified to a Global Food Safety Initiative (GFSI) recognized food safety certification program
B33: Food Safety | C33: FB-AG-250a.3 | D33: 1 | E33: (1) Number of recalls issued and (2) total amount of food product recalled
B34: Workforce Health & Safety | C34: FB-AG-320a.1 | D34: 1 | E34: (1) Total recordable incident rate (TRIR), (2) fatality rate, and (3) near miss frequency rate (NMFR) for (a) direct employees and (b) seasonal and migrant employees
B35: Environmental & Social Impacts of Ingredient Supply Chain | C35: FB-AG-430a.1 | D35: 1 | E35: Percentage of agricultural products sourced that are certified to a third-party environmental and/or social standard, and percentages by standard
B36: Environmental & Social Impacts of Ingredient Supply Chain | C36: FB-AG-430a.2 | D36: 1 | E36: Suppliers’ social and environmental responsibility audit (1) non-conformance rate and (2) associated corrective action rate for (a) major and (b) minor non-conformances
... B40: Ingredient Sourcing | C40: FB-AG-440a.2 | D40: 1 | E40: Percentage of agricultural products sourced from regions with High or Extremely High Baseline Water Stress
A41: AIR FREIGHT & LOGISTICS | B41: Greenhouse Gas Emissions | C41: TR-AF-110a.1 | D41: 1 | E41: Gross global Scope 1 emissions
B42: Greenhouse Gas Emissions | C42: TR-AF-110a.2 | D42: 0 | E42: Discussion of long-term and short-term strategy or plan to manage Scope 1 emissions, emissions reduction targets, and an analysis of performance against those targets
B43: Greenhouse Gas Emissions | C43: TR-AF-110a.3 | D43: 1 | E43: Fuel consumed by (1) road transport, percentage (a) natural gas and (b) renewable, and (2) air transport, percentage (a) alternative and (b) sustainable
B44: Air Quality | C44: TR-AF-120a.1 | D44: 1 | E44: Air emissions of the following pollutants: (1) NOx (excluding N2O), (2) SOx, and (3) particulate matter (PM10)
B45: Labor Practices | C45: TR-AF-310a.1 | D45: 1 | E45: Percentage of drivers classified as independent contractors
B46: Labor Practices | C46: TR-AF-310a.2 | D46: 1 | E46: Total amount of monetary losses as a result of legal proceedings associated with labor law violations | F46: 1
B47: Employee Health & Safety | C47: TR-AF-320a.1 | D47: 1 | E47: (1) Total recordable incident rate (TRIR) and (2) fatality rate for (a) direct employees and (b) contract employees
B48: Supply Chain Management | C48: TR-AF-430a.1 | D48: 1 | E48: Percentage of carriers with BASIC percentiles above the FMCSA intervention threshold
B49: Supply Chain Management | C49: TR-AF-430a.2 | D49: 1 | E49: Total greenhouse gas (GHG) footprint across transport modes
B50: Accident & Safety Management | C50: TR-AF-540a.1 | D50: 0 | E50: Description of implementation and outcomes of a Safety Management System
B51: Accident & Safety Management | C51: TR-AF-540a.2 | D51: 1 | E51: Number of aviation accidents
B52: Accident & Safety Management | C52: TR-AF-540a.3 | D52: 1 | E52: Number of road accidents and incidents
B53: Accident & Safety Management | C53: TR-AF-540a.4 | D53: 1 | E53: Safety Measurement System BASIC percentiles for: (1) Unsafe Driving, (2) Hours-of-Service Compliance, (3) Driver Fitness, (4) Controlled Substances/Alcohol, (5) Vehicle Maintenance, and (6) Hazardous Materials Compliance
A54: AIRLINES | B54: Greenhouse Gas Emissions | C54: TR-AL-110a.1 | D54: 1 | E54: Gross global Scope 1 emissions
B55: Greenhouse Gas Emissions | C55: TR-AL-110a.2 | D55: 0 | E55: Discussion of long-term and short-term strategy or plan to manage Scope 1 emissions, emissions reduction targets, and an analysis of performance against those targets
B56: Greenhouse Gas Emissions | C56: TR-AL-110a.3 | D56: 1 | E56: (1) Total fuel consumed, (2) percentage alternative, (3) percentage sustainable
B57: Labor Practices | C57: TR-AL-310a.1 | D57: 1 | E57: Percentage of active workforce covered under collective bargaining agreements
B58: Labor Practices | C58: TR-AL-310a.2 | D58: 1 | E58: (1) Number of work stoppages and (2) total days idle
B59: Competitive Behavior | C59: TR-AL-520a.1 | D59: 1 | E59: Total amount of monetary losses as a result of legal proceedings associated with anti-competitive behavior regulations | F59: 1
B60: Accident & Safety Management | C60: TR-AL-540a.1 | D60: 0 | E60: Description of implementation and outcomes of a Safety Management System
B61: Accident & Safety Management | C61: TR-AL-540a.2 | D61: 1 | E61: Number of aviation accidents
B62: Accident & Safety Management | C62: TR-AL-540a.3 | D62: 1 | E62: Number of governmental enforcement actions of aviation safety regulations
A63: ALCOHOLIC BEVERAGES | B63: Energy Management | C63: FB-AB-130a.1 | D63: 1 | E63: (1) Total energy consumed, (2) percentage grid electricity, (3) percentage renewable
B64: Water Management | C64: FB-AB-140a.1 | D64: 1 | E64: (1) Total water withdrawn, (2) total water consumed, percentage of each in regions with High or Extremely High Baseline Water Stress
B65: Water Management | C65: FB-AB-140a.2 | D65: 0 | E65: Description of water management risks and discussion of strategies and practices to mitigate those risks
B66: Responsible Drinking & Marketing | C66: FB-AB-270a.1 | D66: 1 | E66: Percentage of total advertising impressions made on individuals at or above the legal drinking age
B67: Responsible Drinking & Marketing | C67: FB-AB-270a.2 | D67: 1 | E67: Number of incidents of non-compliance with industry or regulatory labeling and/or marketing codes
B68: Responsible Drinking & Marketing | C68: FB-AB-270a.3 | D68: 1 | E68: Total amount of monetary losses as a result of legal proceedings associated with marketing and/or labeling practices
B69: Responsible Drinking & Marketing | C69: FB-AB-270a.4 | D69: 0 | E69: Description of efforts to promote responsible consumption of alcohol
B70: Packaging Lifecycle Management | C70: FB-AB-410a.1 | D70: 1 | E70: (1) Total weight of packaging, (2) percentage made from recycled and/or renewable materials, and (3) percentage that is recyclable, reusable, and/or compostable
B71: Packaging Lifecycle Management | C71: FB-AB-410a.2 | D71: 0 | E71: Discussion of strategies to reduce the environmental impact of packaging throughout its lifecycle | F71: 1
B72: Environmental & Social Impacts of Ingredient Supply Chain | C72: FB-AB-430a.1 | D72: 1 | E72: Suppliers’ social and environmental responsibility audit (1) non-conformance rate and (2) associated corrective action rate for (a) major and (b) minor non-conformances
B73: Ingredient Sourcing | C73: FB-AB-440a.1 | D73: 1 | E73: Percentage of beverage ingredients sourced from regions with High or Extremely High Baseline Water Stress
B74: Ingredient Sourcing | C74: FB-AB-440a.2 | D74: 0 | E74: List of priority beverage ingredients and description of sourcing risks due to environmental and social considerations
A75: APPAREL, ACCESSORIES & FOOTWEAR | B75: Management of Chemicals in Products | C75: CG-AA-250a.1 | D75: 0 | E75: Discussion of processes to maintain compliance with restricted substances regulations | N75: Note: CG-AA-440a.1 is equivalent to CG-AA-440a.3; CG-AA-440a.2 is equivalent to CG-AA-440a.4 (Company might choose either one pair)
B76: Management of Chemicals in Products | C76: CG-AA-250a.2 | D76: 0 | E76: Discussion of processes to assess and manage risks and/or hazards associated with chemicals in products
B77: Environmental Impacts in the Supply Chain | C77: CG-AA-430a.1 | D77: 1 | E77: Percentage of (1) Tier 1 supplier facilities and (2) supplier facilities beyond Tier 1 in compliance with wastewater discharge permits and/or contractual agreements
B78: Environmental Impacts in the Supply Chain | C78: CG-AA-430a.2 | D78: 1 | E78: Percentage of (1) Tier 1 supplier facilities and (2) supplier facilities beyond Tier 1 that have completed the Sustainable Apparel Coalition’s Higg Facility Environmental Module (Higg FEM) assessment or an equivalent environmental data assessment
B79: Labor Conditions in the Supply Chain | C79: CG-AA-430b.1 | D79: 1 | E79: Percentage of (1) Tier 1 supplier facilities and (2) supplier facilities beyond Tier 1 that have been audited to a labor code of conduct, (3) percentage of total audits conducted by a third-party auditor
B80: Labor Conditions in the Supply Chain | C80: CG-AA-430b.2 | D80: 1 | E80: Priority non-conformance rate and associated corrective action rate for suppliers’ labor code of conduct audits
B81: Labor Conditions in the Supply Chain | C81: CG-AA-430b.3 | D81: 0 | E81: Description of the greatest (1) labor and (2) environmental, health, and safety risks in the supply chain
B82: Raw Materials Sourcing | C82: CG-AA-440a.1 | D82: 0 | E82: Description of environmental and social risks associated with sourcing priority raw materials
B83: Raw Materials Sourcing | C83: CG-AA-440a.2 | D83: 1 | E83: Percentage of raw materials third-party certified to an environmental and/or social sustainability standard, by standard
B84: Raw Materials Sourcing | C84: CG-AA-440a.3 | D84: 0 | E84: (1) List of priority raw materials; for each priority raw material: (2) environmental and/or social factor (s) most likely to threaten sourcing, (3) discussion on business risks and/or opportunities associated with environmental and/or social factors, and (4) management strategy for addressing business risks and opportunities
B85: Raw Materials Sourcing | C85: CG-AA-440a.4 | D85: 1 | E85: (1) Amount of priority raw materials purchased, by material, and (2) amount of each priority raw material that is certified to a third-party environmental and/or social standard, by standard
A86: APPLIANCE MANUFACTURING | B86: Product Safety | C86: CG-AM-250a.1 | D86: 1 | E86: Number of (1) recalls issued and (2) total units recalled
B87: Product Safety | C87: CG-AM-250a.2 | D87: 0 | E87: Discussion of process to identify and manage safety risks associated with the use of its products
B88: Product Safety | C88: CG-AM-250a.3 | D88: 1 | E88: Total amount of monetary losses as a result of legal proceedings associated with product safety | F88: 1
B89: Product Lifecycle Environmental Impacts | C89: CG-AM-410a.1 | D89: 1 | E89: Percentage of eligible products by revenue certified to the ENERGY STAR® program
B90: Product Lifecycle Environmental Impacts | C90: CG-AM-410a.2 | D90: 1 | E90: Percentage of eligible products certified to an Association of Home Appliance Manufacturers (AHAM) sustainability standard
B91: Product Lifecycle Environmental Impacts | C91: CG-AM-410a.3 | D91: 0 | E91: Description of efforts to manage products’ end-of-life impacts
A92: ASSET MANAGEMENT & CUSTODY | B92: Transparent Information & Fair Advice for Customers | C92: FN-AC-270a.1 | D92: 1 | E92: (1) Number and (2) percentage of covered employees with a record of investment-related investigations, consumer-initiated complaints, private civil litigations, or other regulatory proceedings
B93: Transparent Information & Fair Advice for Customers | C93: FN-AC-270a.2 | D93: 1 | E93: Total amount of monetary losses as a result of legal proceedings associated with marketing and communication of financial product-related information to new and returning customers | F93: 1
B94: Transparent Information & Fair Advice for Customers | C94: FN-AC-270a.3 | D94: 0 | E94: Description of approach to informing customers about products and services
B95: Employee Diversity & Inclusion | C95: FN-AC-330a.1 | D95: 1 | E95: Percentage of gender and racial/ethnic group representation for (1) executive management, (2) non-executive management, (3) professionals, and (4) all other employees
B96: Incorporation of Environmental, Social, and Governance Factors in Investment Management & Advisory | C96: FN-AC-410a.1 | D96: 1 | E96: Amount of assets under management, by asset class, that employ (1) integration of environmental, social, and governance (ESG) issues, (2) sustainability themed investing, and (3) screening
B97: Incorporation of Environmental, Social, and Governance Factors in Investment Management & Advisory | C97: FN-AC-410a.2 | D97: 0 | E97: Description of approach to incorporation of environmental, social, and governance (ESG) factors in investment and/or wealth management processes and strategies
B98: Incorporation of Environmental, Social, and Governance Factors in Investment Management & Advisory | C98: FN-AC-410a.3 | D98: 0 | E98: Description of proxy voting and investee engagement policies and procedures
B99: Business Ethics | C99: FN-AC-510a.1 | D99: 1 | E99: Total amount of monetary losses as a result of legal proceedings associated with fraud, insider trading, anti-trust, anti-competitive behavior, market manipulation, malpractice, or other related financial industry laws or regulations | F99: 1
B100: Business Ethics | C100: FN-AC-510a.2 | D100: 0 | E100: Description of whistleblower policies and procedures
B101: Systemic Risk Management | C101: FN-AC-550a.1 | D101: 1 | E101: Percentage of open-end fund assets under management by category of liquidity classification | I101: Updated in 2021
B102: Systemic Risk Management | C102: FN-AC-550a.2 | D102: 0 | E102: Description of approach to incorporation of liquidity risk management programs into portfolio strategy and redemption risk management | I102: Updated in 2021
B103: Systemic Risk Management | C103: FN-AC-550a.3 | D103: 1 | E103: Total exposure to securities financing transactions | I103: Updated in 2021
...

Sheet List of Sample Metrics
A1: Line in Master | B1: Company | C1: Industry | D1: Code | E1: Metrics | F1: Reported
A2: =Sample!A2 -> 10 | B2: =Sample!B2 -> AdvanSix Inc | C2: CHEMICALS | D2: RT-CH-110a.1 | E2: Gross global Scope 1 emissions, percentage covered under emissions-limiting regulations | F2: 1
D3: RT-CH-110a.2 | E3: Discussion of long-term and short-term strategy or plan to manage Scope 1 emissions, emissions reduction targets, and an analysis of performance against those targets | F3: 1
D4: RT-CH-120a.1 | E4: Air emissions of the following pollutants: (1) NOX (excluding N2O), (2) SOX, (3) volatile organic compounds (VOCs), and (4) hazardous air pollutants (HAPs) | F4: 1
D5: RT-CH-130a.1 | E5: (1) Total energy consumed, (2) percentage grid electricity, (3) percentage renewable, (4) total self-generated energy | F5: 1
D6: RT-CH-140a.1 | E6: (1) Total water withdrawn, (2) total water consumed, percentage of each in regions with High or Extremely High Baseline Water Stress | F6: 1
D7: RT-CH-140a.2 | E7: Number of incidents of non-compliance associated with water quality permits, standards, and regulations | F7: 0
D8: RT-CH-140a.3 | E8: Description of water management risks and discussion of strategies and practices to mitigate those risks | F8: 0
D9: RT-CH-150a.1 | E9: Amount of hazardous waste generated, percentage recycled | F9: 1
D10: RT-CH-210a.1 | E10: Discussion of engagement processes to manage risks and opportunities associated with community interests | F10: 1
D11: RT-CH-320a.1 | E11: (1) Total recordable incident rate (TRIR) and (2) fatality rate for (a) direct employees and (b) contract employees | F11: 1
D12: RT-CH-320a.2 | E12: Description of efforts to assess, monitor, and reduce exposure of employees and contract workers to long-term (chronic) health risks | F12: 1
D13: RT-CH-410a.1 | E13: Revenue from products designed for use-phase resource efficiency | F13: 0
D14: RT-CH-410b.1 | E14: (1) Percentage of products that contain Globally Harmonized System of Classification and Labeling of Chemicals (GHS) Category 1 and 2 Health and Environmental Hazardous Substances, (2) percentage of such products that have undergone a hazard assessment | F14: 0
... D19: RT-CH-540a.2 | E19: Number of transport incidents | F19: 0
A20: =Sample!A3 -> 11 | B20: =Sample!B3 -> Aflac Inc | C20: INSURANCE | D20: FN-IN-270a.1 | E20: Total amount of monetary losses as a result of legal proceedings associated with marketing and communication of insurance product-related information to new and returning customers | F20: 1
D21: FN-IN-270a.2 | E21: Complaints-to-claims ratio | F21: 0
D22: FN-IN-270a.3 | E22: Customer retention rate | F22: 0
D23: FN-IN-270a.4 | E23: Description of approach to informing customers about products | F23: 1
D24: FN-IN-410a.1 | E24: Total invested assets, by industry and asset class | F24: 1
D25: FN-IN-410a.2 | E25: Description of approach to incorporation of environmental, social, and governance (ESG) factors in investment management processes and strategies | F25: 1
D26: FN-IN-410b.1 | E26: Net premiums written related to energy efficiency and low carbon technology | F26: 0
D27: FN-IN-410b.2 | E27: Discussion of products and/or product features that incentivize health, safety, and/or environmentally responsible actions and/or behaviors | F27: 0
D28: FN-IN-450a.1 | E28: Probable Maximum Loss (PML) of insured products from weather-related natural catastrophes | F28: 0
D29: FN-IN-450a.2 | E29: Total amount of monetary losses attributable to insurance payouts from (1) modeled natural catastrophes and (2) non-modeled natural catastrophes, by type of event and geographic segment (net and gross of reinsurance) | F29: 0
D30: FN-IN-450a.3 | E30: Description of approach to incorporation of environmental risks into (1) the underwriting process for individual contracts and (2) the management of firm-level risks and capital adequacy | F30: 0
D31: FN-IN-550a.1 | E31: Exposure to derivative instruments by category: (1) total potential exposure to non-centrally cleared derivatives, (2) total fair value of acceptable collateral posted with the Central Clearinghouse, and (3) total potential exposure to centrally cleared derivatives | F31: 0
D32: FN-IN-550a.2 | E32: Total fair value of securities lending collateral assets | F32: 0
D33: FN-IN-550a.3 | E33: Description of approach to managing capital- and liquidity-related risks associated with systemic non-insurance activities | F33: 0
A34: =Sample!A4 -> 12 | B34: =Sample!B4 -> Agilent Technologies Inc | C34: MEDICAL EQUIPMENT & SUPPLIES | D34: HC-MS-240a.1 | E34: Ratio of weighted average rate of net price increases (for all products) to the annual increase in the U.S. Consumer Price Index | F34: 1
D35: HC-MS-240a.2 | E35: Description of how price information for each product is disclosed to customers or to their agents | F35: 1
D36: HC-MS-250a.1 | E36: Number of recalls issued, total units recalled | F36: 1
D37: HC-MS-250a.2 | E37: List of products listed in the FDA’s MedWatch Safety Alerts for Human Medical Products database | F37: 1
D38: HC-MS-250a.3 | E38: Number of fatalities related to products as reported in the FDA Manufacturer and User Facility Device Experiencedatabase | F38: 1
D39: HC-MS-250a.4 | E39: Number of FDA enforcement actions taken in response to violations of current Good Manufacturing Practices (cGMP), by type | F39: 1
D40: HC-MS-270a.1 | E40: Total amount of monetary losses as a result of legal proceedings associated with bribery or corruption | F40: 1
D41: HC-MS-270a.2 | E41: Description of code of ethics governing promotion of off-label use of products | F41: 1
D42: HC-MS-410a.1 | E42: Discussion of process to assess and manage environmental and human health considerations associated with chemicals in products, and meet demand for sustainable products | F42: 1
D43: HC-MS-410a.2 | E43: Total amount of products accepted for take-back and reused, recycled, or donated, broken down by: (1) devices and equipment and (2) supplies | F43: 1
D44: HC-MS-430a.1 | E44: Percentage of (1) entity's facilities and (2) Tier I suppliers' facilities participating in third-party audit programs for manufacturing and product quality | F44: 1
D45: HC-MS-430a.2 | E45: Description of efforts to maintain traceability within the distribution chain | F45: 1
D46: HC-MS-430a.3 | E46: Description of the management of risks associated with the use of critical materials | F46: 1
... D48: HC-MS-510a.2 | E48: Description of code of ethics governing interactions with health care professionals | F48: 1
A49: =Sample!A5 -> 14 | B49: =Sample!B5 -> AGNC Investment Corp | C49: ASSET MANAGEMENT & CUSTODY | D49: FN-AC-510a.1 | E49: Total amount of monetary losses as a result of legal proceedings associated with fraud, insider trading, anti-trust, anti-competitive behavior, market manipulation, malpractice, or other related financial industry laws or regulations | F49: 1
D50: FN-AC-510a.2 | E50: Description of whistleblower policies and procedures | F50: 1
D51: FN-AC-330a.1 | E51: Percentage of gender and racial/ethnic group representation for (1) executive management, (2) non-executive management, (3) professionals, and (4) all other employees | F51: 1
D52: FN-AC-410a.1 | E52: Amount of assets under management, by asset class, that employ (1) integration of environmental, social, and governance (ESG) issues, (2) sustainability themed investing, and (3) screening | F52: 1
D53: FN-AC-410a.2 | E53: Description of approach to incorporation of environmental, social, and governance (ESG) factors in investment and/or wealth management processes and strategies | F53: 1
D54: FN-AC-410a.3 | E54: Description of proxy voting and investee engagement policies and procedures | F54: 1
D55: FN-AC-270a.1 | E55: (1) Number and (2) percentage of covered employees with a record of investment-related investigations, consumer-initiated complaints, private civil litigations, or other regulatory proceedings | F55: 1
D56: FN-AC-270a.2 | E56: Total amount of monetary losses as a result of legal proceedings associated with marketing and communication of financial product-related information to new and returning customers | F56: 1
D57: FN-AC-270a.3 | E57: Description of approach to informing customers about products and services | F57: 1
D58: FN-AC-550a.2 | E58: Description of approach to incorporation of liquidity risk management programs into portfolio strategy and redemption risk management | F58: 2
D59: FN-AC-550a.3 | E59: Total exposure to securities financing transactions | F59: 1
D60: FN-AC-550a.4 | E60: Net exposure to written credit derivatives | F60: 2
A61: =Sample!A6 -> 15 | B61: =Sample!B6 -> AIG - American International Group Inc | C61: INSURANCE | D61: FN-IN-450a.1 | E61: Probable Maximum Loss (PML) of insured products from weather-related natural catastrophes | F61: 1
D62: FN-IN-450a.2 | E62: Total amount of monetary losses attributable to insurance payouts from (1) modeled natural catastrophes and (2) non-modeled natural catastrophes, by type of event and geographic segment (net and gross of reinsurance) | F62: 1
D63: FN-IN-450a.3 | E63: Description of approach to incorporation of environmental risks into (1) the underwriting process for individual contracts and (2) the management of firm-level risks and capital adequacy | F63: 1
D64: FN-IN-410a.1 | E64: Total invested assets, by industry and asset class | F64: 1
D65: FN-IN-410a.2 | E65: Description of approach to incorporation of environmental, social, and governance (ESG) factors in investment management processes and strategies | F65: 1
D66: FN-IN-410b.1 | E66: Net premiums written related to energy efficiency and low carbon technology | F66: 1
D67: FN-IN-410b.2 | E67: Discussion of products and/or product features that incentivize health, safety, and/or environmentally responsible actions and/or behaviors | F67: 1
D68: FN-IN-550a.1 | E68: Exposure to derivative instruments by category: (1) total potential exposure to non-centrally cleared derivatives, (2) total fair value of acceptable collateral posted with the Central Clearinghouse, and (3) total potential exposure to centrally cleared derivatives | F68: 1
D69: FN-IN-550a.2 | E69: Total fair value of securities lending collateral assets | F69: 1
D70: FN-IN-550a.3 | E70: Description of approach to managing capital- and liquidity-related risks associated with systemic non-insurance activities | F70: 1
D71: FN-IN-270a.1 | E71: Total amount of monetary losses as a result of legal proceedings associated with marketing and communication of insurance product-related information to new and returning customers | F71: 0
D72: FN-IN-270a.2 | E72: Complaints-to-claims ratio | F72: 0
D73: FN-IN-270a.3 | E73: Customer retention rate | F73: 0
D74: FN-IN-270a.4 | E74: Description of approach to informing customers about products | F74: 1
C75: ASSET MANAGEMENT & CUSTODY | D75: FN-AC-510a.1 | E75: Total amount of monetary losses as a result of legal proceedings associated with fraud, insider trading, anti-trust, anti-competitive behavior, market manipulation, malpractice, or other related financial industry laws or regulations | F75: 0
D76: FN-AC-510a.2 | E76: Description of whistleblower policies and procedures | F76: 1
D77: FN-AC-330a.1 | E77: Percentage of gender and racial/ethnic group representation for (1) executive management, (2) non-executive management, (3) professionals, and (4) all other employees | F77: 1
D78: FN-AC-410a.1 | E78: Amount of assets under management, by asset class, that employ (1) integration of environmental, social, and governance (ESG) issues, (2) sustainability themed investing, and (3) screening | F78: 1
D79: FN-AC-410a.2 | E79: Description of approach to incorporation of environmental, social, and governance (ESG) factors in investment and/or wealth management processes and strategies | F79: 1
D80: FN-AC-410a.3 | E80: Description of proxy voting and investee engagement policies and procedures | F80: 0
D81: FN-AC-270a.1 | E81: (1) Number and (2) percentage of covered employees with a record of investment-related investigations, consumer-initiated complaints, private civil litigations, or other regulatory proceedings | F81: 0
D82: FN-AC-270a.2 | E82: Total amount of monetary losses as a result of legal proceedings associated with marketing and communication of financial product-related information to new and returning customers | F82: 0
D83: FN-AC-270a.3 | E83: Description of approach to informing customers about products and services | F83: 0
A84: =Sample!A7 -> 17 | B84: =Sample!B7 -> Akamai Technologies Inc | C84: SOFTWARE & IT SERVICES | D84: TC-SI-220a.1 | E84: Description of policies and practices relating to behavioral advertising and user privacy | F84: 0
D85: TC-SI-220a.2 | E85: Number of users whose information is used for secondary purposes | F85: 0
D86: TC-SI-220a.3 | E86: Total amount of monetary losses as a result of legal proceedings associated with user privacy | F86: 0
D87: TC-SI-220a.4 | E87: (1) Number of law enforcement requests for user information, (2) number of users whose information was requested, (3) percentage resulting in disclosure | F87: 0
D88: TC-SI-220a.5 | E88: List of countries where core products or services are subject to government-required monitoring, blocking, content filtering, or censoring | F88: 0
D89: TC-SI-230a.1 | E89: (1) Number of data breaches, (2) percentage involving personally identifiable information (PII), (3) number of users affected | F89: 0
D90: TC-SI-230a.2 | E90: Description of approach to identifying and addressing data security risks, including use of third-party cybersecurity standards | F90: 0
D91: TC-SI-130a.1 | E91: (1) Total energy consumed, (2) percentage grid electricity, (3) percentage renewable | F91: 1
D92: TC-SI-130a.2 | E92: (1) Total water withdrawn, (2) total water consumed, percentage of each in regions with High or Extremely High Baseline Water Stress | F92: 1
D93: TC-SI-130a.3 | E93: Discussion of the integration of environmental considerations into strategic planning for data center needs | F93: 0
D94: TC-SI-520a.1 | E94: Total amount of monetary losses as a result of legal proceedings associated with anti-competitive behavior regulations | F94: 0
D95: TC-SI-550a.1 | E95: Number of (1) performance issues and (2) service disruptions; (3) total customer downtime | F95: 0
D96: TC-SI-550a.2 | E96: Description of business continuity risks related to disruptions of operations | F96: 0
... D99: TC-SI-330a.3 | E99: Percentage of gender and racial/ethnic group representation for (1) management, (2) technical staff, and (3) all other employees | F99: 0
A100: =Sample!A8 -> 21 | B100: =Sample!B8 -> Albemarle Corp | C100: CHEMICALS | D100: RT-CH-120a.1 | E100: Air emissions of the following pollutants: (1) NOX (excluding N2O), (2) SOX, (3) volatile organic compounds (VOCs), and (4) hazardous air pollutants (HAPs) | F100: 1
D101: RT-CH-210a.1 | E101: Discussion of engagement processes to manage risks and opportunities associated with community interests | F101: 0
D102: RT-CH-130a.1 | E102: (1) Total energy consumed, (2) percentage grid electricity, (3) percentage renewable, (4) total self-generated energy | F102: 1
D103: RT-CH-410c.1 | E103: Percentage of products by revenue that contain genetically modified organisms (GMOs) | F103: 0
D104: RT-CH-110a.1 | E104: Gross global Scope 1 emissions, percentage covered under emissions-limiting regulations | F104: 1
D105: RT-CH-110a.2 | E105: Discussion of long-term and short-term strategy or plan to manage Scope 1 emissions, emissions reduction targets, and an analysis of performance against those targets | F105: 1
D106: RT-CH-150a.1 | E106: Amount of hazardous waste generated, percentage recycled | F106: 1
D107: RT-CH-530a.1 | E107: Discussion of corporate positions related to government regulations and/or policy proposals that address environmental and social factors affecting the industry | F107: 0
...

Sheet List of Sample Metrics (fill)
A1: Line in Master | B1: Company | C1: Industry | D1: Code | E1: Metrics | F1: Reported | G1: Disclosed Information | H1: Reason Summary
A2: 10 | B2: AdvanSix Inc | C2: CHEMICALS | D2: RT-CH-110a.1 | E2: Gross global Scope 1 emissions, percentage covered under emissions-limiting regulations | F2: 1
A3: 10 | B3: AdvanSix Inc | C3: CHEMICALS | D3: RT-CH-110a.2 | E3: Discussion of long-term and short-term strategy or plan to manage Scope 1 emissions, emissions reduction targets, and an analysis of performance against those targets | F3: 1
A4: 10 | B4: AdvanSix Inc | C4: CHEMICALS | D4: RT-CH-120a.1 | E4: Air emissions of the following pollutants: (1) NOX (excluding N2O), (2) SOX, (3) volatile organic compounds (VOCs), and (4) hazardous air pollutants (HAPs) | F4: 1
A5: 10 | B5: AdvanSix Inc | C5: CHEMICALS | D5: RT-CH-130a.1 | E5: (1) Total energy consumed, (2) percentage grid electricity, (3) percentage renewable, (4) total self-generated energy | F5: 1
A6: 10 | B6: AdvanSix Inc | C6: CHEMICALS | D6: RT-CH-140a.1 | E6: (1) Total water withdrawn, (2) total water consumed, percentage of each in regions with High or Extremely High Baseline Water Stress | F6: 1
A7: 10 | B7: AdvanSix Inc | C7: CHEMICALS | D7: RT-CH-140a.2 | E7: Number of incidents of non-compliance associated with water quality permits, standards, and regulations | F7: 0 | G7: N/A
A8: 10 | B8: AdvanSix Inc | C8: CHEMICALS | D8: RT-CH-140a.3 | E8: Description of water management risks and discussion of strategies and practices to mitigate those risks | F8: 0 | G8: N/A
A9: 10 | B9: AdvanSix Inc | C9: CHEMICALS | D9: RT-CH-150a.1 | E9: Amount of hazardous waste generated, percentage recycled | F9: 1
A10: 10 | B10: AdvanSix Inc | C10: CHEMICALS | D10: RT-CH-210a.1 | E10: Discussion of engagement processes to manage risks and opportunities associated with community interests | F10: 1
A11: 10 | B11: AdvanSix Inc | C11: CHEMICALS | D11: RT-CH-320a.1 | E11: (1) Total recordable incident rate (TRIR) and (2) fatality rate for (a) direct employees and (b) contract employees | F11: 1
A12: 10 | B12: AdvanSix Inc | C12: CHEMICALS | D12: RT-CH-320a.2 | E12: Description of efforts to assess, monitor, and reduce exposure of employees and contract workers to long-term (chronic) health risks | F12: 1
A13: 10 | B13: AdvanSix Inc | C13: CHEMICALS | D13: RT-CH-410a.1 | E13: Revenue from products designed for use-phase resource efficiency | F13: 0 | G13: N/A
A14: 10 | B14: AdvanSix Inc | C14: CHEMICALS | D14: RT-CH-410b.1 | E14: (1) Percentage of products that contain Globally Harmonized System of Classification and Labeling of Chemicals (GHS) Category 1 and 2 Health and Environmental Hazardous Substances, (2) percentage of such products that have undergone a hazard assessment | F14: 0 | G14: N/A
A15: 10 | B15: AdvanSix Inc | C15: CHEMICALS | D15: RT-CH-410b.2 | E15: Discussion of strategy to (1) manage chemicals of concern and (2) develop alternatives with reduced human and/or environmental impact | F15: 1
A16: 10 | B16: AdvanSix Inc | C16: CHEMICALS | D16: RT-CH-410c.1 | E16: Percentage of products by revenue that contain genetically modified organisms (GMOs) | F16: 0 | G16: N/A
A17: 10 | B17: AdvanSix Inc | C17: CHEMICALS | D17: RT-CH-530a.1 | E17: Discussion of corporate positions related to government regulations and/or policy proposals that address environmental and social factors affecting the industry | F17: 1
A18: 10 | B18: AdvanSix Inc | C18: CHEMICALS | D18: RT-CH-540a.1 | E18: Process Safety Incidents Count (PSIC), Process Safety Total Incident Rate (PSTIR), and Process Safety Incident Severity Rate (PSISR) | F18: 1
A19: 10 | B19: AdvanSix Inc | C19: CHEMICALS | D19: RT-CH-540a.2 | E19: Number of transport incidents | F19: 0 | G19: N/A
A20: 11 | B20: Aflac Inc | C20: INSURANCE | D20: FN-IN-270a.1 | E20: Total amount of monetary losses as a result of legal proceedings associated with marketing and communication of insurance product-related information to new and returning customers | F20: 1
A21: 11 | B21: Aflac Inc | C21: INSURANCE | D21: FN-IN-270a.2 | E21: Complaints-to-claims ratio | F21: 0 | G21: N/A
A22: 11 | B22: Aflac Inc | C22: INSURANCE | D22: FN-IN-270a.3 | E22: Customer retention rate | F22: 0 | G22: N/A
A23: 11 | B23: Aflac Inc | C23: INSURANCE | D23: FN-IN-270a.4 | E23: Description of approach to informing customers about products | F23: 1
A24: 11 | B24: Aflac Inc | C24: INSURANCE | D24: FN-IN-410a.1 | E24: Total invested assets, by industry and asset class | F24: 1
A25: 11 | B25: Aflac Inc | C25: INSURANCE | D25: FN-IN-410a.2 | E25: Description of approach to incorporation of environmental, social, and governance (ESG) factors in investment management processes and strategies | F25: 1
A26: 11 | B26: Aflac Inc | C26: INSURANCE | D26: FN-IN-410b.1 | E26: Net premiums written related to energy efficiency and low carbon technology | F26: 0 | G26: N/A
A27: 11 | B27: Aflac Inc | C27: INSURANCE | D27: FN-IN-410b.2 | E27: Discussion of products and/or product features that incentivize health, safety, and/or environmentally responsible actions and/or behaviors | F27: 0 | G27: N/A
A28: 11 | B28: Aflac Inc | C28: INSURANCE | D28: FN-IN-450a.1 | E28: Probable Maximum Loss (PML) of insured products from weather-related natural catastrophes | F28: 0 | G28: N/A
A29: 11 | B29: Aflac Inc | C29: INSURANCE | D29: FN-IN-450a.2 | E29: Total amount of monetary losses attributable to insurance payouts from (1) modeled natural catastrophes and (2) non-modeled natural catastrophes, by type of event and geographic segment (net and gross of reinsurance) | F29: 0 | G29: N/A
A30: 11 | B30: Aflac Inc | C30: INSURANCE | D30: FN-IN-450a.3 | E30: Description of approach to incorporation of environmental risks into (1) the underwriting process for individual contracts and (2) the management of firm-level risks and capital adequacy | F30: 0 | G30: N/A
A31: 11 | B31: Aflac Inc | C31: INSURANCE | D31: FN-IN-550a.1 | E31: Exposure to derivative instruments by category: (1) total potential exposure to non-centrally cleared derivatives, (2) total fair value of acceptable collateral posted with the Central Clearinghouse, and (3) total potential exposure to centrally cleared derivatives | F31: 0 | G31: N/A
A32: 11 | B32: Aflac Inc | C32: INSURANCE | D32: FN-IN-550a.2 | E32: Total fair value of securities lending collateral assets | F32: 0 | G32: N/A
A33: 11 | B33: Aflac Inc | C33: INSURANCE | D33: FN-IN-550a.3 | E33: Description of approach to managing capital- and liquidity-related risks associated with systemic non-insurance activities | F33: 0 | G33: N/A
A34: 12 | B34: Agilent Technologies Inc | C34: MEDICAL EQUIPMENT & SUPPLIES | D34: HC-MS-240a.1 | E34: Ratio of weighted average rate of net price increases (for all products) to the annual increase in the U.S. Consumer Price Index | F34: 1
A35: 12 | B35: Agilent Technologies Inc | C35: MEDICAL EQUIPMENT & SUPPLIES | D35: HC-MS-240a.2 | E35: Description of how price information for each product is disclosed to customers or to their agents | F35: 1
A36: 12 | B36: Agilent Technologies Inc | C36: MEDICAL EQUIPMENT & SUPPLIES | D36: HC-MS-250a.1 | E36: Number of recalls issued, total units recalled | F36: 1
A37: 12 | B37: Agilent Technologies Inc | C37: MEDICAL EQUIPMENT & SUPPLIES | D37: HC-MS-250a.2 | E37: List of products listed in the FDAâ€™s MedWatch Safety Alerts for Human Medical Products database | F37: 1
A38: 12 | B38: Agilent Technologies Inc | C38: MEDICAL EQUIPMENT & SUPPLIES | D38: HC-MS-250a.3 | E38: Number of fatalities related to products as reported in the FDA Manufacturer and User Facility Device Experiencedatabase | F38: 1
A39: 12 | B39: Agilent Technologies Inc | C39: MEDICAL EQUIPMENT & SUPPLIES | D39: HC-MS-250a.4 | E39: Number of FDA enforcement actions taken in response to violations of current Good Manufacturing Practices (cGMP), by type | F39: 1
A40: 12 | B40: Agilent Technologies Inc | C40: MEDICAL EQUIPMENT & SUPPLIES | D40: HC-MS-270a.1 | E40: Total amount of monetary losses as a result of legal proceedings associated with bribery or corruption | F40: 1
A41: 12 | B41: Agilent Technologies Inc | C41: MEDICAL EQUIPMENT & SUPPLIES | D41: HC-MS-270a.2 | E41: Description of code of ethics governing promotion of off-label use of products | F41: 1
A42: 12 | B42: Agilent Technologies Inc | C42: MEDICAL EQUIPMENT & SUPPLIES | D42: HC-MS-410a.1 | E42: Discussion of process to assess and manage environmental and human health considerations associated with chemicals in products, and meet demand for sustainable products | F42: 1
A43: 12 | B43: Agilent Technologies Inc | C43: MEDICAL EQUIPMENT & SUPPLIES | D43: HC-MS-410a.2 | E43: Total amount of products accepted for take-back and reused, recycled, or donated, broken down by: (1) devices and equipment and (2) supplies | F43: 1
A44: 12 | B44: Agilent Technologies Inc | C44: MEDICAL EQUIPMENT & SUPPLIES | D44: HC-MS-430a.1 | E44: Percentage of (1) entity's facilities and (2) Tier I suppliers' facilities participating in third-party audit programs for manufacturing and product quality | F44: 1
A45: 12 | B45: Agilent Technologies Inc | C45: MEDICAL EQUIPMENT & SUPPLIES | D45: HC-MS-430a.2 | E45: Description of efforts to maintain traceability within the distribution chain | F45: 1
... A57: 14 | B57: AGNC Investment Corp | C57: ASSET MANAGEMENT & CUSTODY | D57: FN-AC-270a.3 | E57: Description of approach to informing customers about products and services | F57: 1
A58: 14 | B58: AGNC Investment Corp | C58: ASSET MANAGEMENT & CUSTODY | D58: FN-AC-550a.2 | E58: Description of approach to incorporation of liquidity risk management programs into portfolio strategy and redemption risk management | F58: 2 | G58: AGNC is not an open-end fund and is not subject to redemption obligations with respect to its preferred or common stock.1 Thus, AGNC is not subject to redemption risk. | H58: Doesn't engage underlying activity
A59: 14 | B59: AGNC Investment Corp | C59: ASSET MANAGEMENT & CUSTODY | D59: FN-AC-550a.3 | E59: Total exposure to securities financing transactions | F59: 1
A60: 14 | B60: AGNC Investment Corp | C60: ASSET MANAGEMENT & CUSTODY | D60: FN-AC-550a.4 | E60: Net exposure to written credit derivatives | F60: 2 | G60: AGNC does not write credit derivatives. | H60: Doesn't engage underlying activity
A61: 15 | B61: AIG - American International Group Inc | C61: INSURANCE | D61: FN-IN-450a.1 | E61: Probable Maximum Loss (PML) of insured products from weather-related natural catastrophes | F61: 1
A62: 15 | B62: AIG - American International Group Inc | C62: INSURANCE | D62: FN-IN-450a.2 | E62: Total amount of monetary losses attributable to insurance payouts from (1) modeled natural catastrophes and (2) non-modeled natural catastrophes, by type of event and geographic segment (net and gross of reinsurance) | F62: 1
A63: 15 | B63: AIG - American International Group Inc | C63: INSURANCE | D63: FN-IN-450a.3 | E63: Description of approach to incorporation of environmental risks into (1) the underwriting process for individual contracts and (2) the management of firm-level risks and capital adequacy | F63: 1
A64: 15 | B64: AIG - American International Group Inc | C64: INSURANCE | D64: FN-IN-410a.1 | E64: Total invested assets, by industry and asset class | F64: 1
A65: 15 | B65: AIG - American International Group Inc | C65: INSURANCE | D65: FN-IN-410a.2 | E65: Description of approach to incorporation of environmental, social, and governance (ESG) factors in investment management processes and strategies | F65: 1
A66: 15 | B66: AIG - American International Group Inc | C66: INSURANCE | D66: FN-IN-410b.1 | E66: Net premiums written related to energy efficiency and low carbon technology | F66: 1
A67: 15 | B67: AIG - American International Group Inc | C67: INSURANCE | D67: FN-IN-410b.2 | E67: Discussion of products and/or product features that incentivize health, safety, and/or environmentally responsible actions and/or behaviors | F67: 1
A68: 15 | B68: AIG - American International Group Inc | C68: INSURANCE | D68: FN-IN-550a.1 | E68: Exposure to derivative instruments by category: (1) total potential exposure to non-centrally cleared derivatives, (2) total fair value of acceptable collateral posted with the Central Clearinghouse, and (3) total potential exposure to centrally cleared derivatives | F68: 1
A69: 15 | B69: AIG - American International Group Inc | C69: INSURANCE | D69: FN-IN-550a.2 | E69: Total fair value of securities lending collateral assets | F69: 1
A70: 15 | B70: AIG - American International Group Inc | C70: INSURANCE | D70: FN-IN-550a.3 | E70: Description of approach to managing capital- and liquidity-related risks associated with systemic non-insurance activities | F70: 1
A71: 15 | B71: AIG - American International Group Inc | C71: INSURANCE | D71: FN-IN-270a.1 | E71: Total amount of monetary losses as a result of legal proceedings associated with marketing and communication of insurance product-related information to new and returning customers | F71: 0 | G71: AIG is in the process of revisiting this metric’s applicability and materiality to the organization. To the extent these disclosures are deemed relevant and applicable to the organization, we will continue to enhance our disclosures in future ESG reports. | H71: Materiality under evaluation
A72: 15 | B72: AIG - American International Group Inc | C72: INSURANCE | D72: FN-IN-270a.2 | E72: Complaints-to-claims ratio | F72: 0 | G72: AIG is in the process of revisiting this metric’s applicability and materiality to the organization. To the extent these disclosures are deemed relevant and applicable to the organization, we will continue to enhance our disclosures in future ESG reports. | H72: Materiality under evaluation
A73: 15 | B73: AIG - American International Group Inc | C73: INSURANCE | D73: FN-IN-270a.3 | E73: Customer retention rate | F73: 0 | G73: AIG is in the process of revisiting this metric’s applicability and materiality to the organization. To the extent these disclosures are deemed relevant and applicable to the organization, we will continue to enhance our disclosures in future ESG reports. | H73: Materiality under evaluation
A74: 15 | B74: AIG - American International Group Inc | C74: INSURANCE | D74: FN-IN-270a.4 | E74: Description of approach to informing customers about products | F74: 1
A75: 15 | B75: AIG - American International Group Inc | C75: ASSET MANAGEMENT & CUSTODY | D75: FN-AC-510a.1 | E75: Total amount of monetary losses as a result of legal proceedings associated with fraud, insider trading, anti-trust, anti-competitive behavior, market manipulation, malpractice, or other related financial industry laws or regulations | F75: 0 | G75: AIG is in the process of revisiting this metric’s applicability and materiality to the organization. To the extent these disclosures are deemed relevant and applicable to the organization, we will continue to enhance our disclosures in future ESG reports. | H75: Materiality under evaluation
A76: 15 | B76: AIG - American International Group Inc | C76: ASSET MANAGEMENT & CUSTODY | D76: FN-AC-510a.2 | E76: Description of whistleblower policies and procedures | F76: 1
A77: 15 | B77: AIG - American International Group Inc | C77: ASSET MANAGEMENT & CUSTODY | D77: FN-AC-330a.1 | E77: Percentage of gender and racial/ethnic group representation for (1) executive management, (2) non-executive management, (3) professionals, and (4) all other employees | F77: 1
A78: 15 | B78: AIG - American International Group Inc | C78: ASSET MANAGEMENT & CUSTODY | D78: FN-AC-410a.1 | E78: Amount of assets under management, by asset class, that employ (1) integration of environmental, social, and governance (ESG) issues, (2) sustainability themed investing, and (3) screening | F78: 1
A79: 15 | B79: AIG - American International Group Inc | C79: ASSET MANAGEMENT & CUSTODY | D79: FN-AC-410a.2 | E79: Description of approach to incorporation of environmental, social, and governance (ESG) factors in investment and/or wealth management processes and strategies | F79: 1
A80: 15 | B80: AIG - American International Group Inc | C80: ASSET MANAGEMENT & CUSTODY | D80: FN-AC-410a.3 | E80: Description of proxy voting and investee engagement policies and procedures | F80: 0 | G80: AIG is in the process of revisiting this metric’s applicability and materiality to the organization. To the extent these disclosures are deemed relevant and applicable to the organization, we will continue to enhance our disclosures in future ESG reports. | H80: Materiality under evaluation
A81: 15 | B81: AIG - American International Group Inc | C81: ASSET MANAGEMENT & CUSTODY | D81: FN-AC-270a.1 | E81: (1) Number and (2) percentage of covered employees with a record of investment-related investigations, consumer-initiated complaints, private civil litigations, or other regulatory proceedings | F81: 0 | G81: AIG is in the process of revisiting this metric’s applicability and materiality to the organization. To the extent these disclosures are deemed relevant and applicable to the organization, we will continue to enhance our disclosures in future ESG reports. | H81: Materiality under evaluation
A82: 15 | B82: AIG - American International Group Inc | C82: ASSET MANAGEMENT & CUSTODY | D82: FN-AC-270a.2 | E82: Total amount of monetary losses as a result of legal proceedings associated with marketing and communication of financial product-related information to new and returning customers | F82: 0 | G82: AIG is in the process of revisiting this metric’s applicability and materiality to the organization. To the extent these disclosures are deemed relevant and applicable to the organization, we will continue to enhance our disclosures in future ESG reports. | H82: Materiality under evaluation
A83: 15 | B83: AIG - American International Group Inc | C83: ASSET MANAGEMENT & CUSTODY | D83: FN-AC-270a.3 | E83: Description of approach to informing customers about products and services | F83: 0 | G83: AIG is in the process of revisiting this metric’s applicability and materiality to the organization. To the extent these disclosures are deemed relevant and applicable to the organization, we will continue to enhance our disclosures in future ESG reports. | H83: Materiality under evaluation
A84: 17 | B84: Akamai Technologies Inc | C84: SOFTWARE & IT SERVICES | D84: TC-SI-220a.1 | E84: Description of policies and practices relating to behavioral advertising and user privacy | F84: 0 | G84: N/A
A85: 17 | B85: Akamai Technologies Inc | C85: SOFTWARE & IT SERVICES | D85: TC-SI-220a.2 | E85: Number of users whose information is used for secondary purposes | F85: 0 | G85: N/A
A86: 17 | B86: Akamai Technologies Inc | C86: SOFTWARE & IT SERVICES | D86: TC-SI-220a.3 | E86: Total amount of monetary losses as a result of legal proceedings associated with user privacy | F86: 0 | G86: N/A
A87: 17 | B87: Akamai Technologies Inc | C87: SOFTWARE & IT SERVICES | D87: TC-SI-220a.4 | E87: (1) Number of law enforcement requests for user information, (2) number of users whose information was requested, (3) percentage resulting in disclosure | F87: 0 | G87: N/A
A88: 17 | B88: Akamai Technologies Inc | C88: SOFTWARE & IT SERVICES | D88: TC-SI-220a.5 | E88: List of countries where core products or services are subject to government-required monitoring, blocking, content filtering, or censoring | F88: 0 | G88: N/A
A89: 17 | B89: Akamai Technologies Inc | C89: SOFTWARE & IT SERVICES | D89: TC-SI-230a.1 | E89: (1) Number of data breaches, (2) percentage involving personally identifiable information (PII), (3) number of users affected | F89: 0 | G89: N/A
A90: 17 | B90: Akamai Technologies Inc | C90: SOFTWARE & IT SERVICES | D90: TC-SI-230a.2 | E90: Description of approach to identifying and addressing data security risks, including use of third-party cybersecurity standards | F90: 0 | G90: N/A
A91: 17 | B91: Akamai Technologies Inc | C91: SOFTWARE & IT SERVICES | D91: TC-SI-130a.1 | E91: (1) Total energy consumed, (2) percentage grid electricity, (3) percentage renewable | F91: 1
A92: 17 | B92: Akamai Technologies Inc | C92: SOFTWARE & IT SERVICES | D92: TC-SI-130a.2 | E92: (1) Total water withdrawn, (2) total water consumed, percentage of each in regions with High or Extremely High Baseline Water Stress | F92: 1
A93: 17 | B93: Akamai Technologies Inc | C93: SOFTWARE & IT SERVICES | D93: TC-SI-130a.3 | E93: Discussion of the integration of environmental considerations into strategic planning for data center needs | F93: 0 | G93: N/A
A94: 17 | B94: Akamai Technologies Inc | C94: SOFTWARE & IT SERVICES | D94: TC-SI-520a.1 | E94: Total amount of monetary losses as a result of legal proceedings associated with anti-competitive behavior regulations | F94: 0 | G94: N/A
A95: 17 | B95: Akamai Technologies Inc | C95: SOFTWARE & IT SERVICES | D95: TC-SI-550a.1 | E95: Number of (1) performance issues and (2) service disruptions; (3) total customer downtime | F95: 0 | G95: N/A
A96: 17 | B96: Akamai Technologies Inc | C96: SOFTWARE & IT SERVICES | D96: TC-SI-550a.2 | E96: Description of business continuity risks related to disruptions of operations | F96: 0 | G96: N/A
A97: 17 | B97: Akamai Technologies Inc | C97: SOFTWARE & IT SERVICES | D97: TC-SI-330a.1 | E97: Percentage of employees that are (1) foreign nationals and (2) located offshore | F97: 0 | G97: N/A
A98: 17 | B98: Akamai Technologies Inc | C98: SOFTWARE & IT SERVICES | D98: TC-SI-330a.2 | E98: Employee engagement as a percentage | F98: 0 | G98: N/A
A99: 17 | B99: Akamai Technologies Inc | C99: SOFTWARE & IT SERVICES | D99: TC-SI-330a.3 | E99: Percentage of gender and racial/ethnic group representation for (1) management, (2) technical staff, and (3) all other employees | F99: 0 | G99: N/A
A100: 21 | B100: Albemarle Corp | C100: CHEMICALS | D100: RT-CH-120a.1 | E100: Air emissions of the following pollutants: (1) NOX (excluding N2O), (2) SOX, (3) volatile organic compounds (VOCs), and (4) hazardous air pollutants (HAPs) | F100: 1
A101: 21 | B101: Albemarle Corp | C101: CHEMICALS | D101: RT-CH-210a.1 | E101: Discussion of engagement processes to manage risks and opportunities associated with community interests | F101: 0 | G101: N/A
A102: 21 | B102: Albemarle Corp | C102: CHEMICALS | D102: RT-CH-130a.1 | E102: (1) Total energy consumed, (2) percentage grid electricity, (3) percentage renewable, (4) total self-generated energy | F102: 1
A103: 21 | B103: Albemarle Corp | C103: CHEMICALS | D103: RT-CH-410c.1 | E103: Percentage of products by revenue that contain genetically modified organisms (GMOs) | F103: 0 | G103: N/A
A104: 21 | B104: Albemarle Corp | C104: CHEMICALS | D104: RT-CH-110a.1 | E104: Gross global Scope 1 emissions, percentage covered under emissions-limiting regulations | F104: 1
A105: 21 | B105: Albemarle Corp | C105: CHEMICALS | D105: RT-CH-110a.2 | E105: Discussion of long-term and short-term strategy or plan to manage Scope 1 emissions, emissions reduction targets, and an analysis of performance against those targets | F105: 1
A106: 21 | B106: Albemarle Corp | C106: CHEMICALS | D106: RT-CH-150a.1 | E106: Amount of hazardous waste generated, percentage recycled | F106: 1
A107: 21 | B107: Albemarle Corp | C107: CHEMICALS | D107: RT-CH-530a.1 | E107: Discussion of corporate positions related to government regulations and/or policy proposals that address environmental and social factors affecting the industry | F107: 0 | G107: N/A
A108: 21 | B108: Albemarle Corp | C108: CHEMICALS | D108: RT-CH-540a.1 | E108: Process Safety Incidents Count (PSIC), Process Safety Total Incident Rate (PSTIR), and Process Safety Incident Severity Rate (PSISR) | F108: 0 | G108: N/A
A109: 21 | B109: Albemarle Corp | C109: CHEMICALS | D109: RT-CH-540a.2 | E109: Number of transport incidents | F109: 0 | G109: N/A
A110: 21 | B110: Albemarle Corp | C110: CHEMICALS | D110: RT-CH-410a.1 | E110: Revenue from products designed for use-phase resource efficiency | F110: 1
A111: 21 | B111: Albemarle Corp | C111: CHEMICALS | D111: RT-CH-410b.1 | E111: (1) Percentage of products that contain Globally Harmonized System of Classification and Labeling of Chemicals (GHS) Category 1 and 2 Health and Environmental Hazardous Substances, (2) percentage of such products that have undergone a hazard assessment | F111: 0 | G111: N/A
...

Sheet Losses
A1: Line in Master | B1: Company | C1: Industry | D1: Code | E1: Reported | F1: Topics | G1: Metrics | H1: code_ind1 | I1: code_ind2 | J1: code_topic | K1: ind_code | L1: Disclosed Amount | M1: Violation Tracker | N1: Date | O1: Primary Offense Type | P1: Violation Description | Q1: Agency | R1: Amount | S1: Link
A2: 11 | B2: Aflac Inc | C2: INSURANCE | D2: FN-IN-270a.1 | E2: 1 | F2: Transparent Information & Fair Advice for Customers | G2: Total amount of monetary losses as a result of legal proceedings associated with marketing and communication of insurance product-related information to new and returning customers | H2: FN | I2: IN | J2: 270 | K2: FN-IN | L2: Refered to 10K/Q | M2: No
A3: 11 | B3: Aflac Inc | C3: INSURANCE | D3: FN-IN-450a.2 | E3: 0 | F3: Environmental Risk Exposure | G3: Total amount of monetary losses attributable to insurance payouts from (1) modeled natural catastrophes and (2) non-modeled natural catastrophes, by type of event and geographic segment (net and gross of reinsurance) | H3: FN | I3: IN | J3: 450 | K3: FN-IN | L3: Refered to 10K/Q | M3: No
A4: 12 | B4: Agilent Technologies Inc | C4: MEDICAL EQUIPMENT & SUPPLIES | D4: HC-MS-270a.1 | E4: 1 | F4: Ethical Marketing | G4: Total amount of monetary losses as a result of legal proceedings associated with false marketing claims | H4: HC | I4: MS | J4: 270 | K4: HC-MS | L4: 0 | M4: No
A5: 12 | B5: Agilent Technologies Inc | C5: MEDICAL EQUIPMENT & SUPPLIES | D5: HC-MS-510a.1 | E5: 1 | F5: Business Ethics | G5: Total amount of monetary losses as a result of legal proceedings associated with bribery or corruption | H5: HC | I5: MS | J5: 510 | K5: HC-MS | L5: 0 | M5: No
A6: 14 | B6: AGNC Investment Corp | C6: ASSET MANAGEMENT & CUSTODY | D6: FN-AC-510a.1 | E6: 1 | F6: Business Ethics | G6: Total amount of monetary losses as a result of legal proceedings associated with fraud, insider trading, anti-trust, anti-competitive behavior, market manipulation, malpractice, or other related financial industry laws or regulations | H6: FN | I6: AC | J6: 510 | K6: FN-AC | L6: 0 | M6: No
A7: 14 | B7: AGNC Investment Corp | C7: ASSET MANAGEMENT & CUSTODY | D7: FN-AC-270a.2 | E7: 1 | F7: Transparent Information & Fair Advice for Customers | G7: Total amount of monetary losses as a result of legal proceedings associated with marketing and communication of financial product-related information to new and returning customers | H7: FN | I7: AC | J7: 270 | K7: FN-AC | L7: 0 | M7: No
A8: 15 | B8: AIG - American International Group Inc | C8: INSURANCE | D8: FN-IN-450a.2 | E8: 1 | F8: Environmental Risk Exposure | G8: Total amount of monetary losses attributable to insurance payouts from (1) modeled natural catastrophes and (2) non-modeled natural catastrophes, by type of event and geographic segment (net and gross of reinsurance) | H8: FN | I8: IN | J8: 450 | K8: FN-IN | L8: 0 | M8: No
A9: 15 | B9: AIG - American International Group Inc | C9: INSURANCE | D9: FN-IN-270a.1 | E9: 0 | F9: Transparent Information & Fair Advice for Customers | G9: Total amount of monetary losses as a result of legal proceedings associated with marketing and communication of insurance product-related information to new and returning customers | H9: FN | I9: IN | J9: 270 | K9: FN-IN | M9: No
A10: 15 | B10: AIG - American International Group Inc | C10: ASSET MANAGEMENT & CUSTODY | D10: FN-AC-510a.1 | E10: 0 | F10: Business Ethics | G10: Total amount of monetary losses as a result of legal proceedings associated with fraud, insider trading, anti-trust, anti-competitive behavior, market manipulation, malpractice, or other related financial industry laws or regulations | H10: FN | I10: AC | J10: 510 | K10: FN-AC | M10: No
A11: 15 | B11: AIG - American International Group Inc | C11: ASSET MANAGEMENT & CUSTODY | D11: FN-AC-270a.2 | E11: 0 | F11: Transparent Information & Fair Advice for Customers | G11: Total amount of monetary losses as a result of legal proceedings associated with marketing and communication of financial product-related information to new and returning customers | H11: FN | I11: AC | J11: 270 | K11: FN-AC | M11: No
A12: 17 | B12: Akamai Technologies Inc | C12: SOFTWARE & IT SERVICES | D12: TC-SI-220a.3 | E12: 0 | F12: Data Privacy & Freedom of Expression | G12: Total amount of monetary losses as a result of legal proceedings associated with user privacy | H12: TC | I12: SI | J12: 220 | K12: TC-SI | M12: No
A13: 17 | B13: Akamai Technologies Inc | C13: SOFTWARE & IT SERVICES | D13: TC-SI-520a.1 | E13: 0 | F13: Intellectual Property Protection & Competitive Behavior | G13: Total amount of monetary losses as a result of legal proceedings associated with anti-competitive behavior regulations | H13: TC | I13: SI | J13: 520 | K13: TC-SI | M13: No
A14: 27 | B14: Alliance Data Systems Corp | C14: COMMERCIAL BANKS | D14: FN-CB-510a.1 | E14: 1 | F14: Business Ethics | G14: Total amount of monetary losses as a result of legal proceedings associated with fraud, insider trading, anti-trust, anti-competitive behavior, market manipulation, malpractice, or other related financial industry laws or regulations | H14: FN | I14: CB | J14: 510 | K14: FN-CB | M14: No
A15: 27 | B15: Alliance Data Systems Corp | C15: SOFTWARE & IT SERVICES | D15: TC-SI-220a.3 | E15: 0 | F15: Data Privacy & Freedom of Expression | G15: Total amount of monetary losses as a result of legal proceedings associated with user privacy | H15: TC | I15: SI | J15: 220 | K15: TC-SI | M15: No
A16: 27 | B16: Alliance Data Systems Corp | C16: SOFTWARE & IT SERVICES | D16: TC-SI-520a.1 | E16: 0 | F16: Intellectual Property Protection & Competitive Behavior | G16: Total amount of monetary losses as a result of legal proceedings associated with anti-competitive behavior regulations | H16: TC | I16: SI | J16: 520 | K16: TC-SI | M16: No
A17: 28 | B17: Alliance Data Systems Corp | C17: COMMERCIAL BANKS | D17: FN-CB-510a.1 | E17: 1 | F17: Business Ethics | G17: Total amount of monetary losses as a result of legal proceedings associated with fraud, insider trading, anti-trust, anti-competitive behavior, market manipulation, malpractice, or other related financial industry laws or regulations | H17: FN | I17: CB | J17: 510 | K17: FN-CB | M17: No
A18: 28 | B18: Alliance Data Systems Corp | C18: SOFTWARE & IT SERVICES | D18: TC-SI-220a.3 | E18: 0 | F18: Data Privacy & Freedom of Expression | G18: Total amount of monetary losses as a result of legal proceedings associated with user privacy | H18: TC | I18: SI | J18: 220 | K18: TC-SI | M18: No
A19: 28 | B19: Alliance Data Systems Corp | C19: SOFTWARE & IT SERVICES | D19: TC-SI-520a.1 | E19: 0 | F19: Intellectual Property Protection & Competitive Behavior | G19: Total amount of monetary losses as a result of legal proceedings associated with anti-competitive behavior regulations | H19: TC | I19: SI | J19: 520 | K19: TC-SI | M19: No
A20: 36 | B20: American Airlines Group Inc | C20: AIRLINES | D20: TR-AL-520a.1 | E20: 1 | F20: Competitive Behavior | G20: Total amount of monetary losses as a result of legal proceedings associated with anti-competitive behavior regulations | H20: TR | I20: AL | J20: 520 | K20: TR-AL | L20: 0 | M20: Yes | N20: 43598 | O20: price-fixing or anti-competitive practices | Q20: private lawsuit-federal | R20: 45000000 | S20: https://violationtracker.goodjobsfirst.org/violation-tracker/-american-airlines-20
A21: 39 | B21: American Express Co | C21: CONSUMER FINANCE | D21: FN-CF-220a.2 | E21: 1 | F21: Customer Privacy | G21: Total amount of monetary losses as a result of legal proceedings associated with customer privacy | H21: FN | I21: CF | J21: 220 | K21: FN-CF | L21: 0 | M21: No
A22: 39 | B22: American Express Co | C22: CONSUMER FINANCE | D22: FN-CF-270a.4 | E22: 1 | F22: Selling Practices | G22: (1) Number of complaints filed with the Consumer Financial Protection Bureau (CFPB), (2) percentage with monetary or non-monetary relief, (3) percentage disputed by consumer, (4) percentage that resulted in investigation by the CFPB | H22: FN | I22: CF | J22: 270 | K22: FN-CF | L22: 0 | M22: No
A23: 39 | B23: American Express Co | C23: CONSUMER FINANCE | D23: FN-CF-270a.5 | E23: 1 | F23: Selling Practices | G23: Total amount of monetary losses as a result of legal proceedings associated with selling and servicing of products | H23: FN | I23: CF | J23: 270 | K23: FN-CF | L23: 0 | M23: No
A24: 39 | B24: American Express Co | C24: COMMERCIAL BANKS | D24: FN-CB-510a.1 | E24: 1 | F24: Business Ethics | G24: Total amount of monetary losses as a result of legal proceedings associated with fraud, insider trading, anti-trust, anti-competitive behavior, market manipulation, malpractice, or other related financial industry laws or regulations | H24: FN | I24: CB | J24: 510 | K24: FN-CB | L24: 0 | M24: No
A25: 39 | B25: American Express Co | C25: SOFTWARE & IT SERVICES | D25: TC-SI-220a.3 | E25: 1 | F25: Data Privacy & Freedom of Expression | G25: Total amount of monetary losses as a result of legal proceedings associated with user privacy | H25: TC | I25: SI | J25: 220 | K25: TC-SI | L25: 0 | M25: No
A26: 39 | B26: American Express Co | C26: SOFTWARE & IT SERVICES | D26: TC-SI-520a.1 | E26: 1 | F26: Intellectual Property Protection & Competitive Behavior | G26: Total amount of monetary losses as a result of legal proceedings associated with anti-competitive behavior regulations | H26: TC | I26: SI | J26: 520 | K26: TC-SI | L26: 0 | M26: No
A27: 42 | B27: American Tower Corp | C27: TELECOMMUNICATION SERVICES | D27: TC-TL-520a.1 | E27: 1 | F27: Competitive Behavior & Open Internet | G27: Total amount of monetary losses as a result of legal proceedings associated with anti-competitive behavior regulations | H27: TC | I27: TL | J27: 520 | K27: TC-TL | L27: 0 | M27: No
A28: 42 | B28: American Tower Corp | C28: TELECOMMUNICATION SERVICES | D28: TC-TL-220a.3 | E28: 0 | F28: Data Privacy | G28: Total amount of monetary losses as a result of legal proceedings associated with customer privacy | H28: TC | I28: TL | J28: 220 | K28: TC-TL | L28: 0 | M28: No
A29: 48 | B29: Amphenol Corp | C29: ELECTRICAL & ELECTRONIC EQUIPMENT | D29: RT-EE-510a.2 | E29: 1 | F29: Business Ethics | G29: Total amount of monetary losses as a result of legal proceedings associated with bribery or corruption | H29: RT | I29: EE | J29: 510 | K29: RT-EE | L29: 0 | M29: No
A30: 48 | B30: Amphenol Corp | C30: ELECTRICAL & ELECTRONIC EQUIPMENT | D30: RT-EE-510a.3 | E30: 1 | F30: Business Ethics | G30: Total amount of monetary losses as a result of legal proceedings associated with anti-competitive behavior regulations | H30: RT | I30: EE | J30: 510 | K30: RT-EE | M30: No
A31: 48 | B31: Amphenol Corp | C31: ELECTRICAL & ELECTRONIC EQUIPMENT | D31: RT-EE-250a.2 | E31: 0 | F31: Product Safety | G31: Total amount of monetary losses as a result of legal proceedings associated with product safety | H31: RT | I31: EE | J31: 250 | K31: RT-EE | M31: No
A32: 49 | B32: Amphenol Corp | C32: ELECTRICAL & ELECTRONIC EQUIPMENT | D32: RT-EE-510a.2 | E32: 0 | F32: Business Ethics | G32: Total amount of monetary losses as a result of legal proceedings associated with bribery or corruption | H32: RT | I32: EE | J32: 510 | K32: RT-EE | M32: No
A33: 49 | B33: Amphenol Corp | C33: ELECTRICAL & ELECTRONIC EQUIPMENT | D33: RT-EE-510a.3 | E33: 0 | F33: Business Ethics | G33: Total amount of monetary losses as a result of legal proceedings associated with anti-competitive behavior regulations | H33: RT | I33: EE | J33: 510 | K33: RT-EE | M33: No
A34: 49 | B34: Amphenol Corp | C34: ELECTRICAL & ELECTRONIC EQUIPMENT | D34: RT-EE-250a.2 | E34: 0 | F34: Product Safety | G34: Total amount of monetary losses as a result of legal proceedings associated with product safety | H34: RT | I34: EE | J34: 250 | K34: RT-EE | M34: No
A35: 50 | B35: Amphenol Corp | C35: ELECTRICAL & ELECTRONIC EQUIPMENT | D35: RT-EE-510a.2 | E35: 0 | F35: Business Ethics | G35: Total amount of monetary losses as a result of legal proceedings associated with bribery or corruption | H35: RT | I35: EE | J35: 510 | K35: RT-EE | M35: No
A36: 50 | B36: Amphenol Corp | C36: ELECTRICAL & ELECTRONIC EQUIPMENT | D36: RT-EE-510a.3 | E36: 0 | F36: Business Ethics | G36: Total amount of monetary losses as a result of legal proceedings associated with anti-competitive behavior regulations | H36: RT | I36: EE | J36: 510 | K36: RT-EE | M36: No
A37: 50 | B37: Amphenol Corp | C37: ELECTRICAL & ELECTRONIC EQUIPMENT | D37: RT-EE-250a.2 | E37: 0 | F37: Product Safety | G37: Total amount of monetary losses as a result of legal proceedings associated with product safety | H37: RT | I37: EE | J37: 250 | K37: RT-EE | M37: No
A38: 52 | B38: Annaly Capital Management Inc | C38: ASSET MANAGEMENT & CUSTODY | D38: FN-AC-270a.2 | E38: 1 | F38: Transparent Information & Fair Advice for Customers | G38: Total amount of monetary losses as a result of legal proceedings associated with marketing and communication of financial product-related information to new and returning customers | H38: FN | I38: AC | J38: 270 | K38: FN-AC | M38: No
A39: 52 | B39: Annaly Capital Management Inc | C39: ASSET MANAGEMENT & CUSTODY | D39: FN-AC-510a.1 | E39: 1 | F39: Business Ethics | G39: Total amount of monetary losses as a result of legal proceedings associated with fraud, insider trading, anti-trust, anti-competitive behavior, market manipulation, malpractice, or other related financial industry laws or regulations | H39: FN | I39: AC | J39: 510 | K39: FN-AC | M39: No
A40: 52 | B40: Annaly Capital Management Inc | C40: MORTGAGE FINANCE | D40: FN-MF-270a.3 | E40: 1 | F40: Lending Practices | G40: Total amount of monetary losses as a result of legal proceedings associated with communications to customers or remuneration of loan originators | H40: FN | I40: MF | J40: 270 | K40: FN-MF | M40: No
A41: 52 | B41: Annaly Capital Management Inc | C41: MORTGAGE FINANCE | D41: FN-MF-270b.2 | E41: 1 | F41: Discriminatory Lending | G41: Total amount of monetary losses as a result of legal proceedings associated with discriminatory mortgage lending | H41: FN | I41: MF | J41: 270 | K41: FN-MF | M41: No
... A56: 98 | B56: Blackbaud, Inc. | C56: SOFTWARE & IT SERVICES | D56: TC-SI-520a.1 | E56: 1 | F56: Intellectual Property Protection & Competitive Behavior | G56: Total amount of monetary losses as a result of legal proceedings associated with anti-competitive behavior regulations | H56: TC | I56: SI | J56: 520 | K56: TC-SI | M56: No
A57: 120 | B57: Burlington Stores Inc | C57: MULTILINE AND SPECIALTY RETAILERS & DISTRIBUTORS | D57: CG-MR-310a.3 | E57: 0 | F57: Labor Practices | G57: Total amount of monetary losses as a result of legal proceedings associated with labor law violations | H57: CG | I57: MR | J57: 310 | K57: CG-MR | M57: Yes | N57: 44042 | O57: workplace safety or health violation | Q57: Occupational Safety & Health Administration | R57: 6000 | S57: https://violationtracker.goodjobsfirst.org/violation-tracker/wa-burlington-coat-factory-warehouse-of-aub
N58: 44180 | O58: wage and hour violation | R58: 19613900 | S58: https://violationtracker.goodjobsfirst.org/violation-tracker/-burlington-coat-factory-warehouse-corpor-1
A59: 120 | B59: Burlington Stores Inc | C59: MULTILINE AND SPECIALTY RETAILERS & DISTRIBUTORS | D59: CG-MR-330a.2 | E59: 0 | F59: Workforce Diversity & Inclusion | G59: Total amount of monetary losses as a result of legal proceedings associated with employment discrimination | H59: CG | I59: MR | J59: 330 | K59: CG-MR | M59: No
A60: 124 | B60: Calavo Growers Inc | C60: PROCESSED FOODS | D60: FB-PF-270a.4 | E60: 1 | F60: Product Labeling & Marketing | G60: Total amount of monetary losses as a result of legal proceedings associated with labeling and/or marketing practices | H60: FB | I60: PF | J60: 270 | K60: FB-PF | M60: No
A61: 130 | B61: Cardinal Health Inc | C61: HEALTH CARE DISTRIBUTORS | D61: HC-DI-510a.2 | E61: 1 | F61: Business Ethics | G61: Total amount of monetary losses as a result of legal proceedings associated with bribery, corruption, or other unethical business practices | H61: HC | I61: DI | J61: 510 | K61: HC-DI | L61: $ 8.8 million | M61: Yes | N61: 43889 | O61: Foreign Corrupt Practices Act | Q61: Securities and Exchange Commission | R61: 8000000 | S61: https://violationtracker.goodjobsfirst.org/violation-tracker/-cardinal-health-inc-4
A62: 130 | B62: Cardinal Health Inc | C62: HEALTH CARE DISTRIBUTORS | D62: HC-DI-250a.1 | E62: 1 | F62: Product Safety | G62: Total amount of monetary losses as a result of legal proceedings associated with product safety | H62: HC | I62: DI | J62: 250 | K62: HC-DI | M62: No
A63: 131 | B63: Carrier Global Corp | C63: ELECTRICAL & ELECTRONIC EQUIPMENT | D63: RT-EE-510a.2 | E63: 1 | F63: Business Ethics | G63: Total amount of monetary losses as a result of legal proceedings associated with bribery or corruption | H63: RT | I63: EE | J63: 510 | K63: RT-EE | M63: No
A64: 131 | B64: Carrier Global Corp | C64: ELECTRICAL & ELECTRONIC EQUIPMENT | D64: RT-EE-510a.3 | E64: 1 | F64: Business Ethics | G64: Total amount of monetary losses as a result of legal proceedings associated with anti-competitive behavior regulations | H64: RT | I64: EE | J64: 510 | K64: RT-EE | M64: No
A65: 131 | B65: Carrier Global Corp | C65: ELECTRICAL & ELECTRONIC EQUIPMENT | D65: RT-EE-250a.2 | E65: 0 | F65: Product Safety | G65: Total amount of monetary losses as a result of legal proceedings associated with product safety | H65: RT | I65: EE | J65: 250 | K65: RT-EE | M65: No
A66: 132 | B66: Catalent Inc | C66: BIOTECHNOLOGY & PHARMACEUTICALS | D66: HC-BP-510a.1 | E66: 1 | F66: Business Ethics | G66: Total amount of monetary losses as a result of legal proceedings associated with corruption and bribery | H66: HC | I66: BP | J66: 510 | K66: HC-BP | M66: No
A67: 132 | B67: Catalent Inc | C67: BIOTECHNOLOGY & PHARMACEUTICALS | D67: HC-BP-270a.1 | E67: 2 | F67: Ethical Marketing | G67: Total amount of monetary losses as a result of legal proceedings associated with false marketing claims | H67: HC | I67: BP | J67: 270 | K67: HC-BP | M67: No
A68: 132 | B68: Catalent Inc | C68: BIOTECHNOLOGY & PHARMACEUTICALS | D68: HC-BP-210a.3 | E68: 1 | F68: Safety of Clinical Trial Participants | G68: Total amount of monetary losses as a result of legal proceedings associated with clinical trials in developing countries | H68: HC | I68: BP | J68: 210 | K68: HC-BP | M68: No
A69: 133 | B69: Catalent Inc | C69: BIOTECHNOLOGY & PHARMACEUTICALS | D69: HC-BP-510a.1 | E69: 1 | F69: Business Ethics | G69: Total amount of monetary losses as a result of legal proceedings associated with corruption and bribery | H69: HC | I69: BP | J69: 510 | K69: HC-BP | M69: No
A70: 133 | B70: Catalent Inc | C70: BIOTECHNOLOGY & PHARMACEUTICALS | D70: HC-BP-270a.1 | E70: 2 | F70: Ethical Marketing | G70: Total amount of monetary losses as a result of legal proceedings associated with false marketing claims | H70: HC | I70: BP | J70: 270 | K70: HC-BP
A71: 133 | B71: Catalent Inc | C71: BIOTECHNOLOGY & PHARMACEUTICALS | D71: HC-BP-210a.3 | E71: 1 | F71: Safety of Clinical Trial Participants | G71: Total amount of monetary losses as a result of legal proceedings associated with clinical trials in developing countries | H71: HC | I71: BP | J71: 210 | K71: HC-BP | M71: No
A72: 142 | B72: Century Communities Inc | C72: HOME BUILDERS | D72: IF-HB-160a.3 | E72: 1 | F72: Land Use & Ecological Impacts | G72: Total amount of monetary losses as a result of legal proceedings associated with environmental regulations | H72: IF | I72: HB | J72: 160 | K72: IF-HB | M72: No
A73: 146 | B73: CH Robinson Worldwide Inc | C73: AIR FREIGHT & LOGISTICS | D73: TR-AF-310a.2 | E73: 0 | F73: Labor Practices | G73: Total amount of monetary losses as a result of legal proceedings associated with labor law violations | H73: TR | I73: AF | J73: 310 | K73: TR-AF | M73: No
A74: 147 | B74: Charah Solutions Inc | C74: ENGINEERING & CONSTRUCTION | D74: IF-EN-510a.2 | E74: 1 | F74: Business Ethics | G74: Total amount of monetary losses as a result of legal proceedings associated with charges of (1) bribery or corruption and (2) anti-competitive practices | H74: IF | I74: EN | J74: 510 | K74: IF-EN | M74: No
A75: 147 | B75: Charah Solutions Inc | C75: ENGINEERING & CONSTRUCTION | D75: IF-EN-250a.2 | E75: 1 | F75: Structural Integrity & Safety | G75: Total amount of monetary losses as a result of legal proceedings associated with defect- and safety-related incidents | H75: IF | I75: EN | J75: 250 | K75: IF-EN | M75: No
A76: 154 | B76: Cheniere Energy Partners LP | C76: OIL & GAS - MIDSTREAM | D76: EM-MD-520a.1 | E76: 0 | F76: Competitive Behavior | G76: Total amount of monetary losses as a result of legal proceedings associated with federal pipeline and storage regulations | H76: EM | I76: MD | J76: 520 | K76: EM-MD | M76: No
A77: 154 | B77: Cheniere Energy Partners LP | C77: OIL & GAS - REFINING & MARKETING | D77: EM-RM-520a.1 | E77: 0 | F77: Pricing Integrity & Transparency | G77: Total amount of monetary losses as a result of legal proceedings associated with price fixing or price manipulation | H77: EM | I77: RM | J77: 520 | K77: EM-RM | M77: No
A78: 157 | B78: Chipotle Mexican Grill Inc | C78: RESTAURANTS | D78: FB-RN-310a.3 | E78: 0 | F78: Labor Practices | G78: Total amount of monetary losses as a result of legal proceedings associated with (1) labor law violations and (2) employment discrimination | H78: FB | I78: RN | J78: 310 | K78: FB-RN | M78: Yes | N78: 44013 | O78: employment discrimination | R78: 46220 | S78: https://violationtracker.goodjobsfirst.org/violation-tracker/ny-chipotle-mexican-grill-inc-0
A79: 164 | B79: Citigroup Inc (Citi) | C79: COMMERCIAL BANKS | D79: FN-CB-510a.1 | E79: 0 | F79: Business Ethics | G79: Total amount of monetary losses as a result of legal proceedings associated with fraud, insider trading, anti-trust, anti-competitive behavior, market manipulation, malpractice, or other related financial industry laws or regulations | H79: FN | I79: CB | J79: 510 | K79: FN-CB | L79: Refer to 10K, no amount | M79: Yes | N79: 44000 | O79: price-fixing or anti-competitive practices | R79: 20833333 | S79: https://violationtracker.goodjobsfirst.org/violation-tracker/-citigroup-global-markets-inc-34
N80: 44091 | O80: price-fixing or anti-competitive practices | R80: 33400000 | S80: https://violationtracker.goodjobsfirst.org/violation-tracker/-citibank-na-15
N81: 44102 | O81: investor protection violation | R81: 4500000 | S81: https://violationtracker.goodjobsfirst.org/violation-tracker/-citibank-na-11
N82: 44109 | O82: price-fixing or anti-competitive practices | R82: 7025000 | S82: https://violationtracker.goodjobsfirst.org/violation-tracker/-citibank-na-14
N83: 44154 | O83: price-fixing or anti-competitive practices | R83: 9950000 | S83: https://violationtracker.goodjobsfirst.org/violation-tracker/-citigroup-inc-15
A84: 164 | B84: Citigroup Inc (Citi) | C84: CONSUMER FINANCE | D84: FN-CF-220a.2 | E84: 1 | F84: Customer Privacy | G84: Total amount of monetary losses as a result of legal proceedings associated with customer privacy | H84: FN | I84: CF | J84: 220 | K84: FN-CF | M84: No
A85: 164 | B85: Citigroup Inc (Citi) | C85: CONSUMER FINANCE | D85: FN-CF-270a.4 | E85: 0 | F85: Selling Practices | G85: (1) Number of complaints filed with the Consumer Financial Protection Bureau (CFPB), (2) percentage with monetary or non-monetary relief, (3) percentage disputed by consumer, (4) percentage that resulted in investigation by the CFPB | H85: FN | I85: CF | J85: 270 | K85: FN-CF | M85: No
A86: 164 | B86: Citigroup Inc (Citi) | C86: CONSUMER FINANCE | D86: FN-CF-270a.5 | E86: 1 | F86: Selling Practices | G86: Total amount of monetary losses as a result of legal proceedings associated with selling and servicing of products | H86: FN | I86: CF | J86: 270 | K86: FN-CF | M86: No
A87: 164 | B87: Citigroup Inc (Citi) | C87: INVESTMENT BANKING & BROKERAGE | D87: FN-IB-510a.1 | E87: 0 | F87: Business Ethics | G87: Total amount of monetary losses as a result of legal proceedings associated with fraud, insider trading, anti-trust, anti-competitive behavior, market manipulation, malpractice, or other related financial industry laws or regulations | H87: FN | I87: IB | J87: 510 | K87: FN-IB | L87: Refer to 10K, no amount | M87: Yes | N87: 44000 | O87: price-fixing or anti-competitive practices | R87: 20833333 | S87: https://violationtracker.goodjobsfirst.org/violation-tracker/-citigroup-global-markets-inc-34 | T87: Duplicated
N88: 44091 | O88: price-fixing or anti-competitive practices | R88: 33400000 | S88: https://violationtracker.goodjobsfirst.org/violation-tracker/-citibank-na-15 | T88: Duplicated
N89: 44109 | O89: price-fixing or anti-competitive practices | R89: 7025000 | S89: https://violationtracker.goodjobsfirst.org/violation-tracker/-citibank-na-14 | T89: Duplicated
N90: 44154 | O90: price-fixing or anti-competitive practices | R90: 9950000 | S90: https://violationtracker.goodjobsfirst.org/violation-tracker/-citigroup-inc-15 | T90: Duplicated
A91: 164 | B91: Citigroup Inc (Citi) | C91: INVESTMENT BANKING & BROKERAGE | D91: FN-IB-510b.3 | E91: 0 | F91: Professional Integrity | G91: Total amount of monetary losses as a result of legal proceedings associated with professional integrity, including duty of care | H91: FN | I91: IB | J91: 510 | K91: FN-IB | L91: Refer to 10K, no amount | M91: Yes | N91: 44102 | O91: investor protection violation | R91: 4500000 | S91: https://violationtracker.goodjobsfirst.org/violation-tracker/-citibank-na-11 | T91: Duplicated
A92: 165 | B92: Citizens Financial Group Inc | C92: COMMERCIAL BANKS | D92: FN-CB-510a.1 | E92: 1 | F92: Business Ethics | G92: Total amount of monetary losses as a result of legal proceedings associated with fraud, insider trading, anti-trust, anti-competitive behavior, market manipulation, malpractice, or other related financial industry laws or regulations | H92: FN | I92: CB | J92: 510 | K92: FN-CB | M92: No
A93: 173 | B93: CNX Resources Corp | C93: OIL & GAS - MIDSTREAM | D93: EM-MD-520a.1 | E93: 0 | F93: Competitive Behavior | G93: Total amount of monetary losses as a result of legal proceedings associated with federal pipeline and storage regulations | H93: EM | I93: MD | J93: 520 | K93: EM-MD | M93: No
A94: 188 | B94: ConAgra Foods Inc | C94: PROCESSED FOODS | D94: FB-PF-270a.4 | E94: 1 | F94: Product Labeling & Marketing | G94: Total amount of monetary losses as a result of legal proceedings associated with labeling and/or marketing practices | H94: FB | I94: PF | J94: 270 | K94: FB-PF | M94: No
A95: 190 | B95: Conduent Inc. | C95: SOFTWARE & IT SERVICES | D95: TC-SI-220a.3 | E95: 1 | F95: Data Privacy & Freedom of Expression | G95: Total amount of monetary losses as a result of legal proceedings associated with user privacy | H95: TC | I95: SI | J95: 220 | K95: TC-SI | M95: No
A96: 190 | B96: Conduent Inc. | C96: SOFTWARE & IT SERVICES | D96: TC-SI-520a.1 | E96: 1 | F96: Intellectual Property Protection & Competitive Behavior | G96: Total amount of monetary losses as a result of legal proceedings associated with anti-competitive behavior regulations | H96: TC | I96: SI | J96: 520 | K96: TC-SI | M96: No
A97: 194 | B97: Cooper Cos Inc/The | C97: MEDICAL EQUIPMENT & SUPPLIES | D97: HC-MS-270a.1 | E97: 1 | F97: Ethical Marketing | G97: Total amount of monetary losses as a result of legal proceedings associated with false marketing claims | H97: HC | I97: MS | J97: 270 | K97: HC-MS | M97: No
A98: 194 | B98: Cooper Cos Inc/The | C98: MEDICAL EQUIPMENT & SUPPLIES | D98: HC-MS-510a.1 | E98: 1 | F98: Business Ethics | G98: Total amount of monetary losses as a result of legal proceedings associated with bribery or corruption | H98: HC | I98: MS | J98: 510 | K98: HC-MS | M98: No
A99: 195 | B99: Cooper-Standard Holdings Inc | C99: AUTO PARTS | D99: TR-AP-520a.1 | E99: 1 | F99: Competitive Behavior | G99: Total amount of monetary losses as a result of legal proceedings associated with anti-competitive behavior regulations | H99: TR | I99: AP | J99: 520 | K99: TR-AP | M99: No
A100: 200 | B100: Crestwood Equity Partners LP | C100: OIL & GAS - MIDSTREAM | D100: EM-MD-520a.1 | E100: 1 | F100: Competitive Behavior | G100: Total amount of monetary losses as a result of legal proceedings associated with federal pipeline and storage regulations | H100: EM | I100: MD | J100: 520 | K100: EM-MD | M100: No
A101: 201 | B101: Crestwood Equity Partners LP | C101: OIL & GAS - MIDSTREAM | D101: EM-MD-520a.1 | E101: 1 | F101: Competitive Behavior | G101: Total amount of monetary losses as a result of legal proceedings associated with federal pipeline and storage regulations | H101: EM | I101: MD | J101: 520 | K101: EM-MD | M101: No
A102: 205 | B102: CSX Corp | C102: RAIL TRANSPORTATION | D102: TR-RA-520a.1 | E102: 1 | F102: Competitive Behavior | G102: Total amount of monetary losses as a result of legal proceedings associated with anti-competitive behavior regulations | H102: TR | I102: RA | J102: 520 | K102: TR-RA | M102: No
A103: 207 | B103: Cushman & Wakefield PLC | C103: REAL ESTATE SERVICES | D103: IF-RS-510a.3 | E103: 0 | F103: Transparent Information & Management of Conflict of Interest | G103: Total amount of monetary losses as a result of legal proceedings associated with professional integrity, including duty of care | H103: IF | I103: RS | J103: 510 | K103: IF-RS | M103: No
A104: 208 | B104: CVS Health Corp | C104: DRUG RETAILERS | D104: HC-DR-230a.3 | E104: 0 | F104: Data Security & Privacy | G104: Total amount of monetary losses as a result of legal proceedings associated with data security and privacy | H104: HC | I104: DR | J104: 230 | K104: HC-DR | M104: Yes | N104: 44132 | O104: privacy violation | Q104: Health & Human Services Department Office for Civil Rights | R104: 1000000 | S104: https://violationtracker.goodjobsfirst.org/violation-tracker/-aetna-life-insurance-company-0
A105: 208 | B105: CVS Health Corp | C105: DRUG RETAILERS | D105: HC-DR-260a.2 | E105: 0 | F105: Management of Controlled Substances | G105: Total amount of monetary losses as a result of legal proceedings associated with controlled substances | H105: HC | I105: DR | J105: 260 | K105: HC-DR | M105: Yes | N105: 43964 | O105: Controlled Substances Act violation | Q105: Drug Enforcement Administration | R105: 15300000 | S105: https://violationtracker.goodjobsfirst.org/violation-tracker/-omnicare-inc-15
A106: 208 | B106: CVS Health Corp | C106: DRUG RETAILERS | D106: HC-DR-260b.3 | E106: 0 | F106: Patient Health Outcomes | G106: Total amount of monetary losses as a result of legal proceedings associated with prescription dispensing errors | H106: HC | I106: DR | J106: 260 | K106: HC-DR | M106: No
A107: 208 | B107: CVS Health Corp | C107: HEALTH CARE DELIVERY | D107: HC-DY-510a.1 | E107: 0 | F107: Fraud & Unnecessary Procedures | G107: Total amount of monetary losses as a result of legal proceedings associated with Medicare and Medicaid fraud under the False Claims Act | H107: HC | I107: DY | J107: 510 | K107: HC-DY | M107: No
A108: 208 | B108: CVS Health Corp | C108: HEALTH CARE DELIVERY | D108: HC-DY-230a.4 | E108: 0 | F108: Patient Privacy & Electronic Health Records | G108: Total amount of monetary losses as a result of legal proceedings associated with data security and privacy | H108: HC | I108: DY | J108: 230 | K108: HC-DY | M108: Yes | R108: 1000000 | S108: https://violationtracker.goodjobsfirst.org/violation-tracker/-aetna-life-insurance-company-0 | T108: Duplicated
A109: 208 | B109: CVS Health Corp | C109: MULTILINE AND SPECIALTY RETAILERS & DISTRIBUTORS | D109: CG-MR-310a.3 | E109: 0 | F109: Labor Practices | G109: Total amount of monetary losses as a result of legal proceedings associated with labor law violations | H109: CG | I109: MR | J109: 310 | K109: CG-MR | M109: Yes | R109: 5783 | S109: https://violationtracker.goodjobsfirst.org/violation-tracker/ny-cvs-albany-llc-3
R110: 5783 | S110: https://violationtracker.goodjobsfirst.org/violation-tracker/ri-cvs-health
R111: 14711 | S111: https://violationtracker.goodjobsfirst.org/violation-tracker/ca-garfield-beach-cvs-llc-0
R112: 4500000 | S112: https://violationtracker.goodjobsfirst.org/violation-tracker/-omnicare-inc-et-al
N113: 44078 | O113: wage and hour violation | Q113: Massachusetts Attorney General | R113: 42869 | S113: https://violationtracker.goodjobsfirst.org/violation-tracker/ma-cvs-pharmacy-inc-2
A114: 208 | B114: CVS Health Corp | C114: MULTILINE AND SPECIALTY RETAILERS & DISTRIBUTORS | D114: CG-MR-330a.2 | E114: 0 | F114: Workforce Diversity & Inclusion | G114: Total amount of monetary losses as a result of legal proceedings associated with employment discrimination | H114: CG | I114: MR | J114: 330 | K114: CG-MR | M114: No
...

Sheet Violation Tracker
A1: Note | B1: Line in Master | C1: Company | D1: Report Period | E1: Violation Tracker | F1: Date | G1: Primary Offense Type | H1: Violation Description | I1: Agency | J1: Amount | K1: Link
B2: 11 | C2: Aflac Inc | D2: 2019 calendar year | E2: No
B3: 12 | C3: Agilent Technologies Inc | D3: 11/1/2019 - 10/31/2020 | E3: No
B4: 14 | C4: AGNC Investment Corp | D4: 2020 | E4: No
B5: 15 | C5: AIG - American International Group Inc | D5: 2020 calendar year | E5: No
B6: 17 | C6: Akamai Technologies Inc | D6: 2020 calendar year | E6: No
B7: 27 | C7: Alliance Data Systems Corp | D7: 2020 calendar year | E7: No
B8: 28 | C8: Alliance Data Systems Corp | D8: 2019 calendar year | E8: No
B9: 36 | C9: American Airlines Group Inc | D9: 2019 calendar year | E9: Yes | F9: 43598 | G9: price-fixing or anti-competitive practices | I9: private lawsuit-federal | J9: 45000000 | K9: https://violationtracker.goodjobsfirst.org/violation-tracker/-american-airlines-20
B10: 39 | C10: American Express Co | D10: 2019 calendar year | E10: No
B11: 42 | C11: American Tower Corp | D11: 2019 calendar year | E11: Yes | F11: 43776 | G11: air pollution violation | I11: South Coast (CA) Air Quality Management District | J11: 5000 | K11: https://violationtracker.goodjobsfirst.org/violation-tracker/ca-american-tower-corporation
B12: 48 | C12: Amphenol Corp | D12: 2020 calendar year | E12: No
B13: 49 | C13: Amphenol Corp | D13: 2019 calendar year | E13: No
B14: 50 | C14: Amphenol Corp | D14: 2018 calendar year | E14: No
B15: 52 | C15: Annaly Capital Management Inc | D15: 2020 calendar year | E15: No
B16: 53 | C16: Annaly Capital Management Inc | D16: 2019 calendar year | E16: No
B17: 70 | C17: Arcosa, Inc | D17: 2020 | E17: Yes | F17: 43924 | G17: air pollution violation | I17: Colorado Department of Public Health & Environment | J17: 35175 | K17: https://violationtracker.goodjobsfirst.org/violation-tracker/co-arcosa-lwb-llc
F18: 44145 | G18: environmental violation | I18: Texas Commission on Environmental Quality | J18: 31628 | K18: https://violationtracker.goodjobsfirst.org/violation-tracker/tx-arcosa-lws-llc-0
B19: 71 | C19: Arena Pharmaceuticals Inc | D19: 2020 | E19: No
B20: 78 | C20: Atkore International | D20: 10/1/2018-9/1/2020 | E20: No
B21: 90 | C21: Baxter International Inc | D21: 2019 calendar year | E21: No
B22: 91 | C22: Becton Dickinson and Co | D22: 10/1/2019-9/30/2020 | E22: Yes | F22: 44103 | G22: employment discrimination | I22: Office of Federal Contract Compliance Programs | J22: 89678 | K22: https://violationtracker.goodjobsfirst.org/violation-tracker/md-becton-dickinson-and-co
B23: 98 | C23: Blackbaud, Inc. | D23: 2020 calendar year | E23: No
B24: 120 | C24: Burlington Stores Inc | D24: 1/30/202020-1/30/2021 | E24: Yes | F24: 44042 | G24: workplace safety or health violation | I24: Occupational Safety & Health Administration | J24: 6000 | K24: https://violationtracker.goodjobsfirst.org/violation-tracker/wa-burlington-coat-factory-warehouse-of-aub
F25: 44180 | G25: wage and hour violation | J25: 19613900 | K25: https://violationtracker.goodjobsfirst.org/violation-tracker/-burlington-coat-factory-warehouse-corpor-1
B26: 124 | C26: Calavo Growers Inc | D26: 2020 calendar year | E26: Yes | F26: 44064 | G26: workplace safety or health violation | I26: Occupational Safety & Health Administration | J26: 5885 | K26: https://violationtracker.goodjobsfirst.org/violation-tracker/ca-calavo-growers-inc-1
F27: 44153 | G27: workplace safety or health violation | I27: Occupational Safety & Health Administration | J27: 12875 | K27: https://violationtracker.goodjobsfirst.org/violation-tracker/nj-calavo-growers-inc
B28: 130 | C28: Cardinal Health Inc | D28: 7/1/2019-6/30/2020 | E28: Yes | F28: 43697 | G28: wage and hour violation | J28: 7500000 | K28: https://violationtracker.goodjobsfirst.org/violation-tracker/-cardinal-health-3
F29: 43889 | G29: Foreign Corrupt Practices Act | I29: Securities and Exchange Commission | J29: 8000000 | K29: https://violationtracker.goodjobsfirst.org/violation-tracker/-cardinal-health-inc-4
B30: 131 | C30: Carrier Global Corp | D30: 2019 calendar year | E30: Yes | F30: 43538 | G30: environmental violation | I30: Environmental Protection Agency | J30: 593750 | K30: https://violationtracker.goodjobsfirst.org/violation-tracker/-carrier-corporation
F31: 43663 | G31: labor relations violation | I31: National Labor Relations Board | J31: 16243 | K31: https://violationtracker.goodjobsfirst.org/violation-tracker/tn-carrier-corporation
F32: 43684 | G32: workplace safety or health violation | I32: Occupational Safety & Health Administration | J32: 12730 | K32: https://violationtracker.goodjobsfirst.org/violation-tracker/fl-carrier-enterprise
B33: 132 | C33: Catalent Inc | D33: 7/1/2020-6/30/2021 | E33: No
B34: 133 | C34: Catalent Inc | D34: 7/1/2018-6/30/2019 | E34: No
B35: 142 | C35: Century Communities Inc | D35: 2020 calendar year | E35: No
B36: 146 | C36: CH Robinson Worldwide Inc | D36: 2020 calendar year | E36: No
B37: 147 | C37: Charah Solutions Inc | D37: 2020 | E37: No
B38: 154 | C38: Cheniere Energy Partners LP | D38: 2020 calendar year | E38: No
B39: 157 | C39: Chipotle Mexican Grill Inc | D39: 2020 calendar year | E39: Yes | F39: 43857 | G39: wage and hour violation | I39: Massachusetts Attorney General | J39: 50000 | K39: https://violationtracker.goodjobsfirst.org/violation-tracker/ma-chipotle-mexican-grill-inc-1
F40: 43857 | G40: wage and hour violation | I40: Massachusetts Attorney General | J40: 20000 | K40: https://violationtracker.goodjobsfirst.org/violation-tracker/ma-chipotle-mexican-grill-inc-0
F41: 43857 | G41: wage and hour violation | I41: Massachusetts Attorney General | J41: 1870000 | K41: https://violationtracker.goodjobsfirst.org/violation-tracker/ma-chipotle-mexican-grill-inc
F42: 43942 | G42: food safety violation | I42: Justice Department Civil Division | J42: 25000000 | K42: https://violationtracker.goodjobsfirst.org/violation-tracker/-chipotle-mexican-grill-inc
F43: 44013 | G43: employment discrimination | J43: 46220 | K43: https://violationtracker.goodjobsfirst.org/violation-tracker/ny-chipotle-mexican-grill-inc-0
F44: 44019 | G44: wage and hour violation | I44: New York Department of Labor | J44: 6645 | K44: https://violationtracker.goodjobsfirst.org/violation-tracker/ny-chipotle-mexican-grill-2602
F45: 44105 | G45: labor relations violation | I45: National Labor Relations Board | J45: 5737 | K45: https://violationtracker.goodjobsfirst.org/violation-tracker/ny-chipotle-grill
F46: 44123 | G46: labor relations violation | I46: National Labor Relations Board | J46: 54136 | K46: https://violationtracker.goodjobsfirst.org/violation-tracker/az-chipotle-mexican-grill-inc-0
F47: 44139 | G47: consumer protection violation | J47: 6500000 | K47: https://violationtracker.goodjobsfirst.org/violation-tracker/-chipotle-mexican-grill-inc-1
F48: 44195 | G48: wage and hour violation | I48: Labor Department Wage and Hour Division | J48: 27150 | K48: https://violationtracker.goodjobsfirst.org/violation-tracker/ca-chipotle-mexican-grill-0
B49: 164 | C49: Citigroup Inc (Citi) | D49: 2020 calendar year | E49: Yes | F49: 43847 | G49: banking violation | J49: 17998510 | K49: https://violationtracker.goodjobsfirst.org/violation-tracker/-citibank-na-10
F50: 44000 | G50: price-fixing or anti-competitive practices | J50: 20833333 | K50: https://violationtracker.goodjobsfirst.org/violation-tracker/-citigroup-global-markets-inc-34
F51: 44091 | G51: price-fixing or anti-competitive practices | J51: 33400000 | K51: https://violationtracker.goodjobsfirst.org/violation-tracker/-citibank-na-15
F52: 44102 | G52: investor protection violation | J52: 4500000 | K52: https://violationtracker.goodjobsfirst.org/violation-tracker/-citibank-na-11
F53: 44109 | G53: price-fixing or anti-competitive practices | J53: 7025000 | K53: https://violationtracker.goodjobsfirst.org/violation-tracker/-citibank-na-14
F54: 44111 | G54: banking violation | J54: 400000000 | K54: https://violationtracker.goodjobsfirst.org/violation-tracker/-citibank-national-association
F55: 44154 | G55: price-fixing or anti-competitive practices | J55: 9950000 | K55: https://violationtracker.goodjobsfirst.org/violation-tracker/-citigroup-inc-15
B56: 165 | C56: Citizens Financial Group Inc | D56: 2020 calendar year | E56: No
B57: 173 | C57: CNX Resources Corp | D57: 2020 calendar year | E57: Yes | F57: 43928 | G57: environmental violation | I57: Pennsylvania Department of Environmental Protection | J57: 180000 | K57: https://violationtracker.goodjobsfirst.org/violation-tracker/pa-cnx-gas-company-llc-0
F58: 43941 | G58: environmental violation | I58: Pennsylvania Department of Environmental Protection | J58: 12050 | K58: https://violationtracker.goodjobsfirst.org/violation-tracker/pa-cnx-gas-co-llc-4
F59: 44036 | G59: environmental violation | I59: Pennsylvania Department of Environmental Protection | J59: 310000 | K59: https://violationtracker.goodjobsfirst.org/violation-tracker/pa-cnx-gas-company-llc-and-cnx-midstream-pa
F60: 44063 | G60: oil or gas drilling violation | I60: Pennsylvania Department of Environmental Protection | J60: 175000 | K60: https://violationtracker.goodjobsfirst.org/violation-tracker/pa-cnx-gas-company-llc
B61: 188 | C61: ConAgra Foods Inc | D61: 2020 Fiscal year (5/25/2019 - 5/25/2020) | E61: No
B62: 190 | C62: Conduent Inc. | D62: 2020 calendar year | E62: Yes | F62: 44124 | G62: employment discrimination | I62: Equal Employment Opportunity Commission | J62: 77500 | K62: https://violationtracker.goodjobsfirst.org/violation-tracker/nj-conduent-business-services-llc-0
B63: 194 | C63: Cooper Cos Inc/The | D63: 10/1/2019-5/1/2020 | E63: No
B64: 195 | C64: Cooper-Standard Holdings Inc | D64: 2020 calendar year | E64: No
B65: 200 | C65: Crestwood Equity Partners LP | D65: 2020 calendar year | E65: No
B66: 201 | C66: Crestwood Equity Partners LP | D66: 2019 calendar year | E66: No
B67: 205 | C67: CSX Corp | D67: 2019 calendar year | E67: No
B68: 207 | C68: Cushman & Wakefield PLC | D68: 2020 calendar year | E68: No
B69: 208 | C69: CVS Health Corp | D69: 2020 calendar year | E69: Yes | F69: 43853 | G69: insurance violation | I69: Missouri Department of Insurance | J69: 51000 | K69: https://violationtracker.goodjobsfirst.org/violation-tracker/mo-coventry-health-and-life-insurance-co
F70: 43870 | G70: environmental violation | I70: Environmental Protection Agency | J70: 60000 | K70: https://violationtracker.goodjobsfirst.org/violation-tracker/-puerto-rico-cvs-pharmacy-llc
F71: 43880 | G71: workplace safety or health violation | I71: Occupational Safety & Health Administration | J71: 5783 | K71: https://violationtracker.goodjobsfirst.org/violation-tracker/ny-cvs-albany-llc-3
F72: 43881 | G72: workplace safety or health violation | I72: Occupational Safety & Health Administration | J72: 5783 | K72: https://violationtracker.goodjobsfirst.org/violation-tracker/ri-cvs-health
F73: 43882 | G73: insurance violation | I73: California Department of Managed Health Care | J73: 60000 | K73: https://violationtracker.goodjobsfirst.org/violation-tracker/ca-aetna-health-of-california-inc-64
F74: 43889 | G74: wage and hour violation | I74: California Labor Commissioner's Office | J74: 14711 | K74: https://violationtracker.goodjobsfirst.org/violation-tracker/ca-garfield-beach-cvs-llc-0
F75: 43908 | G75: insurance violation | I75: Virginia Bureau of Insurance | J75: 57805 | K75: https://violationtracker.goodjobsfirst.org/violation-tracker/va-aetna-life-insurance-company-1
F76: 43925 | G76: insurance violation | I76: California Department of Managed Health Care | J76: 35000 | K76: https://violationtracker.goodjobsfirst.org/violation-tracker/ca-aetna-health-of-california-inc-69
F77: 43927 | G77: insurance violation | I77: Delaware Department of Insurance | J77: 67000 | K77: https://violationtracker.goodjobsfirst.org/violation-tracker/de-aetna-life-insurance-company
F78: 43937 | G78: insurance violation | I78: California Department of Managed Health Care | J78: 47500 | K78: https://violationtracker.goodjobsfirst.org/violation-tracker/ca-aetna-health-of-california-inc-68
F79: 43964 | G79: Controlled Substances Act violation | I79: Drug Enforcement Administration | J79: 15300000 | K79: https://violationtracker.goodjobsfirst.org/violation-tracker/-omnicare-inc-15
F80: 43994 | G80: insurance violation | I80: Washington State Office of the Insurance Commissioner | J80: 20000 | K80: https://violationtracker.goodjobsfirst.org/violation-tracker/wa-aetna-life-insurance-company-3
F81: 44004 | G81: insurance violation | I81: South Dakota Division of Insurance | J81: 5000 | K81: https://violationtracker.goodjobsfirst.org/violation-tracker/sd-aetna-network-services-llc
... F84: 44040 | G84: insurance violation | I84: Minnesota Department of Commerce | J84: 10000 | K84: https://violationtracker.goodjobsfirst.org/violation-tracker/mn-coventry-health-care-workers-compensatio
F85: 44061 | G85: wage and hour violation | J85: 4500000 | K85: https://violationtracker.goodjobsfirst.org/violation-tracker/-omnicare-inc-et-al
F86: 44068 | G86: insurance violation | I86: California Department of Managed Health Care | J86: 500000 | K86: https://violationtracker.goodjobsfirst.org/violation-tracker/ca-aetna-health-of-california-inc-66
F87: 44078 | G87: wage and hour violation | I87: Massachusetts Attorney General | J87: 42869 | K87: https://violationtracker.goodjobsfirst.org/violation-tracker/ma-cvs-pharmacy-inc-2
F88: 44113 | G88: insurance violation | I88: California Department of Managed Health Care | J88: 37500 | K88: https://violationtracker.goodjobsfirst.org/violation-tracker/ca-aetna-health-of-california-inc-65
F89: 44132 | G89: privacy violation | I89: Health & Human Services Department Office for Civil Rights | J89: 1000000 | K89: https://violationtracker.goodjobsfirst.org/violation-tracker/-aetna-life-insurance-company-0
F90: 44133 | G90: insurance violation | I90: Delaware Department of Insurance | J90: 298000 | K90: https://violationtracker.goodjobsfirst.org/violation-tracker/de-aetna-health-inc-pa
F91: 44134 | G91: insurance violation | I91: Washington State Office of the Insurance Commissioner | J91: 30000 | K91: https://violationtracker.goodjobsfirst.org/violation-tracker/wa-aetna-life-insurance-company-4
B92: 209 | C92: CyrusOne Inc | D92: 2019 calendar year | E92: No
B93: 213 | C93: Danaher Corp | D93: 2019 calendar year | E93: Yes | F93: 43762 | G93: workplace safety or health violation | I93: Occupational Safety & Health Administration | J93: 10000 | K93: https://violationtracker.goodjobsfirst.org/violation-tracker/ia-integrated-dna-technologies-inc
B94: 243 | C94: Eagle Bulk Shipping Inc | D94: 2020 calendar year | E94: No
B95: 244 | C95: Eagle Bulk Shipping Inc | D95: 2019 calendar year | E95: No
B96: 255 | C96: eHealth Inc | D96: 2020 calendar year | E96: Yes | F96: 44026 | G96: insurance violation | I96: Iowa Insurance Division | J96: 5000 | K96: https://violationtracker.goodjobsfirst.org/violation-tracker/ia-ehealthinsurance-services-inc
B97: 268 | C97: Envista Holdings Corp | D97: 2020 calendar year | E97: No
B98: 274 | C98: Equitrans Midstream Corp | D98: 2020 calendar year | E98: No
B99: 295 | C99: FedEx Corp | D99: 5/31/2018-5/31/2019 | E99: No
B100: 297 | C100: Fifth Third Bancorp | D100: 2020 calendar year | E100: No
B101: 298 | C101: Fifth Third Bancorp | D101: 2019 calendar year | E101: No
B102: 310 | C102: Foot Locker Inc | D102: 2/3/2019-1/30/2021 | E102: Yes | F102: 43808 | G102: wage and hour violation | I102: Labor Department Wage and Hour Division | J102: 7368 | K102: https://violationtracker.goodjobsfirst.org/violation-tracker/ca-foot-locker-retail-inc
...

Sheet Industry Descriptive
A1: ind_code | B1: Industry | C1: # of Metrics | D1: # of Reports | E1: Report_rate | F1: Qualitative | G1: Quantitative
A2: CG-AA | B2: APPAREL, ACCESSORIES & FOOTWEAR | C2: 11 | D2: 12 | E2: 0.62916667 | F2: 0.65 | G2: 0.517
A3: CG-AM | B3: APPLIANCE MANUFACTURING | C3: 6 | D3: 1 | E3: 1 | F3: 1 | G3: 1
A4: CG-BF | B4: BUILDING PRODUCTS & FURNISHINGS | C4: 6 | D4: 1 | E4: 0.75 | F4: 1 | G4: 0.75
A5: CG-EC | B5: E-COMMERCE | C5: 13 | D5: 2 | E5: 0.16666667 | F5: 0.125 | G5: 0.167
A6: CG-HP | B6: HOUSEHOLD & PERSONAL PRODUCTS | C6: 9 | D6: 6 | E6: 0.38888889 | F6: 0.667 | G6: 0.389
A7: CG-MR | B7: MULTILINE AND SPECIALTY RETAILERS & DISTRIBUTORS | C7: 11 | D7: 10 | E7: 0.58541667 | F7: 0.9 | G7: 0.481
A8: CG-TS | B8: TOYS & SPORTING GOODS | C8: 6 | D8: 1 | E8: 0.4 | F8: 0 | G8: 0.4
A9: EM-CM | B9: CONSTRUCTION MATERIALS | C9: 13 | D9: 2 | E9: 0.72727273 | F9: 0.75 | G9: 0.727
A10: EM-EP | B10: OIL & GAS - EXPLORATION & PRODUCTION | C10: 27 | D10: 22 | E10: 0.57108586 | F10: 0.686 | G10: 0.571
A11: EM-IS | B11: IRON & STEEL PRODUCERS | C11: 9 | D11: 2 | E11: 0.78571429 | F11: 0.75 | G11: 0.786
A12: EM-MD | B12: OIL & GAS - MIDSTREAM | C12: 12 | D12: 15 | E12: 0.64444444 | F12: 0.844 | G12: 0.644
A13: EM-MM | B13: METALS & MINING | C13: 32 | D13: 7 | E13: 0.56152279 | F13: 0.503 | G13: 0.562
... A73: TR-RO | B73: ROAD TRANSPORTATION | C73: 10 | D73: 3 | E73: 0.75 | F73: 0.5 | G73: 0.75
C74: =SUM(C2:C73) -> 937 | D74: =SUM(D2:D73) -> 392 | E74: =AVERAGE(E2:E73) -> 0.63154162 | F74: =AVERAGE(F2:F73) -> 0.74643056 | G74: =AVERAGE(G2:G73) -> 0.60861111

Sheet Truncated Metrics
A1: Truncated Metrics | B1: Total Count | C1: % | D1: Reported Count | E1: Report Rate | F1: Weighted Report Rate (for ranking) | G1: Mean Quantitative
A2: Total amount of monetary losses as a result of legal proceedings associated with | B2: 351 | C2: =B2/$B$602 -> 0.063981043 | D2: 209 | E2: 0.595 | F2: =E2*C2 -> 0.03806872 | G2: 1 | I2: Higher than mean
A3: (1) Total energy consumed, (2) percentage grid electricity, (3) percentage renew | B3: 143 | C3: =B3/$B$602 -> 0.026066351 | D3: 127 | E3: 0.888 | F3: =E3*C3 -> 0.023146919 | G3: 1
A4: Discussion of long-term and short-term strategy or plan to manage Scope 1 emissi | B4: 117 | C4: =B4/$B$602 -> 0.021327014 | D4: 99 | E4: 0.846 | F4: =E4*C4 -> 0.018042654 | G4: 0.154
A5: (1) Total water withdrawn, (2) total water consumed, percentage of each in regio | B5: 102 | C5: =B5/$B$602 -> 0.018592782 | D5: 82 | E5: 0.804 | F5: =E5*C5 -> 0.014948596 | G5: 1
A6: Description of water management risks and discussion of strategies and practices | B6: 89 | C6: =B6/$B$602 -> 0.016223113 | D6: 78 | E6: 0.876 | F6: =E6*C6 -> 0.014211447 | G6: 0.056
A7: Description of the management of risks associated with the use of critical mater | B7: 63 | C7: =B7/$B$602 -> 0.011483777 | D7: 50 | E7: 0.794 | F7: =E7*C7 -> 0.0091181188 | G7: 0.19
A8: Air emissions of the following pollutants: (1) NOx (excluding N2O), (2) SOx, (3) | B8: 65 | C8: =B8/$B$602 -> 0.011848341 | D8: 45 | E8: 0.692 | F8: =E8*C8 -> 0.0081990521 | G8: 1
A9: (1) Total recordable incident rate (TRIR), (2) fatality rate, and (3) near miss | B9: 44 | C9: =B9/$B$602 -> 0.0080204156 | D9: 40 | E9: 0.909 | F9: =E9*C9 -> 0.0072905578 | G9: 1
A10: Description of approach to identifying and addressing data security risks | B10: 42 | C10: =B10/$B$602 -> 0.0076558513 | D10: 37 | E10: 0.881 | F10: =E10*C10 -> 0.006744805 | G10: 0
A11: Gross global Scope 1 emissions, percentage methane, percentage covered under emi | B11: 37 | C11: =B11/$B$602 -> 0.0067444404 | D11: 34 | E11: 0.919 | F11: =E11*C11 -> 0.0061981407 | G11: 1
A12: Amount of hazardous waste generated, percentage recycled | B12: 40 | C12: =B12/$B$602 -> 0.0072912869 | D12: 33 | E12: 0.825 | F12: =E12*C12 -> 0.0060153117 | G12: 1
A13: Gross global Scope 1 emissions, percentage covered under emissions-limiting regu | B13: 38 | C13: =B13/$B$602 -> 0.0069267226 | D13: 33 | E13: 0.868 | F13: =E13*C13 -> 0.0060123952 | G13: 1
A14: Discussion of corporate positions related to government regulations and/or polic | B14: 46 | C14: =B14/$B$602 -> 0.0083849799 | D14: 33 | E14: 0.717 | F14: =E14*C14 -> 0.0060120306 | G14: 0
... A280: Total weight of tailings produced | B280: 3 | C280: =B280/$B$602 -> 0.00054684652 | D280: 3 | E280: 1 | F280: =E280*C280 -> 0.00054684652 | G280: 1
A281: Total weight of tailings waste, percentage recycled | B281: 3 | C281: =B281/$B$602 -> 0.00054684652 | D281: 3 | E281: 1 | F281: =E281*C281 -> 0.00054684652
A282: Tier 1 suppliersâ€™ (1) non-conformance rate with the RBA Validated Audit Process | B282: 4 | C282: =B282/$B$602 -> 0.00072912869 | D282: 3 | E282: 0.75 | F282: =E282*C282 -> 0.00054684652 | G282: 1
A283: Amount of waste generated, percentage hazardous, percentage recycled | B283: 4 | C283: =B283/$B$602 -> 0.00072912869 | D283: 3 | E283: 0.75 | F283: =E283*C283 -> 0.00054684652 | G283: 1
A284: Description of policies and programs to prevent worker harassment | B284: 4 | C284: =B284/$B$602 -> 0.00072912869 | D284: 3 | E284: 0.75 | F284: =E284*C284 -> 0.00054684652 | G284: 0
A285: Percentage of revenue from (1) eggs that originated from a cage-free environment | B285: 4 | C285: =B285/$B$602 -> 0.00072912869 | D285: 3 | E285: 0.75 | F285: =E285*C285 -> 0.00054684652 | G285: 1
A286: Discussion of management systems used to integrate a culture of safety | B286: 4 | C286: =B286/$B$602 -> 0.00072912869 | D286: 3 | E286: 0.75 | F286: =E286*C286 -> 0.00054684652 | G286: 0
A287: Percentage of Tier 1 supplier facilities audited in the RBA Validated Audit Proc | B287: 4 | C287: =B287/$B$602 -> 0.00072912869 | D287: 3 | E287: 0.75 | F287: =E287*C287 -> 0.00054684652 | G287: 1
A288: Percentage of variable remuneration of Material Risk Takers (MRTs) to which malu | B288: 5 | C288: =B288/$B$602 -> 0.00091141086 | D288: 3 | E288: 0.6 | F288: =E288*C288 -> 0.00054684652 | G288: 1
A289: Percentage of total remuneration that is variable for Material Risk Takers (MRTs | B289: 5 | C289: =B289/$B$602 -> 0.00091141086 | D289: 3 | E289: 0.6 | F289: =E289*C289 -> 0.00054684652 | G289: 1
A290: Average refrigerant emissions rate | B290: 5 | C290: =B290/$B$602 -> 0.00091141086 | D290: 3 | E290: 0.6 | F290: =E290*C290 -> 0.00054684652 | G290: 1
A291: Description of how proximity and access to infrastructure, services, and economi | B291: 5 | C291: =B291/$B$602 -> 0.00091141086 | D291: 3 | E291: 0.6 | F291: =E291*C291 -> 0.00054684652 | G291: 0
A292: (1) Number and (2) total value of investments and loans incorporating integratio | B292: 5 | C292: =B292/$B$602 -> 0.00091141086 | D292: 3 | E292: 0.6 | F292: =E292*C292 -> 0.00054684652 | G292: 1
A293: Discussion of policies around supervision, control, and validation of tradersâ€™ p | B293: 5 | C293: =B293/$B$602 -> 0.00091141086 | D293: 3 | E293: 0.6 | F293: =E293*C293 -> 0.00054684652 | G293: 0
... A340: (1) Number, (2) value, and (3) weighted average Loan-to-Value (LTV) ratio of mor | B340: 2 | C340: =B340/$B$602 -> 0.00036456435 | D340: 2 | E340: 1 | F340: =E340*C340 -> 0.00036456435 | G340: 1
A341: Number of tailings impoundments, broken down by MSHA hazard potential | B341: 2 | C341: =B341/$B$602 -> 0.00036456435 | D341: 2 | E341: 1 | F341: =E341*C341 -> 0.00036456435
A342: Payload fuel economy | B342: 2 | C342: =B342/$B$602 -> 0.00036456435 | D342: 2 | E342: 1 | F342: =E342*C342 -> 0.00036456435 | G342: 1
A343: Number of incidents of non-compliance with environmental permits, standards, and | B343: 2 | C343: =B343/$B$602 -> 0.00036456435 | D343: 2 | E343: 1 | F343: =E343*C343 -> 0.00036456435 | G343: 1
A344: (1) Total energy consumed, (2) percentage grid electricity, (3) percentage from | B344: 2 | C344: =B344/$B$602 -> 0.00036456435 | D344: 2 | E344: 1 | F344: =E344*C344 -> 0.00036456435 | G344: 1
A345: Number of Federal Railroad Administration (FRA) Recommended Violation Defects | B345: 2 | C345: =B345/$B$602 -> 0.00036456435 | D345: 2 | E345: 1 | F345: =E345*C345 -> 0.00036456435 | G345: 1
A346: (1) Total energy consumed, (2) percentage grid electricity, (3) percentage alter | B346: 2 | C346: =B346/$B$602 -> 0.00036456435 | D346: 2 | E346: 1 | F346: =E346*C346 -> 0.00036456435 | G346: 1
A347: Discussion of strategy to manage environmental and social risks arising from con | B347: 2 | C347: =B347/$B$602 -> 0.00036456435 | D347: 2 | E347: 1 | F347: =E347*C347 -> 0.00036456435 | G347: 0
A348: Frequency of internal railway integrity inspections | B348: 2 | C348: =B348/$B$602 -> 0.00036456435 | D348: 2 | E348: 1 | F348: =E348*C348 -> 0.00036456435 | G348: 1
A349: Amount of recycled and recovered fiber procured | B349: 2 | C349: =B349/$B$602 -> 0.00036456435 | D349: 2 | E349: 1 | F349: =E349*C349 -> 0.00036456435 | G349: 1
A350: Amount of defect- and safety-related rework costs | B350: 2 | C350: =B350/$B$602 -> 0.00036456435 | D350: 2 | E350: 1 | F350: =E350*C350 -> 0.00036456435 | G350: 1
A351: Discussion of processes to assess and manage environmental risks associated with | B351: 2 | C351: =B351/$B$602 -> 0.00036456435 | D351: 2 | E351: 1 | F351: =E351*C351 -> 0.00036456435 | G351: 0
A352: Discussion of processes to manage business ethics risks throughout the value cha | B352: 2 | C352: =B352/$B$602 -> 0.00036456435 | D352: 2 | E352: 1 | F352: =E352*C352 -> 0.00036456435 | G352: 0
A353: Area of forestland in indigenous land | B353: 2 | C353: =B353/$B$602 -> 0.00036456435 | D353: 2 | E353: 1 | F353: =E353*C353 -> 0.00036456435 | G353: 1
... A374: Description of approach to ensuring intellectual property (IP) protection | B374: 2 | C374: =B374/$B$602 -> 0.00036456435 | D374: 2 | E374: 1 | F374: =E374*C374 -> 0.00036456435 | G374: 0
A375: Total weight of mineral processing waste, percentage recycled | B375: 2 | C375: =B375/$B$602 -> 0.00036456435 | D375: 2 | E375: 1 | F375: =E375*C375 -> 0.00036456435
A376: (1) Number of data breaches, (2) percentage involving customers' confidential bu | B376: 4 | C376: =B376/$B$602 -> 0.00072912869 | D376: 2 | E376: 0.5 | F376: =E376*C376 -> 0.00036456435 | G376: 1
A377: (1) Voluntary and (2) involuntary turnover rate for lodging facility employees | B377: 4 | C377: =B377/$B$602 -> 0.00072912869 | D377: 2 | E377: 0.5 | F377: =E377*C377 -> 0.00036456435 | G377: 1
A378: Net exposure to written credit derivatives | B378: 4 | C378: =B378/$B$602 -> 0.00072912869 | D378: 2 | E378: 0.5 | F378: =E378*C378 -> 0.00036456435 | G378: 1
A379: Total addressable market and share of market for advanced biofuels and associate | B379: 4 | C379: =B379/$B$602 -> 0.00072912869 | D379: 2 | E379: 0.5 | F379: =E379*C379 -> 0.00036456435 | G379: 1
A380: Number of lodging facilities located in or near areas of protected conservation | B380: 4 | C380: =B380/$B$602 -> 0.00072912869 | D380: 2 | E380: 0.5 | F380: =E380*C380 -> 0.00036456435 | G380: 1
A381: Wastewater treatment capacity located in 100-year flood zones | B381: 4 | C381: =B381/$B$602 -> 0.00072912869 | D381: 2 | E381: 0.5 | F381: =E381*C381 -> 0.00036456435 | G381: 1
A382: Revenue from products that contain substances on the California DTSC Candidate C | B382: 6 | C382: =B382/$B$602 -> 0.001093693 | D382: 1 | E382: 0.167 | F382: =E382*C382 -> 0.00018264674 | G382: 1
A383: Weight of end-of-life material recovered, percentage recycled | B383: 6 | C383: =B383/$B$602 -> 0.001093693 | D383: 1 | E383: 0.167 | F383: =E383*C383 -> 0.00018264674 | G383: 1
A384: Revenue from products that contain REACH substances of very high concern (SVHC) | B384: 6 | C384: =B384/$B$602 -> 0.001093693 | D384: 1 | E384: 0.167 | F384: =E384*C384 -> 0.00018264674 | G384: 1
A385: Percentage change in: (1) list price and (2) net price of product with largest i | B385: 7 | C385: =B385/$B$602 -> 0.0012759752 | D385: 1 | E385: 0.143 | F385: =E385*C385 -> 0.00018246445 | G385: 1
A386: Ratio of weighted average rate of net price increases (for all products) to the | B386: 11 | C386: =B386/$B$602 -> 0.0020051039 | D386: 1 | E386: 0.091 | F386: =E386*C386 -> 0.00018246445 | G386: 0
A387: (1) Number of data breaches, (2) percentage involving (a) personally identifiabl | B387: 5 | C387: =B387/$B$602 -> 0.00091141086 | D387: 1 | E387: 0.2 | F387: =E387*C387 -> 0.00018228217 | G387: 1
... A597: (1) Amount of priority raw materials purchased, by material, and (2) amount of e | B597: 7 | C597: =B597/$B$602 -> 0.0012759752 | D597: 0 | E597: 0 | F597: =E597*C597 -> 0 | G597: 1
A598: Average disturbed acreage per (1) oil and (2) gas well site | B598: 0 | C598: =B598/$B$602 -> 0 | D598: 0 | G598: 1 | H598: Not Applicable
A599: Net exposure to written credit derivatives | B599: 0 | C599: =B599/$B$602 -> 0 | D599: 0 | G599: 1 | H599: Not Applicable
A600: Percentage of engines in service that meet Tier 4 compliance for non-road diesel | B600: 0 | C600: =B600/$B$602 -> 0 | D600: 0 | G600: 1 | H600: Not Applicable
A601: Total exposure to securities financing transactions | B601: 0 | C601: =B601/$B$602 -> 0 | D601: 0 | G601: 1 | H601: Not Applicable
A602: Total | B602: =SUM(B2:B601) -> 5486 | C602: =B602/$B$602 -> 1
A603: Mean | E603: =AVERAGE(E2:E597) -> 0.60179866
A604: Median | E604: =MEDIAN(E2:E597) -> 0.636

Sheet Sheet1
A1: Truncated Metrics | B1: Total Count | C1: % | D1: Reported Count | E1: Report Rate | F1: Weighted Report Rate (for ranking) | G1: Mean Quantitative | I1: industries
A2: Percentage of animal production that received (1) medically important antibiotic | B2: 2 | C2: 0.00036456435 | D2: 0 | E2: 0 | F2: 0 | G2: 1
A3: Percentage of controlled substance prescriptions dispensed for which a prescript | B3: 2 | C3: 0.00036456435 | D3: 0 | E3: 0 | F3: 0 | G3: 1
A4: Percentage of animal feed sourced from regions with High or Extremely High Basel | B4: 2 | C4: 0.00036456435 | D4: 0 | E4: 0 | F4: 0 | G4: 1
A5: (1) Gross revenue and (2) revenue net of excise taxes from (a) non-tobacco nicot | B5: 3 | C5: 0.00054684652 | D5: 0 | E5: 0 | F5: 0 | G5: 1
A6: (1) Fatality rate and (2) injury rate for customers | B6: 2 | C6: 0.00036456435 | D6: 0 | E6: 0 | F6: 0 | G6: 1
A7: Total weight of non-mineral waste generated | B7: 4 | C7: 0.00072912869 | D7: 0 | E7: 0 | F7: 0 | G7: 1
A8: (1) List of priority raw materials; for each priority raw material: (2) environm | B8: 7 | C8: 0.0012759752 | D8: 0 | E8: 0 | F8: 0 | G8: 0
A9: Percentage of cage-free shell egg sales | B9: 1 | C9: 0.00018228217 | D9: 0 | E9: 0 | F9: 0 | G9: 1
A10: Percentage of carriers with BASIC percentiles above the FMCSA intervention thres | B10: 3 | C10: 0.00054684652 | D10: 0 | E10: 0 | F10: 0 | G10: 1
A11: Percentage of claims denied that were appealed by customers and ultimately rever | B11: 1 | C11: 0.00018228217 | D11: 0 | E11: 0 | F11: 0 | G11: 1
A12: Number of the entityâ€™s 25 most common services for which pricing information is | B12: 2 | C12: 0.00036456435 | D12: 0 | E12: 0 | F12: 0 | G12: 1
A13: Number of significant incidents associated with hazardous materials and waste ma | B13: 4 | C13: 0.00072912869 | D13: 0 | E13: 0 | F13: 0 | G13: 1
... A225: (1) Number, (2) value, and (3) weighted average Loan-to-Value (LTV) ratio of mor | B225: 2 | C225: 0.00036456435 | D225: 2 | E225: 1 | F225: 0.00036456435 | G225: 1
A226: Number of tailings impoundments, broken down by MSHA hazard potential | B226: 2 | C226: 0.00036456435 | D226: 2 | E226: 1 | F226: 0.00036456435
A227: Payload fuel economy | B227: 2 | C227: 0.00036456435 | D227: 2 | E227: 1 | F227: 0.00036456435 | G227: 1
A228: Number of incidents of non-compliance with environmental permits, standards, and | B228: 2 | C228: 0.00036456435 | D228: 2 | E228: 1 | F228: 0.00036456435 | G228: 1
A229: (1) Total energy consumed, (2) percentage grid electricity, (3) percentage from | B229: 2 | C229: 0.00036456435 | D229: 2 | E229: 1 | F229: 0.00036456435 | G229: 1
A230: Number of Federal Railroad Administration (FRA) Recommended Violation Defects | B230: 2 | C230: 0.00036456435 | D230: 2 | E230: 1 | F230: 0.00036456435 | G230: 1
A231: (1) Total energy consumed, (2) percentage grid electricity, (3) percentage alter | B231: 2 | C231: 0.00036456435 | D231: 2 | E231: 1 | F231: 0.00036456435 | G231: 1
A232: Discussion of strategy to manage environmental and social risks arising from con | B232: 2 | C232: 0.00036456435 | D232: 2 | E232: 1 | F232: 0.00036456435 | G232: 0
A233: Frequency of internal railway integrity inspections | B233: 2 | C233: 0.00036456435 | D233: 2 | E233: 1 | F233: 0.00036456435 | G233: 1
A234: Amount of recycled and recovered fiber procured | B234: 2 | C234: 0.00036456435 | D234: 2 | E234: 1 | F234: 0.00036456435 | G234: 1
A235: Amount of defect- and safety-related rework costs | B235: 2 | C235: 0.00036456435 | D235: 2 | E235: 1 | F235: 0.00036456435 | G235: 1
A236: Discussion of processes to assess and manage environmental risks associated with | B236: 2 | C236: 0.00036456435 | D236: 2 | E236: 1 | F236: 0.00036456435 | G236: 0
A237: Discussion of processes to manage business ethics risks throughout the value cha | B237: 2 | C237: 0.00036456435 | D237: 2 | E237: 1 | F237: 0.00036456435 | G237: 0
A238: Area of forestland in indigenous land | B238: 2 | C238: 0.00036456435 | D238: 2 | E238: 1 | F238: 0.00036456435 | G238: 1
... A259: Description of approach to ensuring intellectual property (IP) protection | B259: 2 | C259: 0.00036456435 | D259: 2 | E259: 1 | F259: 0.00036456435 | G259: 0
A260: Total weight of mineral processing waste, percentage recycled | B260: 2 | C260: 0.00036456435 | D260: 2 | E260: 1 | F260: 0.00036456435
A261: (1) Number of recalls, (2) number of units recalled, (3) percentage of units rec | B261: 5 | C261: 0.00091141086 | D261: 1 | E261: 0.2 | F261: 0.00018228217 | G261: 1
A262: Sales-weighted fuel efficiency for stationary generators | B262: 10 | C262: 0.0018228217 | D262: 2 | E262: 0.2 | F262: 0.00036456435 | G262: 1
A263: Number of (1) performance issues and (2) service disruptions; (3) total customer | B263: 18 | C263: 0.0032810791 | D263: 4 | E263: 0.222 | F263: 0.00072839956 | G263: 0.944
A264: Estimated carbon dioxide emissions embedded in proved hydrocarbon reserves | B264: 22 | C264: 0.0040102078 | D264: 5 | E264: 0.227 | F264: 0.00091031717 | G264: 1 | I264: 1 | J264: OIL & GAS – EXPLORATION & PRODUCTION
A265: Amount invested in renewable energy, revenue generated by renewable energy sales | B265: 21 | C265: 0.0038279256 | D265: 5 | E265: 0.238 | F265: 0.0009110463 | G265: 1
A266: Revenue from products third-party certified to environmental and/or social susta | B266: 11 | C266: 0.0020051039 | D266: 3 | E266: 0.273 | F266: 0.00054739336 | G266: 1
A267: Number of road accidents and incidents | B267: 11 | C267: 0.0020051039 | D267: 3 | E267: 0.273 | F267: 0.00054739336 | G267: 1 | I267: 3 | J267: AIR FREIGHT & LOGISTICS; ROAD TRANSPORTATION; WASTE MANAGEMENT
A268: Sales-weighted fuel efficiency for non-road equipment | B268: 11 | C268: 0.0020051039 | D268: 3 | E268: 0.273 | F268: 0.00054739336 | G268: 1
A269: Percentage of hydraulic fracturing sites where ground or surface water quality d | B269: 22 | C269: 0.0040102078 | D269: 6 | E269: 0.273 | F269: 0.0010947867 | G269: 1
A270: Number of users whose information is used for secondary purposes | B270: 25 | C270: 0.0045570543 | D270: 7 | E270: 0.28 | F270: 0.0012759752 | G270: 1 | I270: 3 | J270: E-COMMERCE; INTERNET MEDIA & SERVICES; SOFTWARE & IT SERVICES
A271: Approach to development of Emergency Preparedness and Response Plans (EPRPs) for | B271: 7 | C271: 0.0012759752 | D271: 2 | E271: 0.286 | F271: 0.00036492891 | G271: 0
A272: Summary of tailings management systems and governance structure used to monitor | B272: 7 | C272: 0.0012759752 | D272: 2 | E272: 0.286 | F272: 0.00036492891 | G272: 0
A273: (1) Total fuel consumed, (2) percentage natural gas, (3) percentage renewable | B273: 3 | C273: 0.00054684652 | D273: 2 | E273: 0.667 | F273: 0.00036474663 | G273: 1
A274: (1) Voluntary and (2) involuntary turnover rate for restaurant employees | B274: 3 | C274: 0.00054684652 | D274: 2 | E274: 0.667 | F274: 0.00036474663 | G274: 1
A275: Number of (1) acute health-based, (2) non-acute health-based, and (3) non-health | B275: 3 | C275: 0.00054684652 | D275: 2 | E275: 0.667 | F275: 0.00036474663 | G275: 1
A276: Discussion of strategies to manage drinking water contaminants of emerging conce | B276: 3 | C276: 0.00054684652 | D276: 2 | E276: 0.667 | F276: 0.00036474663 | G276: 0
A277: Description of policies and practices relating to behavioral advertising and cus | B277: 3 | C277: 0.00054684652 | D277: 2 | E277: 0.667 | F277: 0.00036474663 | G277: 0
A278: Percentage of drivers classified as independent contractors | B278: 3 | C278: 0.00054684652 | D278: 2 | E278: 0.667 | F278: 0.00036474663 | G278: 1
A279: Percentage of (1) eggs that originated from a cage-free environment and (2) pork | B279: 3 | C279: 0.00054684652 | D279: 2 | E279: 0.667 | F279: 0.00036474663 | G279: 1
A280: (1) Number and (2) volume of sanitary sewer overflows (SSO), (3) percentage of v | B280: 3 | C280: 0.00054684652 | D280: 2 | E280: 0.667 | F280: 0.00036474663 | G280: 1
A281: Volume of recycled water delivered to customers | B281: 3 | C281: 0.00054684652 | D281: 2 | E281: 0.667 | F281: 0.00036474663 | G281: 1
A282: Processor energy efficiency at a system-level for: (1) servers, (2) desktops, an | B282: 3 | C282: 0.00054684652 | D282: 2 | E282: 0.667 | F282: 0.00036474663 | G282: 1
... A299: Percentage of (1) proved and (2) probable reserves in or near indigenous land | B299: 25 | C299: 0.0045570543 | D299: 9 | E299: 0.36 | F299: 0.0016405396 | G299: 1
A300: (1) Voluntary and (2) involuntary turnover rate for in-store employees | B300: 11 | C300: 0.0020051039 | D300: 4 | E300: 0.364 | F300: 0.00072985782 | G300: 1 | I300: 1 | J300: MULTILINE AND SPECIALTY RETAILERS & DISTRIBUTORS
A301: Percentage of eligible products, by revenue, that meet ENERGY STARÂ® criteria | B301: 8 | C301: 0.0014582574 | D301: 3 | E301: 0.375 | F301: 0.00054684652 | G301: 1
A302: Number of government requests to remove content, percentage compliance with requ | B302: 5 | C302: 0.00091141086 | D302: 2 | E302: 0.4 | F302: 0.00036456435 | G302: 1
A303: Percentage of input materials from recycled or remanufactured content | B303: 5 | C303: 0.00091141086 | D303: 2 | E303: 0.4 | F303: 0.00036456435 | G303: 1
A304: Number of incidents of non-compliance associated with air emissions | B304: 5 | C304: 0.00091141086 | D304: 2 | E304: 0.4 | F304: 0.00036456435 | G304: 1
A305: Number of incidents of non-compliance associated with environmental impacts | B305: 5 | C305: 0.00091141086 | D305: 2 | E305: 0.4 | F305: 0.00036456435 | G305: 1
A306: (1) Average hourly wage and (2) percentage of in-store and distribution center e | B306: 5 | C306: 0.00091141086 | D306: 2 | E306: 0.4 | F306: 0.00036456435 | G306: 1
A307: (1) Fleet fuel consumed, (2) percentage natural gas, (3) percentage renewable | B307: 5 | C307: 0.00091141086 | D307: 2 | E307: 0.4 | F307: 0.00036456435 | G307: 1
A308: Percentage of alternative fuel vehicles in fleet | B308: 5 | C308: 0.00091141086 | D308: 2 | E308: 0.4 | F308: 0.00036456435 | G308: 1
A309: Percentage of products sold that are recyclable | B309: 5 | C309: 0.00091141086 | D309: 2 | E309: 0.4 | F309: 0.00036456435 | G309: 1
A310: Amount of material (1) recycled, (2) composted, and (3) processed as waste-to-en | B310: 5 | C310: 0.00091141086 | D310: 2 | E310: 0.4 | F310: 0.00036456435 | G310: 1
A311: Number of mediation and arbitration cases associated with professional integrity | B311: 5 | C311: 0.00091141086 | D311: 2 | E311: 0.4 | F311: 0.00036456435 | G311: 1
A312: Tier 1 suppliersâ€™ (1) non-conformance rate with the RBA Validated Audit Process | B312: 4 | C312: 0.00072912869 | D312: 3 | E312: 0.75 | F312: 0.00054684652 | G312: 1
... A346: Total weight of tailings produced | B346: 3 | C346: 0.00054684652 | D346: 3 | E346: 1 | F346: 0.00054684652 | G346: 1
A347: Total weight of tailings waste, percentage recycled | B347: 3 | C347: 0.00054684652 | D347: 3 | E347: 1 | F347: 0.00054684652
A348: Amount of electronic waste collected, percentage recovered through recycling | B348: 5 | C348: 0.00091141086 | D348: 2 | E348: 0.4 | F348: 0.00036456435 | G348: 1
A349: (1) Number and (2) amount of past due and nonaccrual loans qualified to programs | B349: 10 | C349: 0.0018228217 | D349: 4 | E349: 0.4 | F349: 0.00072912869 | G349: 1
A350: Safety Measurement System BASIC percentiles for: (1) Unsafe Driving, (2) Hours-o | B350: 10 | C350: 0.0018228217 | D350: 4 | E350: 0.4 | F350: 0.00072912869 | G350: 1
A351: Percentage of (1) entity's facilities and (2) Tier I suppliers' facilities parti | B351: 20 | C351: 0.0036456435 | D351: 8 | E351: 0.4 | F351: 0.0014582574 | G351: 1
A352: Process Safety Event (PSE) rates for Loss of Primary Containment (LOPC) of great | B352: 26 | C352: 0.0047393365 | D352: 11 | E352: 0.423 | F352: 0.0020047393 | G352: 1
A353: Net premiums written related to energy efficiency and low carbon technology | B353: 7 | C353: 0.0012759752 | D353: 3 | E353: 0.429 | F353: 0.00054739336 | G353: 1
A354: Number and duration of strikes and lockouts | B354: 7 | C354: 0.0012759752 | D354: 3 | E354: 0.429 | F354: 0.00054739336 | G354: 1
A355: Percentage change in: (1) average list price and (2) average net price across U. | B355: 7 | C355: 0.0012759752 | D355: 3 | E355: 0.429 | F355: 0.00054739336 | G355: 1
A356: Complaints-to-claims ratio | B356: 9 | C356: 0.0016405396 | D356: 4 | E356: 0.444 | F356: 0.00072839956 | G356: 1
A357: Customer retention rate | B357: 9 | C357: 0.0016405396 | D357: 4 | E357: 0.444 | F357: 0.00072839956 | G357: 1
A358: Revenue from renewable energy-related and energy efficiency-related products | B358: 9 | C358: 0.0016405396 | D358: 4 | E358: 0.444 | F358: 0.00072839956 | G358: 1
A359: Total fair value of securities lending collateral assets | B359: 9 | C359: 0.0016405396 | D359: 4 | E359: 0.444 | F359: 0.00072839956 | G359: 1
... A412: Terrestrial acreage disturbed, percentage of impacted area restored | B412: 17 | C412: 0.0030987969 | D412: 10 | E412: 0.588 | F412: 0.0018220926 | G412: 1
A413: Total amount of monetary losses as a result of legal proceedings associated with | B413: 351 | C413: 0.063981043 | D413: 209 | E413: 0.595 | F413: 0.03806872 | G413: 1 | I413: Higher than mean
A414: Percentage of variable remuneration of Material Risk Takers (MRTs) to which malu | B414: 5 | C414: 0.00091141086 | D414: 3 | E414: 0.6 | F414: 0.00054684652 | G414: 1
A415: Percentage of total remuneration that is variable for Material Risk Takers (MRTs | B415: 5 | C415: 0.00091141086 | D415: 3 | E415: 0.6 | F415: 0.00054684652 | G415: 1
A416: Average refrigerant emissions rate | B416: 5 | C416: 0.00091141086 | D416: 3 | E416: 0.6 | F416: 0.00054684652 | G416: 1
A417: Description of how proximity and access to infrastructure, services, and economi | B417: 5 | C417: 0.00091141086 | D417: 3 | E417: 0.6 | F417: 0.00054684652 | G417: 0
A418: (1) Number and (2) total value of investments and loans incorporating integratio | B418: 5 | C418: 0.00091141086 | D418: 3 | E418: 0.6 | F418: 0.00054684652 | G418: 1
A419: Discussion of policies around supervision, control, and validation of tradersâ€™ p | B419: 5 | C419: 0.00091141086 | D419: 3 | E419: 0.6 | F419: 0.00054684652 | G419: 0
A420: Revenue from products third-party certified to environmental or social sustainab | B420: 5 | C420: 0.00091141086 | D420: 3 | E420: 0.6 | F420: 0.00054684652 | G420: 1
A421: (1) Voluntary and (2) involuntary turnover rate for all employees | B421: 5 | C421: 0.00091141086 | D421: 3 | E421: 0.6 | F421: 0.00054684652 | G421: 1
A422: Total aluminum purchased, percentage from certified sources | B422: 5 | C422: 0.00091141086 | D422: 3 | E422: 0.6 | F422: 0.00054684652 | G422: 1
A423: Total wood fiber procured, percentage from certified sources | B423: 5 | C423: 0.00091141086 | D423: 3 | E423: 0.6 | F423: 0.00054684652 | G423: 1
A424: High-risk food safety violation rate | B424: 5 | C424: 0.00091141086 | D424: 3 | E424: 0.6 | F424: 0.00054684652 | G424: 1
A425: Percentage of electric load served by smart grid technology | B425: 10 | C425: 0.0018228217 | D425: 6 | E425: 0.6 | F425: 0.001093693 | G425: 1
... A597: Percentage of ingredients sourced from Tier 1 supplier facilities certified to a | B597: 12 | C597: 0.0021873861 | D597: 12 | E597: 1 | F597: 0.0021873861 | G597: 1
A598: Average disturbed acreage per (1) oil and (2) gas well site | B598: 0 | C598: 0 | D598: 0 | G598: 1 | H598: Not Applicable
A599: Net exposure to written credit derivatives | B599: 0 | C599: 0 | D599: 0 | G599: 1 | H599: Not Applicable
A600: Percentage of engines in service that meet Tier 4 compliance for non-road diesel | B600: 0 | C600: 0 | D600: 0 | G600: 1 | H600: Not Applicable
A601: Total exposure to securities financing transactions | B601: 0 | C601: 0 | D601: 0 | G601: 1 | H601: Not Applicable
A602: Total | B602: 5486 | C602: 1

Sheet Consumer exposure
A1: Main Industry | B1: SASB Industry | C1: ind_code | D1: Corresponding IO Industry | E1: B2C
A2: Consumer Goods | B2: APPAREL, ACCESSORIES & FOOTWEAR | C2: CG-AA | D2: Apparel and leather and allied products | E2: 1.8850639
A3: Consumer Goods | B3: APPLIANCE MANUFACTURING | C3: CG-AM | D3: Electrical equipment, appliances, and components | E3: 0.79353177
A4: Consumer Goods | B4: BUILDING PRODUCTS & FURNISHINGS | C4: CG-BF | D4: Miscellaneous manufacturing | E4: 1.2913113
A5: Consumer Goods | B5: E-COMMERCE | C5: CG-EC | D5: Miscellaneous manufacturing | E5: 1.2913113
A6: Consumer Goods | B6: HOUSEHOLD & PERSONAL PRODUCTS | C6: CG-HP | D6: Housing | E6: 1.9812882
A7: Consumer Goods | B7: MULTILINE AND SPECIALTY RETAILERS & DISTRIBUTORS | C7: CG-MR | D7: Miscellaneous manufacturing | E7: 1.2913113
A8: Consumer Goods | B8: TOYS & SPORTING GOODS | C8: CG-TS | D8: Miscellaneous manufacturing | E8: 1.2913113
A9: Extractives & Minerals | B9: CONSTRUCTION MATERIALS | C9: EM-CM | D9: Nonmetallic mineral products | E9: 0.20018522
A10: Extractives & Minerals | B10: COAL OPERATIONS | C10: EM-CO | D10: Mining, except oil and gas | E10: 0.02556211
A11: Extractives & Minerals | B11: OIL & GAS - EXPLORATION & PRODUCTION | C11: EM-EP | D11: Oil and gas extraction | E11: 0.09884717
A12: Extractives & Minerals | B12: IRON & STEEL PRODUCERS | C12: EM-IS | D12: Mining, except oil and gas | E12: 0.02556211
A13: Extractives & Minerals | B13: OIL & GAS - MIDSTREAM | C13: EM-MD | D13: Oil and gas extraction | E13: 0.09884717
... A78: Transportation | B78: ROAD TRANSPORTATION | C78: TR-RO | D78: Transit and ground passenger transportation | E78: 0.87160411
